Workbook

Sheet 📞 Call Tracker
A1: AccountNumber | B1: Associate | C1: DateCalled | D1: VM | E1: Outcome | F1: Notes | G1: Priority | H1: CustomerName | I1: City | J1: RatePlan | K1: MEPStatus | L1: Issue
A2: 5411325149 | B2: Michelle | C2: 46025 | D2: YES | G2: Called | H2: Coudriet, Lise | I2: Goodyear | J2: R-BASICL | K2: Not on Best Plan | L2: Will cause hardships
A3: 5372102528 | B3: Michelle | C3: 46046 | D3: NO | E3: Utility Assistance | G3: Called | H3: Price, Shannon | I3: Phoenix | J3: R3-47 | K3: Not on Best Plan | L3: Form letter
A4: 4300170000 | B4: Joaquin | C4: 46046 | D4: YES | F4: STOPPED S-A 2025-06-04 to 2025-11-03 | G4: Called | H4: Bryant, Shelby | I4: Phoenix | J4: RTOUE47 | K4: Not on Best Plan | L4: Opposed, unfair burden on families and seniors
A5: 0356005964 | B5: Joaquin | C5: 46046 | D5: NO | E5: General Education | F5: OFFER OPTION TO LOWER BILL | G5: Called | H5: Santoyo, Ashlee | I5: Surprise | J5: RTOUE47 | K5: Not on Best Plan | L5: Form letter
A6: 6846061000 | B6: Joaquin | C6: 46039 | D6: YES | G6: Called | H6: McCloud, Jason | I6: Surprise | J6: RTOUE47 | K6: Not on Best Plan | L6: Unchecked greed
A7: 0902311000 | B7: Joaquin | C7: 46025 | D7: YES | F7: LEFT VOICE MAIL | G7: Called | H7: Inman, Bonnie | I7: Phoenix | J7: RTOUE47 | K7: Not on Best Plan | L7: Form letter
A8: 4528501000 | B8: Joaquin | C8: 46025 | F8: LEFT VOICE MAIL | G8: Called | H8: Josselyn, Anne | I8: Sun City | J8: R-BASIC | K8: Not on Best Plan | L8: Opposed
A9: 2060349043 | B9: Joaquin | C9: 46025 | D9: NO | F9: VOICE MAIL WAS FULL | G9: Called | H9: Ramos, Mercedes | I9: Yuma | J9: RCPw/R3-47 | K9: Not on Best Plan | L9: Extremely expensive
A10: 4573855715 | B10: Joaquin | C10: 45997 | D10: YES | F10: NO E3 ON ACCT IS ON PAYMENT ARRANGEMENT | G10: Called | H10: Vandenberg, Taylor | I10: Phoenix | J10: RTOUE47 | K10: Not on Best Plan | L10: Opposed-Terrible idea for Arizonans
A11: 9340701000 | B11: Joaquin | C11: 46039 | D11: YES | G11: Called | H11: Pablo, Jerome | I11: Buckeye | J11: RCPw/RTOUE47 | K11: Not on Best Plan | L11: Power is already expensive
A12: 5596059869 | B12: Joaquin | C12: 46032 | E12: Other (fill in) | F12: CALLER HUNG UP | G12: Called | H12: Youngker, Virginia | I12: Scottsdale | J12: RTOUE47 | K12: Not on Best Plan | L12: Form Letter: Enough is enough! You must reject the latest 14% rate hikes by APS and TEP
A13: 6013821000 | B13: Joaquin | C13: 46032 | D13: YES | F13: BETTER RATE FIXXED ENERGY PLAN | G13: Called | H13: Haden, Scott | I13: Phoenix | J13: RTOUE47 | K13: Not on Best Plan | L13: Form Letter: Enough is enough! You must reject the latest 14% rate hikes by APS and TEP
A14: 1205900735 | B14: Joaquin | C14: 46032 | D14: YES | F14: LEFT VOICE MESSAGE | G14: Called | H14: Summons, Miranda | I14: Phoenix | J14: R-BASIC | K14: Not on Best Plan | L14: I am against the rate increase
A15: 1039090000 | B15: Joaquin | C15: 46032 | D15: YES | F15: LEFT VOICE MESSAGE | G15: Called | H15: Byman, Rachel | I15: Phoenix | J15: R3-47 | K15: Not on Best Plan | L15: Form Letter: Enough is enough! You must reject the latest 14% rate hikes by APS and TEP
A16: 6003957639 | B16: Joaquin | C16: 46032 | D16: YES | F16: BETTER PLAN TIME OF WITH DEMAND | G16: Called | H16: Hernandez, Maria | I16: Youngtown | J16: RTOUE47 | K16: Not on Best Plan | L16: Form Letter: Enough is enough! You must reject the latest 14% rate hikes by APS and TEP
A17: 3304816868 | B17: Joaquin | C17: 46032 | E17: Rate Change | F17: ED ON PLANS TO HELP SAVE & REBATE INFO | G17: Called | H17: Curds, Diana | I17: Phoenix | J17: RTOUE47 | K17: Not on Best Plan | L17: I oppose the rate hike. Bills are high enough. No one can survive paying $650.
A18: 0509660000 | B18: Joaquin | C18: 46018 | D18: NO | E18: General Education | G18: Called | H18: Posey, Michael | I18: Buckeye | J18: RTOUE47 | K18: Not on Best Plan | L18: Form Letter: Enough is enough! You must reject the latest 14% rate hikes by APS e TEP
A19: 7401033818 | G19: P1 | H19: Cearns, Katharine | I19: Yuma | J19: R-2 | K19: Not on Best Plan | L19: Form Letter: Enough is enough! You must reject the latest 14% rate hikes by APS e TEP
A20: 2947560540 | G20: P1 | H20: Apolinar, Alexia | I20: Goodyear | J20: RCPw/TOUE47 | K20: Not on Best Plan | L20: Oppose -rate was just increased less than 2 years ago
A21: 3110727023 | G21: P1 | H21: Downs, Jodi | I21: Glendale | J21: R-BASIC | K21: Not on Best Plan | L21: On a budget and already working 2 jobs to make ends meet, the price hike is nothing but greed.
A22: 8998382174 | G22: P1 | H22: Andujar, Elizabeth | I22: Phoenix | J22: R3-47 | K22: Not on Best Plan | L22: I believe that aps should lower the cost because not all of us has the funds to keep paying a lot of money
A23: 7201057343 | G23: P1 | H23: Arends, TeNisha | I23: Surprise | J23: R3-47 | K23: Not on Best Plan | L23: We have the sun at our disposal. Why isn't APS taking advantage of that to help the consumers that need their services
A24: 3323516971 | G24: P1 | H24: Bugenski, Jennifer | I24: Flagstaff | J24: RTOUE47 | K24: Not on Best Plan | L24: I'm against the rate hike we are expensive enough
A25: 4067480384 | G25: P1 | H25: King, Melvinna | I25: Avondale | J25: 0 | K25: Not on Best Plan | L25: it's time to humble oneself because God is coming to humble those who feel they are in control
A26: 0339264588 | G26: P1 | H26: Gajon, Anaisabel | I26: Yuma | J26: RTOUE47 | K26: Not on Best Plan | L26: Everything is too expensive. It is impossible to afford electricity in this heat as is,
A27: 9532631000 | G27: P1 | H27: Valladares, Rosalva | I27: Phoenix | J27: RTOUE47 | K27: Not on Best Plan | L27: If APS really cares about its customers look into blocking these data centers from moving to Arizona
A28: 0310740000 | G28: P1 | H28: Bean, Jodi | I28: Wittmann | J28: RTOUE47 | K28: Not on Best Plan | L28: I dent think APS needs another 14% rate hike people are barely making ends meet.
A29: 3049940000 | B29: Michelle | C29: 46067 | D29: YES | G29: Called | H29: Rizzi, Carol | I29: Unknown | J29: R-XS | K29: Not on Best Plan | L29: Opposed
A30: 2779220471 | B30: Michelle | C30: 46060 | D30: YES | F30: SOLAR ACCT | G30: Called | H30: Charapata, Maxwell | I30: Phoenix | J30: RTOUE47 | K30: Not on Best Plan | L30: Opposed
A31: 6635023227 | B31: Michelle | C31: 46032 | D31: NO | E31: Other (fill in) | F31: SOLAR ACCT | G31: Called | H31: Howell, Chris | I31: Surprise | J31: RTOUE47 | K31: Not on Best Plan | L31: Form letter
A32: 6924836428 | B32: Michelle | C32: 46053 | D32: NO | E32: General Education | G32: Called | H32: Scharroo, George | I32: Phoenix | J32: R3-47 | K32: Not on Best Plan | L32: Opposed
A33: 7035930772 | B33: Michelle | C33: 46053 | D33: YES | G33: Called | H33: Farr, Amanda | I33: Phoenix | J33: RTOUE47 | K33: Not on Best Plan | L33: Form letter
A34: 4659820000 | B34: Joaquin | C34: 46018 | D34: YES | G34: Called | H34: Norton, Colin | I34: Phoenix | J34: RTOUE47 | K34: Not on Best Plan | L34: Form letter
A35: 7477798096 | B35: Michelle | C35: 46053 | D35: YES | G35: Called | H35: Bergstrom, Shailey | I35: Phoenix | J35: R-BASICL | K35: Not on Best Plan | L35: Apt electric bill is as high as her parent home in Tucson
A36: 2605161000 | B36: Michelle | C36: 46053 | D36: YES | F36: LEFT VM | G36: Called | H36: Rogers, Richard | I36: Flagstaff | J36: R-BASIC | K36: Not on Best Plan | L36: Opposed
A37: 1560131000 | B37: Joaquin | C37: 46018 | D37: NO | G37: Called | H37: Gutierrez, Francisco | I37: Yuma | J37: RTOUE47 | K37: Not on Best Plan | L37: Form letter
A38: 4557041000 | B38: Michelle | C38: 46032 | D38: NO | E38: General Education | F38: SOLAR ACCT | G38: Called | H38: Mohapatra, Sangram | I38: Peoria | J38: RTOUE47 | K38: Not on Best Plan | L38: Form letter
A39: 7001761000 | B39: Michelle | C39: 46039 | D39: YES | F39: SOLAR ACCT | G39: Called | H39: Gurram , Tanooj Kumar Reddy | I39: Peoria | J39: RTOUE47 | K39: Not on Best Plan | L39: Form letter
A40: 5849875191 | B40: Michelle | C40: 46074 | D40: NO | E40: General Education | G40: Called | H40: Crowley, Kendell | I40: Phoenix | J40: RTOUE47 | K40: Not on Best Plan | L40: Form letter
A41: 4014511000 | B41: Michelle | C41: 46032 | D41: YES | F41: SOLAR ACCT | G41: Called | H41: Schroeder, John | I41: Goodyear | J41: RTOUE47 | K41: Not on Best Plan | L41: People are suffering financially
A42: 5131511000 | B42: Michelle | C42: 46018 | D42: NO | G42: Called | H42: Messmer, Catherine | I42: Goodyear | J42: RTOUE47 | K42: Not on Best Plan | L42: Widow on limited income
A43: 0487982450 | B43: Michelle | C43: 46025 | D43: YES | G43: Called | H43: Pranesh, Vinay | I43: Peoria | J43: R3-47 | K43: Not on Best Plan | L43: Form letter
A44: 9875751000 | B44: Joaquin | C44: 46053 | D44: NO | E44: General Education | F44: SOLAR ACCT | G44: Called | H44: Kukkapalli, Vasu | I44: Phoenix | J44: RCPw/R3-47 | K44: Not on Best Plan | L44: Opposed
A45: 6079940000 | B45: Joaquin | C45: 46053 | D45: NO | E45: General Education | F45: WILL CB TO MAKE CHANGES | G45: Called | H45: Gottipati, Srinivasa | I45: Peoria | J45: REV47 | K45: Not on Best Plan | L45: Opposed
A46: 9757441000 | B46: Joaquin | C46: 46060 | D46: NO | F46: SOLAR ACCT | G46: Called | H46: Kuppuswamy, Balaji | I46: Peoria | J46: REV47 | K46: Not on Best Plan | L46: Form letter
A47: 7502531000 | B47: Michelle | C47: 46039 | D47: YES | G47: Called | H47: Ziller, Chris | I47: Phoenix | J47: RTOUE47 | K47: Not on Best Plan | L47: Form letter
A48: 0987457107 | B48: Michelle | C48: 46039 | D48: YES | G48: Called | H48: Arrowsmith, Kelsey | I48: Phoenix | J48: RTOUE47 | K48: Not on Best Plan | L48: Form letter
A49: 1316621000 | B49: Michelle | C49: 46039 | D49: YES | G49: Called | H49: Ahmad, Ammara | I49: Goodyear | J49: R-BASIC | K49: Not on Best Plan | L49: Opposed
A50: 4026025798 | B50: Michelle | C50: 46039 | D50: YES | G50: Called | H50: Rauschkolb, Phillip | I50: Goodyear | J50: R-BASICL | K50: Not on Best Plan | L50: Form letter
A51: 1842320000 | B51: Joaquin | C51: 46060 | D51: YES | G51: Called | H51: Arpaia, Mary | I51: Avondale | J51: R-BASIC | K51: Not on Best Plan | L51: Opposed
A52: 3553261000 | B52: Michelle | C52: 46039 | D52: NO | E52: General Education | G52: Called | H52: Erra, Mohan | I52: Peoria | J52: RTOUE47 | K52: Not on Best Plan | L52: Form letter
A53: 5784101000 | B53: Michelle | C53: 46060 | D53: YES | G53: Called | H53: Underwood, Sarah | I53: Litchfield Park | J53: R-BASICL | K53: Not on Best Plan | L53: Opposed
A54: 3862538912 | B54: Michelle | C54: 46046 | D54: YES | G54: Called | H54: Cuadras, JoVon | I54: Phoenix | J54: RTOUE47 | K54: Not on Best Plan | L54: Form letter
A55: 0974119043 | B55: Michelle | C55: 46046 | D55: YES | G55: Called | H55: Monteleone, Kathleen | I55: Goodyear | J55: RTOUE47 | K55: Not on Best Plan | L55: Opposed/will cause hardships
A56: 8849042993 | B56: Michelle | C56: 46046 | D56: YES | G56: Called | H56: Pahuja, Himanshu | I56: Peoria | J56: RTOUE47 | K56: Not on Best Plan | L56: Form letter
A57: 4095200000 | B57: Michelle | C57: 46046 | D57: NO | G57: Called | H57: Clow, Richard | I57: Goodyear | J57: RTOUE47 | K57: Not on Best Plan | L57: Opposed
A58: 7835950000 | B58: Michelle | C58: 46046 | D58: NO | E58: Rate Change | G58: Called | H58: Tremblay, Michelle | I58: Phoenix | J58: RTOUE47 | K58: Not on Best Plan | L58: Opposed
A59: 4997806847 | B59: Michelle | C59: 46046 | D59: NO | F59: UNHAPPY WITH THE RATE INCREASE CASE | G59: Called | H59: Marshall, Allen | I59: Goodyear | J59: R-BASICL | K59: Not on Best Plan | L59: Opposed
A60: 2166343167 | B60: Michelle | C60: 46046 | D60: YES | G60: Called | H60: Robinson, Carter | I60: Glendale | J60: R-BASICL | K60: Not on Best Plan | L60: Opposed, usage is not high, it is normal in AZ extreme climate
A61: 6907731000 | B61: Joaquin | C61: 46060 | D61: YES | F61: LEFT V-M | G61: Called | H61: Woehl, Timothy | I61: Scottsdale | J61: RTOUE47 | K61: Not on Best Plan | L61: Opposed
A62: 0555026441 | B62: Michelle | C62: 46060 | D62: YES | G62: Called | H62: Delaney, Amy | I62: Phoenix | J62: RTOUE47 | K62: Not on Best Plan | L62: Form letter
A63: 3305713016 | B63: Michelle | C63: 46046 | D63: NO | F63: NUMBER DISCONNECTED | G63: Called | H63: Votypka, Lindsay | I63: Scottsdale | J63: RTOUE47 | K63: Not on Best Plan | L63: Form letter
A64: 1687826451 | B64: Michelle | C64: 46060 | D64: NO | F64: COULD NOT LEAVE MESSAGE, VM NOT SET UP | G64: Called | H64: Sundarachar, Hema | I64: Tempe | J64: RTOUE47 | K64: Not on Best Plan | L64: Form letter
A65: 5718650660 | B65: Michelle | C65: 46046 | D65: YES | G65: Called | H65: Laszczak, Lauren | I65: Phoenix | J65: RTOUE47 | K65: Not on Best Plan | L65: Form letter
A66: 9800380431 | B66: Michelle | C66: 46060 | D66: YES | G66: Called | H66: Blocker, Nicholas | I66: Surprise | J66: RTOUE47 | K66: Not on Best Plan | L66: Form letter
A67: 0998552497 | B67: Michelle | C67: 46053 | D67: YES | G67: Called | H67: Sedillo, Sidney | I67: Chandler | J67: R3-47 | K67: Not on Best Plan | L67: Form letter
A68: 9660984623 | B68: Michelle | C68: 46053 | D68: YES | G68: Called | H68: Torres, Daniel | I68: Phoenix | J68: RTOUE47 | K68: Not on Best Plan | L68: Form letter
A69: 5278430000 | B69: Michelle | C69: 46053 | D69: YES | G69: Called | H69: Thomas, Shaun | I69: Payson | J69: RTOUE47 | K69: Not on Best Plan | L69: Opposed
A70: 6940323949 | B70: Michelle | C70: 46053 | D70: YES | G70: Called | H70: Berry, Mason | I70: Phoenix | J70: RTOUE47 | K70: Not on Best Plan | L70: Form letter
A71: 2290331000 | B71: Michelle | C71: 46053 | D71: YES | G71: Called | H71: Ficarra, Gregory | I71: Glendale | J71: RTOUE47 | K71: Not on Best Plan | L71: Form letter
A72: 4333270000 | B72: Joaquin | C72: 46053 | D72: NO | F72: NO GOOD CBR# ON FILE | G72: Called | H72: Ramos, Pedro | I72: Yuma | J72: R-BASICL | K72: Not on Best Plan | L72: Senior/Fixed Income
A73: 4789794091 | B73: Joaquin | C73: 46053 | D73: YES | F73: LEFT V-M | G73: Called | H73: Cross, Katie | I73: Tempe | J73: R-BASIC | K73: Not on Best Plan | L73: Form letter
A74: 5582530000 | B74: Joaquin | C74: 46053 | D74: NO | E74: General Education | F74: NOT FOR THE RATE CASE PROPOSAL | G74: Called | H74: Matelski, Heather | I74: Tempe | J74: RTOUE47 | K74: Not on Best Plan | L74: Opposed
A75: 2697623904 | B75: Joaquin | C75: 46053 | D75: NO | E75: General Education | G75: Called | H75: Testo, George | I75: Flagstaff | J75: RTOUE47 | K75: Not on Best Plan | L75: Opposed
A76: 7036097429 | B76: Joaquin | C76: 46060 | F76: LEFT V-M | G76: Called | H76: Brunetti, Isabel | I76: Phoenix | J76: R3-47 | K76: Not on Best Plan | L76: Unfair
A77: 0947385737 | B77: Joaquin | C77: 46053 | D77: YES | F77: LEFT V-M | G77: Called | H77: Pera, Natalie | I77: Phoenix | J77: RTOUE47 | K77: Not on Best Plan | L77: Form letter
A78: 0189241000 | B78: Joaquin | C78: 46053 | D78: YES | F78: LEFT V-M | G78: Called | H78: Kennedy, Robert | I78: Phoenix | J78: R3-47 | K78: Not on Best Plan | L78: Opposed
A79: 5976850000 | B79: Joaquin | C79: 46053 | D79: NO | E79: Rate Change | F79: RATE CHANGE NEXT BILL DATE 2/21/26 | G79: Called | H79: Healey, Tyler | I79: Phoenix | J79: RTOUE47 | K79: Not on Best Plan | L79: Enough with the rate hikes
A80: 9504901000 | B80: Joaquin | C80: 46053 | D80: YES | F80: LEFT V-M | G80: Called | H80: Abitz, Zachary | I80: Surprise | J80: RTOUE47 | K80: Not on Best Plan | L80: Enough is enough
A81: 9467156300 | B81: Joaquin | C81: 46046 | D81: NO | F81: NO V-M OPTION | G81: Called | H81: Henderson, David | I81: Scottsdale | J81: RTOUE47 | K81: Not on Best Plan | L81: Form letter
A82: 1876163520 | B82: Joaquin | C82: 46060 | D82: NO | E82: E3/E4 | F82: SOLAR ACT | G82: Called | H82: Siddavatam, Govardhan Reddy | I82: Peoria | J82: RTOUE47 | K82: Not on Best Plan | L82: Opposed
A83: 0901196121 | B83: Joaquin | C83: 46046 | D83: NO | E83: Rate Change | F83: PROVIDED TIPS LINE #S | G83: Called | H83: Zohn, Ethan | I83: Phoenix | J83: RTOUE47 | K83: Not on Best Plan | L83: Not good
A84: 0363441000 | B84: Joaquin | C84: 46046 | D84: YES | G84: Called | H84: Royster, Aaron | I84: Tempe | J84: RTOUE47 | K84: Not on Best Plan | L84: Form letter
A85: 9986232210 | B85: Joaquin | C85: 46046 | D85: NO | F85: NO V-M OPTION | G85: Called | H85: Macagni, Christopher | I85: Peoria | J85: RTOUE47 | K85: Not on Best Plan | L85: Form letter
A86: 4586872061 | B86: Joaquin | C86: 46046 | D86: YES | F86: LEFT V-M | G86: Called | H86: Heiser, Morgan | I86: Phoenix | J86: R3-47 | K86: Not on Best Plan | L86: Opposed
A87: 5137610000 | B87: Joaquin | C87: 46046 | D87: YES | F87: LEFT V-M | G87: Called | H87: Phipps, Michelle | I87: Casa Grande | J87: RTOUE47 | K87: Not on Best Plan | L87: Opposed, out of control
A88: 5161972296 | B88: Joaquin | C88: 46046 | D88: YES | F88: LEFT V-M | G88: Called | H88: Smith, Jordon | I88: Phoenix | J88: R-BASICL | K88: Not on Best Plan | L88: Opposed
A89: 6017698985 | B89: Joaquin | C89: 46060 | D89: YES | F89: LEFT V-M | G89: Called | H89: Sommer, Bryce | I89: Scottsdale | J89: R-BASIC | K89: Not on Best Plan | L89: Horrible policy
A90: 6228956660 | B90: Joaquin | C90: 46060 | D90: NO | F90: CORE HUNG UP CALL | G90: Called | H90: Glass, Samuel | I90: Surprise | J90: RTOUE47 | K90: Not on Best Plan | L90: Opposed, unjust and wrong
A91: 9746250000 | B91: Joaquin | C91: 46046 | D91: YES | F91: LEFT V-M | G91: Called | H91: Pham, Anthony | I91: Peoria | J91: R-BASICL | K91: Not on Best Plan | L91: Opposed (included news story of indoor heat deaths)
A92: 4022467820 | B92: Joaquin | C92: 46046 | D92: YES | F92: LEFT V-M | G92: Called | H92: Roberts, Stefan | I92: Glendale | J92: RTOUE47 | K92: Not on Best Plan | L92: Form letter
A93: 3852813845 | B93: Joaquin | C93: 46060 | D93: YES | F93: LEFT V-M | G93: Called | H93: Rascon, Diego | I93: Phoenix | J93: R-BASICL | K93: Not on Best Plan | L93: Form letter
A94: 7042751772 | B94: Joaquin | C94: 46046 | D94: YES | F94: LEFT V-M | G94: Called | H94: De Simone, Andre | I94: Phoenix | J94: RTOUE47 | K94: Not on Best Plan | L94: Form letter
A95: 4096651000 | B95: Joaquin | C95: 46046 | D95: YES | F95: LEFT V-M | G95: Called | H95: McWilliams, Jesse | I95: Cave Creek | J95: RTOUE47 | K95: Not on Best Plan | L95: Form letter
A96: 5127241787 | B96: Joaquin | C96: 46060 | D96: NO | E96: General Education | G96: Called | H96: Perelman, Dale | I96: Scottsdale | J96: R3-47 | K96: Not on Best Plan | L96: Increase will be very onerous for those on fixed income
A97: 4864054917 | B97: Joaquin | C97: 46046 | D97: YES | F97: LEFT V-M | G97: Called | H97: Leal, Steven | I97: Phoenix | J97: R-BASIC | K97: Not on Best Plan | L97: Opposed
A98: 0228851000 | B98: Joaquin | C98: 46046 | D98: NO | E98: E3/E4 | F98: MAILED OUT E3 | G98: Called | H98: Lakshmipathy, Arunkumar | I98: Peoria | J98: RCPw/RTOUE47 | K98: Not on Best Plan | L98: Form letter
A99: 7370951000 | B99: Joaquin | C99: 46060 | D99: NO | F99: NO VOICE MAIL OPTION | G99: Called | H99: Copeland, Joen | I99: Phoenix | J99: R-BASICL | K99: Not on Best Plan | L99: Opposed
A100: 5604121000 | B100: Joaquin | C100: 46046 | D100: YES | F100: LEFT V-M | G100: Called | H100: Bracken, Daniel | I100: Scottsdale | J100: R-BASICL | K100: Not on Best Plan | L100: Form letter
...

Sheet Summary
B2: RATE CASE OUTREACH — EXECUTIVE SUMMARY
B4: Total Docketed | C4: Callable | D4: Contacted | E4: Remaining | F4: Progress | G4: VMs Left
B5: =COUNTA('Docketed Comments'!B2:B1949) -> 1946 | C5: {=SUMPRODUCT(('Call Queue'!H2:H1310<>"")*1)} -> 1309 | D5: =COUNTA('📞 Call Tracker'!B2:B2000) -> 399 | E5: =C5-D5 -> 910 | F5: =D5/C5 -> 0.30481283 | G5: =COUNTIF('📞 Call Tracker'!D2:D2000,"YES") -> 244
B6: Comments Filed | C6: Valid Customers | D6: Calls Made | E6: To Contact | F6: Completion | G6: Voicemails
B8: CUSTOMER INSIGHTS
B9: Not on MEP Left | C9: Payoff Balance Left | D9: On MEP | E9: Avg Calls/Week | F9: Unable to Locate | G9: Spoke With
B10: =COUNTIFS('Call Queue'!V2:V1310,"❌ Not on Best Plan")-COUNTIFS('Call Queue'!V2:V1310,"❌ Not on Best Plan",'Call Queue'!X2:X1310,">0") -> 229 | C10: =COUNTIFS('Call Queue'!N2:N1310,"<>No",'Call Queue'!N2:N1310,"<>")-COUNTIFS('Call Queue'!N2:N1310,"<>No",'Call Queue'!N2:N1310,"<>",'Call Queue'!X2:X1310,">0") -> 58 | D10: =COUNTIFS('Call Queue'!V2:V1310,"✅ On Best Plan")+COUNTIFS('Call Queue'!V2:V1310,"❄ Frozen Rate") -> 936 | E10: =IFERROR(ROUND(D5/MAX(1,(NETWORKDAYS(MIN('📞 Call Tracker'!C:C),TODAY())/5)),1),"-") -> 31.7 | F10: =COUNTIF('Docketed Comments'!H2:H1949,"Unable to Locate Acct")+COUNTBLANK('Docketed Comments'!H2:H1949) -> 478 | G10: =COUNTIF('📞 Call Tracker'!D2:D2000,"NO") -> 133
B11: =COUNTIFS('Call Queue'!V2:V1310,"❌ Not on Best Plan",'Call Queue'!X2:X1310,">0")&" of "&COUNTIFS('Call Queue'!V2:V1310,"❌ Not on Best Plan")&" contacted" -> 113 of 342 contacted | C11: =COUNTIFS('Call Queue'!N2:N1310,"<>No",'Call Queue'!N2:N1310,"<>",'Call Queue'!X2:X1310,">0")&" of "&COUNTIFS('Call Queue'!N2:N1310,"<>No",'Call Queue'!N2:N1310,"<>")&" contacted" -> 36 of 94 contacted | D11: Currently Enrolled | E11: Per Week | F11: Removed from Queue | G11: Conversations
B13: WEEKLY PERFORMANCE
B14: Week Of | C14: Total Calls | D14: VMs | E14: Contacts | F14: Michelle | G14: Joaquin
B15: {=IFERROR(_xlfn._xlws.SORT(_xlfn.UNIQUE(_xlfn._xlws.FILTER('📞 Call Tracker'!C2:C2000,'📞 Call Tracker'!C2:C2000>0))),"")} -> 45997 | C15: =IF(B15="","",COUNTIFS('📞 Call Tracker'!$C:$C,">="&B15,'📞 Call Tracker'!$C:$C,"<"&B15+1)) -> 46 | D15: =IF(B15="","",COUNTIFS('📞 Call Tracker'!$C:$C,">="&B15,'📞 Call Tracker'!$C:$C,"<"&B15+1,'📞 Call Tracker'!$D:$D,"YES")) -> 27 | E15: =IF(B15="","",COUNTIFS('📞 Call Tracker'!$C:$C,">="&B15,'📞 Call Tracker'!$C:$C,"<"&B15+1,'📞 Call Tracker'!$D:$D,"NO")) -> 9 | F15: =IF(B15="","",COUNTIFS('📞 Call Tracker'!$C:$C,">="&B15,'📞 Call Tracker'!$C:$C,"<"&B15+1,'📞 Call Tracker'!$B:$B,"Michelle")) -> 15 | G15: =IF(B15="","",COUNTIFS('📞 Call Tracker'!$C:$C,">="&B15,'📞 Call Tracker'!$C:$C,"<"&B15+1,'📞 Call Tracker'!$B:$B,"Joaquin")) -> 31
B16: 46011 | C16: =IF(B16="","",COUNTIFS('📞 Call Tracker'!$C:$C,">="&B16,'📞 Call Tracker'!$C:$C,"<"&B16+1)) -> 26 | D16: =IF(B16="","",COUNTIFS('📞 Call Tracker'!$C:$C,">="&B16,'📞 Call Tracker'!$C:$C,"<"&B16+1,'📞 Call Tracker'!$D:$D,"YES")) -> 19 | E16: =IF(B16="","",COUNTIFS('📞 Call Tracker'!$C:$C,">="&B16,'📞 Call Tracker'!$C:$C,"<"&B16+1,'📞 Call Tracker'!$D:$D,"NO")) -> 5 | F16: =IF(B16="","",COUNTIFS('📞 Call Tracker'!$C:$C,">="&B16,'📞 Call Tracker'!$C:$C,"<"&B16+1,'📞 Call Tracker'!$B:$B,"Michelle")) -> 0 | G16: =IF(B16="","",COUNTIFS('📞 Call Tracker'!$C:$C,">="&B16,'📞 Call Tracker'!$C:$C,"<"&B16+1,'📞 Call Tracker'!$B:$B,"Joaquin")) -> 26
B17: 46018 | C17: =IF(B17="","",COUNTIFS('📞 Call Tracker'!$C:$C,">="&B17,'📞 Call Tracker'!$C:$C,"<"&B17+1)) -> 11 | D17: =IF(B17="","",COUNTIFS('📞 Call Tracker'!$C:$C,">="&B17,'📞 Call Tracker'!$C:$C,"<"&B17+1,'📞 Call Tracker'!$D:$D,"YES")) -> 4 | E17: =IF(B17="","",COUNTIFS('📞 Call Tracker'!$C:$C,">="&B17,'📞 Call Tracker'!$C:$C,"<"&B17+1,'📞 Call Tracker'!$D:$D,"NO")) -> 7 | F17: =IF(B17="","",COUNTIFS('📞 Call Tracker'!$C:$C,">="&B17,'📞 Call Tracker'!$C:$C,"<"&B17+1,'📞 Call Tracker'!$B:$B,"Michelle")) -> 2 | G17: =IF(B17="","",COUNTIFS('📞 Call Tracker'!$C:$C,">="&B17,'📞 Call Tracker'!$C:$C,"<"&B17+1,'📞 Call Tracker'!$B:$B,"Joaquin")) -> 9
B18: 46025 | C18: =IF(B18="","",COUNTIFS('📞 Call Tracker'!$C:$C,">="&B18,'📞 Call Tracker'!$C:$C,"<"&B18+1)) -> 37 | D18: =IF(B18="","",COUNTIFS('📞 Call Tracker'!$C:$C,">="&B18,'📞 Call Tracker'!$C:$C,"<"&B18+1,'📞 Call Tracker'!$D:$D,"YES")) -> 27 | E18: =IF(B18="","",COUNTIFS('📞 Call Tracker'!$C:$C,">="&B18,'📞 Call Tracker'!$C:$C,"<"&B18+1,'📞 Call Tracker'!$D:$D,"NO")) -> 6 | F18: =IF(B18="","",COUNTIFS('📞 Call Tracker'!$C:$C,">="&B18,'📞 Call Tracker'!$C:$C,"<"&B18+1,'📞 Call Tracker'!$B:$B,"Michelle")) -> 2 | G18: =IF(B18="","",COUNTIFS('📞 Call Tracker'!$C:$C,">="&B18,'📞 Call Tracker'!$C:$C,"<"&B18+1,'📞 Call Tracker'!$B:$B,"Joaquin")) -> 35
B19: 46032 | C19: =IF(B19="","",COUNTIFS('📞 Call Tracker'!$C:$C,">="&B19,'📞 Call Tracker'!$C:$C,"<"&B19+1)) -> 20 | D19: =IF(B19="","",COUNTIFS('📞 Call Tracker'!$C:$C,">="&B19,'📞 Call Tracker'!$C:$C,"<"&B19+1,'📞 Call Tracker'!$D:$D,"YES")) -> 13 | E19: =IF(B19="","",COUNTIFS('📞 Call Tracker'!$C:$C,">="&B19,'📞 Call Tracker'!$C:$C,"<"&B19+1,'📞 Call Tracker'!$D:$D,"NO")) -> 2 | F19: =IF(B19="","",COUNTIFS('📞 Call Tracker'!$C:$C,">="&B19,'📞 Call Tracker'!$C:$C,"<"&B19+1,'📞 Call Tracker'!$B:$B,"Michelle")) -> 4 | G19: =IF(B19="","",COUNTIFS('📞 Call Tracker'!$C:$C,">="&B19,'📞 Call Tracker'!$C:$C,"<"&B19+1,'📞 Call Tracker'!$B:$B,"Joaquin")) -> 16
B20: 46039 | C20: =IF(B20="","",COUNTIFS('📞 Call Tracker'!$C:$C,">="&B20,'📞 Call Tracker'!$C:$C,"<"&B20+1)) -> 28 | D20: =IF(B20="","",COUNTIFS('📞 Call Tracker'!$C:$C,">="&B20,'📞 Call Tracker'!$C:$C,"<"&B20+1,'📞 Call Tracker'!$D:$D,"YES")) -> 19 | E20: =IF(B20="","",COUNTIFS('📞 Call Tracker'!$C:$C,">="&B20,'📞 Call Tracker'!$C:$C,"<"&B20+1,'📞 Call Tracker'!$D:$D,"NO")) -> 9 | F20: =IF(B20="","",COUNTIFS('📞 Call Tracker'!$C:$C,">="&B20,'📞 Call Tracker'!$C:$C,"<"&B20+1,'📞 Call Tracker'!$B:$B,"Michelle")) -> 9 | G20: =IF(B20="","",COUNTIFS('📞 Call Tracker'!$C:$C,">="&B20,'📞 Call Tracker'!$C:$C,"<"&B20+1,'📞 Call Tracker'!$B:$B,"Joaquin")) -> 19
B21: 46046 | C21: =IF(B21="","",COUNTIFS('📞 Call Tracker'!$C:$C,">="&B21,'📞 Call Tracker'!$C:$C,"<"&B21+1)) -> 41 | D21: =IF(B21="","",COUNTIFS('📞 Call Tracker'!$C:$C,">="&B21,'📞 Call Tracker'!$C:$C,"<"&B21+1,'📞 Call Tracker'!$D:$D,"YES")) -> 23 | E21: =IF(B21="","",COUNTIFS('📞 Call Tracker'!$C:$C,">="&B21,'📞 Call Tracker'!$C:$C,"<"&B21+1,'📞 Call Tracker'!$D:$D,"NO")) -> 18 | F21: =IF(B21="","",COUNTIFS('📞 Call Tracker'!$C:$C,">="&B21,'📞 Call Tracker'!$C:$C,"<"&B21+1,'📞 Call Tracker'!$B:$B,"Michelle")) -> 10 | G21: =IF(B21="","",COUNTIFS('📞 Call Tracker'!$C:$C,">="&B21,'📞 Call Tracker'!$C:$C,"<"&B21+1,'📞 Call Tracker'!$B:$B,"Joaquin")) -> 31
B22: 46053 | C22: =IF(B22="","",COUNTIFS('📞 Call Tracker'!$C:$C,">="&B22,'📞 Call Tracker'!$C:$C,"<"&B22+1)) -> 38 | D22: =IF(B22="","",COUNTIFS('📞 Call Tracker'!$C:$C,">="&B22,'📞 Call Tracker'!$C:$C,"<"&B22+1,'📞 Call Tracker'!$D:$D,"YES")) -> 22 | E22: =IF(B22="","",COUNTIFS('📞 Call Tracker'!$C:$C,">="&B22,'📞 Call Tracker'!$C:$C,"<"&B22+1,'📞 Call Tracker'!$D:$D,"NO")) -> 16 | F22: =IF(B22="","",COUNTIFS('📞 Call Tracker'!$C:$C,">="&B22,'📞 Call Tracker'!$C:$C,"<"&B22+1,'📞 Call Tracker'!$B:$B,"Michelle")) -> 10 | G22: =IF(B22="","",COUNTIFS('📞 Call Tracker'!$C:$C,">="&B22,'📞 Call Tracker'!$C:$C,"<"&B22+1,'📞 Call Tracker'!$B:$B,"Joaquin")) -> 28
B23: 46060 | C23: =IF(B23="","",COUNTIFS('📞 Call Tracker'!$C:$C,">="&B23,'📞 Call Tracker'!$C:$C,"<"&B23+1)) -> 38 | D23: =IF(B23="","",COUNTIFS('📞 Call Tracker'!$C:$C,">="&B23,'📞 Call Tracker'!$C:$C,"<"&B23+1,'📞 Call Tracker'!$D:$D,"YES")) -> 23 | E23: =IF(B23="","",COUNTIFS('📞 Call Tracker'!$C:$C,">="&B23,'📞 Call Tracker'!$C:$C,"<"&B23+1,'📞 Call Tracker'!$D:$D,"NO")) -> 14 | F23: =IF(B23="","",COUNTIFS('📞 Call Tracker'!$C:$C,">="&B23,'📞 Call Tracker'!$C:$C,"<"&B23+1,'📞 Call Tracker'!$B:$B,"Michelle")) -> 12 | G23: =IF(B23="","",COUNTIFS('📞 Call Tracker'!$C:$C,">="&B23,'📞 Call Tracker'!$C:$C,"<"&B23+1,'📞 Call Tracker'!$B:$B,"Joaquin")) -> 26
B24: 46067 | C24: =IF(B24="","",COUNTIFS('📞 Call Tracker'!$C:$C,">="&B24,'📞 Call Tracker'!$C:$C,"<"&B24+1)) -> 46 | D24: =IF(B24="","",COUNTIFS('📞 Call Tracker'!$C:$C,">="&B24,'📞 Call Tracker'!$C:$C,"<"&B24+1,'📞 Call Tracker'!$D:$D,"YES")) -> 28 | E24: =IF(B24="","",COUNTIFS('📞 Call Tracker'!$C:$C,">="&B24,'📞 Call Tracker'!$C:$C,"<"&B24+1,'📞 Call Tracker'!$D:$D,"NO")) -> 18 | F24: =IF(B24="","",COUNTIFS('📞 Call Tracker'!$C:$C,">="&B24,'📞 Call Tracker'!$C:$C,"<"&B24+1,'📞 Call Tracker'!$B:$B,"Michelle")) -> 22 | G24: =IF(B24="","",COUNTIFS('📞 Call Tracker'!$C:$C,">="&B24,'📞 Call Tracker'!$C:$C,"<"&B24+1,'📞 Call Tracker'!$B:$B,"Joaquin")) -> 24
B25: 46074 | C25: =IF(B25="","",COUNTIFS('📞 Call Tracker'!$C:$C,">="&B25,'📞 Call Tracker'!$C:$C,"<"&B25+1)) -> 42 | D25: =IF(B25="","",COUNTIFS('📞 Call Tracker'!$C:$C,">="&B25,'📞 Call Tracker'!$C:$C,"<"&B25+1,'📞 Call Tracker'!$D:$D,"YES")) -> 28 | E25: =IF(B25="","",COUNTIFS('📞 Call Tracker'!$C:$C,">="&B25,'📞 Call Tracker'!$C:$C,"<"&B25+1,'📞 Call Tracker'!$D:$D,"NO")) -> 14 | F25: =IF(B25="","",COUNTIFS('📞 Call Tracker'!$C:$C,">="&B25,'📞 Call Tracker'!$C:$C,"<"&B25+1,'📞 Call Tracker'!$B:$B,"Michelle")) -> 16 | G25: =IF(B25="","",COUNTIFS('📞 Call Tracker'!$C:$C,">="&B25,'📞 Call Tracker'!$C:$C,"<"&B25+1,'📞 Call Tracker'!$B:$B,"Joaquin")) -> 26
B26: 46081 | C26: =IF(B26="","",COUNTIFS('📞 Call Tracker'!$C:$C,">="&B26,'📞 Call Tracker'!$C:$C,"<"&B26+1)) -> 26 | E26: =IF(B26="","",COUNTIFS('📞 Call Tracker'!$C:$C,">="&B26,'📞 Call Tracker'!$C:$C,"<"&B26+1,'📞 Call Tracker'!$D:$D,"NO")) -> 15 | F26: =IF(B26="","",COUNTIFS('📞 Call Tracker'!$C:$C,">="&B26,'📞 Call Tracker'!$C:$C,"<"&B26+1,'📞 Call Tracker'!$B:$B,"Michelle")) -> 1 | G26: =IF(B26="","",COUNTIFS('📞 Call Tracker'!$C:$C,">="&B26,'📞 Call Tracker'!$C:$C,"<"&B26+1,'📞 Call Tracker'!$B:$B,"Joaquin")) -> 25
C27: =IF(B27="","",COUNTIFS('📞 Call Tracker'!$C:$C,">="&B27,'📞 Call Tracker'!$C:$C,"<"&B27+1)) | D27: =IF(B27="","",COUNTIFS('📞 Call Tracker'!$C:$C,">="&B27,'📞 Call Tracker'!$C:$C,"<"&B27+1,'📞 Call Tracker'!$D:$D,"YES")) | E27: =IF(B27="","",COUNTIFS('📞 Call Tracker'!$C:$C,">="&B27,'📞 Call Tracker'!$C:$C,"<"&B27+1,'📞 Call Tracker'!$D:$D,"NO")) | F27: =IF(B27="","",COUNTIFS('📞 Call Tracker'!$C:$C,">="&B27,'📞 Call Tracker'!$C:$C,"<"&B27+1,'📞 Call Tracker'!$B:$B,"Michelle")) | G27: =IF(B27="","",COUNTIFS('📞 Call Tracker'!$C:$C,">="&B27,'📞 Call Tracker'!$C:$C,"<"&B27+1,'📞 Call Tracker'!$B:$B,"Joaquin"))
B30: ASSOCIATE PERFORMANCE | F30: CALL OUTCOMES
B31: Associate | C31: Calls | D31: Contacts | F31: Outcome | G31: Count
B32: Michelle | C32: =COUNTIF('📞 Call Tracker'!B2:B2000,"Michelle") -> 103 | D32: =COUNTIFS('📞 Call Tracker'!B2:B2000,"Michelle",'📞 Call Tracker'!D2:D2000,"NO") -> 36 | F32: General Education | G32: =COUNTIF('📞 Call Tracker'!E2:E2000,"General Education") -> 75
B33: Joaquin | C33: =COUNTIF('📞 Call Tracker'!B2:B2000,"Joaquin") -> 296 | D33: =COUNTIFS('📞 Call Tracker'!B2:B2000,"Joaquin",'📞 Call Tracker'!D2:D2000,"NO") -> 97 | F33: Rate Change | G33: =COUNTIF('📞 Call Tracker'!E2:E2000,"Rate Change") -> 10
B34: Total | C34: =SUM(C32:C33) -> 399 | D34: =SUM(D32:D33) -> 133 | F34: Updated/New PA | G34: =COUNTIF('📞 Call Tracker'!E2:E2000,"Updated/New PA") -> 1
F35: Utility Assistance | G35: =COUNTIF('📞 Call Tracker'!E2:E2000,"Utility Assistance") -> 3
F36: E3/E4 | G36: =COUNTIF('📞 Call Tracker'!E2:E2000,"E3/E4") -> 7
F37: Other | G37: =COUNTIF('📞 Call Tracker'!E2:E2000,"Other (fill in)") -> 9
F38: VM - No Answer | G38: =COUNTIF('📞 Call Tracker'!D2:D2000,"YES") -> 244
B40: ="Last updated: "&TEXT(TODAY(),"mmmm d, yyyy") -> Last updated: March 4, 2026
B41: =_xlfn.LET(_xlpm.trackerTotal,COUNTA('📞 Call Tracker'!A2:A2000),"✅ "&_xlpm.trackerTotal&" customers in tracker ("&COUNTA('📞 Call Tracker'!B2:B2000)&" called, "&_xlpm.trackerTotal-COUNTA('📞 Call Tracker'!B2:B2000)&" remaining)") -> ✅ 1100 customers in tracker (399 called, 701 remaining)

Sheet Docketed Comments
A1: Date | B1: Last Name | C1: First Name | D1: City | E1: Zip code | F1: Issue / Complaint | G1: Docketed Consumer Comments | H1: Account # | I1: Rate Plan | J1: E3? | K1: MCP? | L1: Cust on MEP | M1: PA? | N1: Payoff Balance | O1: Team Reviewed | P1: Response Y(date)/N | Q1: Last date of Account review | R1: Notes | S1: ACC Inquiry Sent to CA | T1: APS CA Referral | U1: Comments | V1: Include_Row
A2: 45796 | B2: Abidali | C2: Sanar | D2: Glendale | E2: 85308 | F2: Opposed | G2: https://images.edocket.azcc.gov/docketpdf/E000044112.pdf | H2: Unable to Locate Acct | V2: =IF( OR( ISNUMBER(SEARCH("unable to locate acct", tblDocketedComments[[#This Row],[Docketed Consumer Comments]])), ISNUMBER(SEARCH("unknown", tblDocketedComments[[#This Row],[Docketed Consumer Comments]])), ISNUMBER(SEARCH("inactive", tblDocketedComments[[#This Row],[Docketed Consumer Comments]])) ), 0, 1 ) -> 1
A3: 45797 | B3: Paulus | C3: Carl | D3: Unknown | E3: Unknown | F3: Opposed | G3: https://images.edocket.azcc.gov/docketpdf/E000044128.pdf | H3: Unable to Locate Acct | V3: =IF( OR( ISNUMBER(SEARCH("unable to locate acct", tblDocketedComments[[#This Row],[Docketed Consumer Comments]])), ISNUMBER(SEARCH("unknown", tblDocketedComments[[#This Row],[Docketed Consumer Comments]])), ISNUMBER(SEARCH("inactive", tblDocketedComments[[#This Row],[Docketed Consumer Comments]])) ), 0, 1 ) -> 1
A4: 45797 | B4: Wall | C4: Rae | D4: Glendale | E4: Unknown | F4: Opposed | G4: https://images.edocket.azcc.gov/docketpdf/E000044126.pdf | H4: 5494061000 | I4: R3-47 | J4: No | K4: No | L4: Yes | M4: No | N4: No | O4: Yes | P4: N | Q4: 45589 | U4: Also filed 6/10, 6/12, 6/16 | V4: =IF( OR( ISNUMBER(SEARCH("unable to locate acct", tblDocketedComments[[#This Row],[Docketed Consumer Comments]])), ISNUMBER(SEARCH("unknown", tblDocketedComments[[#This Row],[Docketed Consumer Comments]])), ISNUMBER(SEARCH("inactive", tblDocketedComments[[#This Row],[Docketed Consumer Comments]])) ), 0, 1 ) -> 1
A5: 45798 | B5: Gwiazda | C5: Patricia | D5: Youngtown | E5: 85363 | F5: Opposed | G5: https://images.edocket.azcc.gov/docketpdf/E000044147.pdf | H5: 2074850000 | I5: RCPw/RTOUE47 | J5: No | K5: No | L5: No - MEP is R3-47 ($65.13) | M5: No | N5: No | O5: Yes | P5: N | Q5: 45589 | R5: MEP Annual Savings - $67.68 - Didn't Contact | V5: =IF( OR( ISNUMBER(SEARCH("unable to locate acct", tblDocketedComments[[#This Row],[Docketed Consumer Comments]])), ISNUMBER(SEARCH("unknown", tblDocketedComments[[#This Row],[Docketed Consumer Comments]])), ISNUMBER(SEARCH("inactive", tblDocketedComments[[#This Row],[Docketed Consumer Comments]])) ), 0, 1 ) -> 1
A6: 45798 | B6: Phillips | C6: Crystal | D6: Young | E6: 85554 | F6: Opposed | G6: https://images.edocket.azcc.gov/docketpdf/E000044147.pdf | H6: 4823746138 | I6: R3-47 | J6: No | K6: No | L6: Yes | M6: No | N6: No | O6: Yes | P6: N | Q6: 45589 | V6: =IF( OR( ISNUMBER(SEARCH("unable to locate acct", tblDocketedComments[[#This Row],[Docketed Consumer Comments]])), ISNUMBER(SEARCH("unknown", tblDocketedComments[[#This Row],[Docketed Consumer Comments]])), ISNUMBER(SEARCH("inactive", tblDocketedComments[[#This Row],[Docketed Consumer Comments]])) ), 0, 1 ) -> 1
A7: 45799 | B7: Beame | C7: Sndney | D7: Unknown | E7: Unknown | F7: Opposed/Senior/fixed income | G7: https://images.edocket.azcc.gov/docketpdf/E000044169.pdf | H7: 8991140195 | I7: R-BASICL | J7: No | K7: No | L7: No - MEP R3-47 ($192.78) | M7: No | N7: No | O7: Yes | P7: 45964 | Q7: 45954 | R7: 11/03 - Customer agreed to change to their MEP | U7: Estimated savings $225.94/12 = $18.82 potential monthly savings on MEP | V7: =IF( OR( ISNUMBER(SEARCH("unable to locate acct", tblDocketedComments[[#This Row],[Docketed Consumer Comments]])), ISNUMBER(SEARCH("unknown", tblDocketedComments[[#This Row],[Docketed Consumer Comments]])), ISNUMBER(SEARCH("inactive", tblDocketedComments[[#This Row],[Docketed Consumer Comments]])) ), 0, 1 ) -> 1
A8: 45800 | B8: Scoggins | C8: Troy | D8: Phoenix | E8: 85009 | F8: Opposed | G8: https://images.edocket.azcc.gov/docketpdf/E000044282.pdf | H8: Unknown | U8: Unable to locate account with name provided | V8: =IF( OR( ISNUMBER(SEARCH("unable to locate acct", tblDocketedComments[[#This Row],[Docketed Consumer Comments]])), ISNUMBER(SEARCH("unknown", tblDocketedComments[[#This Row],[Docketed Consumer Comments]])), ISNUMBER(SEARCH("inactive", tblDocketedComments[[#This Row],[Docketed Consumer Comments]])) ), 0, 1 ) -> 1
A9: 45804 | B9: Nuccio | C9: Tina | D9: Cave Creek | E9: 85331 | F9: Opposed | G9: https://images.edocket.azcc.gov/docketpdf/E000044298.pdf | H9: 5900820000 | I9: R3-47 | J9: No | K9: No | L9: Yes | M9: No | N9: No | O9: Yes | P9: N | Q9: 45954 | V9: =IF( OR( ISNUMBER(SEARCH("unable to locate acct", tblDocketedComments[[#This Row],[Docketed Consumer Comments]])), ISNUMBER(SEARCH("unknown", tblDocketedComments[[#This Row],[Docketed Consumer Comments]])), ISNUMBER(SEARCH("inactive", tblDocketedComments[[#This Row],[Docketed Consumer Comments]])) ), 0, 1 ) -> 1
A10: 45805 | B10: Henkel | C10: Dean | D10: Unknown | E10: Unknown | F10: Opposed | G10: https://images.edocket.azcc.gov/docketpdf/E000044312.pdf | H10: 1569851000 | I10: R-XS | J10: No | K10: No | L10: Yes | M10: No | N10: No | O10: Yes | P10: N | Q10: 45954 | V10: =IF( OR( ISNUMBER(SEARCH("unable to locate acct", tblDocketedComments[[#This Row],[Docketed Consumer Comments]])), ISNUMBER(SEARCH("unknown", tblDocketedComments[[#This Row],[Docketed Consumer Comments]])), ISNUMBER(SEARCH("inactive", tblDocketedComments[[#This Row],[Docketed Consumer Comments]])) ), 0, 1 ) -> 1
A11: 45812 | B11: Palmer | C11: William | D11: Unknown | E11: Unknown | F11: Opposed | G11: https://images.edocket.azcc.gov/docketpdf/E000044514.pdf | H11: Unable to Locate Acct | U11: Not able to locate specific account | V11: =IF( OR( ISNUMBER(SEARCH("unable to locate acct", tblDocketedComments[[#This Row],[Docketed Consumer Comments]])), ISNUMBER(SEARCH("unknown", tblDocketedComments[[#This Row],[Docketed Consumer Comments]])), ISNUMBER(SEARCH("inactive", tblDocketedComments[[#This Row],[Docketed Consumer Comments]])) ), 0, 1 ) -> 1
A12: 45812 | B12: Paulsen | C12: Jodi | D12: Unknown | E12: Unknown | F12: Opposed | G12: https://images.edocket.azcc.gov/docketpdf/E000044514.pdf | H12: 7938430000 | I12: EPR-6w/ET-1 | J12: No | K12: No | L12: Not able to Compare | M12: No | N12: No | O12: Yes | P12: N | Q12: 45957 | V12: =IF( OR( ISNUMBER(SEARCH("unable to locate acct", tblDocketedComments[[#This Row],[Docketed Consumer Comments]])), ISNUMBER(SEARCH("unknown", tblDocketedComments[[#This Row],[Docketed Consumer Comments]])), ISNUMBER(SEARCH("inactive", tblDocketedComments[[#This Row],[Docketed Consumer Comments]])) ), 0, 1 ) -> 1
A13: 45813 | B13: Berto | C13: Kim & Dave | D13: Chino Valley | E13: Unknown | F13: Opposed | G13: https://images.edocket.azcc.gov/docketpdf/E000044536.pdf | H13: 2009184288 | I13: RCPw/RTOUE47 | J13: No | K13: No | L13: Yes | M13: No | N13: No | O13: Yes | P13: N | Q13: 45957 | V13: =IF( OR( ISNUMBER(SEARCH("unable to locate acct", tblDocketedComments[[#This Row],[Docketed Consumer Comments]])), ISNUMBER(SEARCH("unknown", tblDocketedComments[[#This Row],[Docketed Consumer Comments]])), ISNUMBER(SEARCH("inactive", tblDocketedComments[[#This Row],[Docketed Consumer Comments]])) ), 0, 1 ) -> 1
A14: 45813 | B14: Misamore | C14: Bruce | D14: Sedona | E14: 86336 | F14: Opposed | G14: https://images.edocket.azcc.gov/docketpdf/E000044536.pdf | H14: Inactive Acct | J14: No | V14: =IF( OR( ISNUMBER(SEARCH("unable to locate acct", tblDocketedComments[[#This Row],[Docketed Consumer Comments]])), ISNUMBER(SEARCH("unknown", tblDocketedComments[[#This Row],[Docketed Consumer Comments]])), ISNUMBER(SEARCH("inactive", tblDocketedComments[[#This Row],[Docketed Consumer Comments]])) ), 0, 1 ) -> 1
A15: 45814 | B15: Shroyer | C15: Mary Lynne | D15: Sun City | E15: 85351 | F15: Opposed | G15: https://images.edocket.azcc.gov/docketpdf/E000044648.pdf | H15: 1163301000 | I15: R-XS | J15: No | K15: No | L15: Yes | M15: No | N15: No | O15: Yes | P15: N | Q15: 45957 | V15: =IF( OR( ISNUMBER(SEARCH("unable to locate acct", tblDocketedComments[[#This Row],[Docketed Consumer Comments]])), ISNUMBER(SEARCH("unknown", tblDocketedComments[[#This Row],[Docketed Consumer Comments]])), ISNUMBER(SEARCH("inactive", tblDocketedComments[[#This Row],[Docketed Consumer Comments]])) ), 0, 1 ) -> 1
A16: 45821 | B16: Driscoll | C16: David & Donna | D16: Unknown | E16: Unknown | F16: Opposed | G16: https://images.edocket.azcc.gov/docketpdf/E000044766.pdf | H16: 6242500593 | I16: RCPw/RTOUE47 | J16: No | K16: No | L16: No - MEP R3-47($151.35) | M16: No | N16: No | O16: Yes | P16: N | Q16: 45957 | R16: Prior ACC Complaint customer - Solar customer does not want to be on demand rate. | V16: =IF( OR( ISNUMBER(SEARCH("unable to locate acct", tblDocketedComments[[#This Row],[Docketed Consumer Comments]])), ISNUMBER(SEARCH("unknown", tblDocketedComments[[#This Row],[Docketed Consumer Comments]])), ISNUMBER(SEARCH("inactive", tblDocketedComments[[#This Row],[Docketed Consumer Comments]])) ), 0, 1 ) -> 1
A17: 45824 | B17: Hix | C17: Debbie | D17: Unknown | E17: Unknown | F17: Opposed | G17: https://images.edocket.azcc.gov/docketpdf/E000044775.pdf https://images.edocket.azcc.gov/docketpdf/E000044791.pdf | H17: Unable to Locate Acct | U17: Filed 2x on 6/16 (Thompson and Myers), Not able to locate specific account | V17: =IF( OR( ISNUMBER(SEARCH("unable to locate acct", tblDocketedComments[[#This Row],[Docketed Consumer Comments]])), ISNUMBER(SEARCH("unknown", tblDocketedComments[[#This Row],[Docketed Consumer Comments]])), ISNUMBER(SEARCH("inactive", tblDocketedComments[[#This Row],[Docketed Consumer Comments]])) ), 0, 1 ) -> 1
A18: 45824 | B18: Montana | C18: Casitas | D18: Unknown | E18: Unknown | F18: Opposed | G18: https://images.edocket.azcc.gov/docketpdf/E000044777.pdf | H18: Unable to Locate Acct | V18: =IF( OR( ISNUMBER(SEARCH("unable to locate acct", tblDocketedComments[[#This Row],[Docketed Consumer Comments]])), ISNUMBER(SEARCH("unknown", tblDocketedComments[[#This Row],[Docketed Consumer Comments]])), ISNUMBER(SEARCH("inactive", tblDocketedComments[[#This Row],[Docketed Consumer Comments]])) ), 0, 1 ) -> 1
A19: 45824 | B19: Paulus | C19: Carl | D19: Unknown | E19: Unknown | F19: Opposed | G19: https://images.edocket.azcc.gov/docketpdf/E000044776.pdf | H19: Unable to Locate Acct | U19: Filed on 5/18 and 6/16 | V19: =IF( OR( ISNUMBER(SEARCH("unable to locate acct", tblDocketedComments[[#This Row],[Docketed Consumer Comments]])), ISNUMBER(SEARCH("unknown", tblDocketedComments[[#This Row],[Docketed Consumer Comments]])), ISNUMBER(SEARCH("inactive", tblDocketedComments[[#This Row],[Docketed Consumer Comments]])) ), 0, 1 ) -> 1
A20: 45825 | B20: Carpio | C20: Tania | D20: Surprise | E20: 85379 | F20: Opposed | G20: https://images.edocket.azcc.gov/docketpdf/E000044799.pdf | H20: Unable to Locate Acct | V20: =IF( OR( ISNUMBER(SEARCH("unable to locate acct", tblDocketedComments[[#This Row],[Docketed Consumer Comments]])), ISNUMBER(SEARCH("unknown", tblDocketedComments[[#This Row],[Docketed Consumer Comments]])), ISNUMBER(SEARCH("inactive", tblDocketedComments[[#This Row],[Docketed Consumer Comments]])) ), 0, 1 ) -> 1
A21: 45825 | B21: Mansour | C21: Joe | D21: Surprise | E21: 85387 | F21: Opposed | G21: https://images.edocket.azcc.gov/docketpdf/E000044799.pdf | H21: Unable to Locate Acct | V21: =IF( OR( ISNUMBER(SEARCH("unable to locate acct", tblDocketedComments[[#This Row],[Docketed Consumer Comments]])), ISNUMBER(SEARCH("unknown", tblDocketedComments[[#This Row],[Docketed Consumer Comments]])), ISNUMBER(SEARCH("inactive", tblDocketedComments[[#This Row],[Docketed Consumer Comments]])) ), 0, 1 ) -> 1
A22: 45825 | B22: Neal | C22: Michelle | D22: Glendale | E22: 85308 | F22: Opposed | G22: https://images.edocket.azcc.gov/docketpdf/E000044799.pdf | H22: 1565756559 | I22: R3-47 | J22: No | K22: No | L22: Yes | M22: No | N22: No | O22: Yes | P22: N | Q22: 45957 | V22: =IF( OR( ISNUMBER(SEARCH("unable to locate acct", tblDocketedComments[[#This Row],[Docketed Consumer Comments]])), ISNUMBER(SEARCH("unknown", tblDocketedComments[[#This Row],[Docketed Consumer Comments]])), ISNUMBER(SEARCH("inactive", tblDocketedComments[[#This Row],[Docketed Consumer Comments]])) ), 0, 1 ) -> 1
A23: 45826 | B23: Couillard | C23: Andre | D23: Phoenix | E23: 85027 | F23: Opposed | G23: https://images.edocket.azcc.gov/docketpdf/E000044842.pdf | H23: Unable to Locate Acct | U23: Filed 2x on 6/18 | V23: =IF( OR( ISNUMBER(SEARCH("unable to locate acct", tblDocketedComments[[#This Row],[Docketed Consumer Comments]])), ISNUMBER(SEARCH("unknown", tblDocketedComments[[#This Row],[Docketed Consumer Comments]])), ISNUMBER(SEARCH("inactive", tblDocketedComments[[#This Row],[Docketed Consumer Comments]])) ), 0, 1 ) -> 1
A24: 45826 | B24: Witte | C24: Jessica | D24: Scottsdale | E24: 85254 | F24: Opposed | G24: https://images.edocket.azcc.gov/docketpdf/E000044842.pdf | H24: 7413433376 | I24: R-BASIC | J24: No | K24: No | L24: Yes | M24: No | N24: No | O24: Yes | P24: N | Q24: 45957 | V24: =IF( OR( ISNUMBER(SEARCH("unable to locate acct", tblDocketedComments[[#This Row],[Docketed Consumer Comments]])), ISNUMBER(SEARCH("unknown", tblDocketedComments[[#This Row],[Docketed Consumer Comments]])), ISNUMBER(SEARCH("inactive", tblDocketedComments[[#This Row],[Docketed Consumer Comments]])) ), 0, 1 ) -> 1
A25: 45826 | B25: Figueroa | C25: Enrique | D25: Gilbert | E25: 85233 | F25: Opposed | G25: https://images.edocket.azcc.gov/docketpdf/E000044842.pdf | H25: 6601188228 | I25: R3-47 | J25: No | K25: No | L25: Yes | M25: No | N25: No | O25: Yes | P25: N | Q25: 45957 | V25: =IF( OR( ISNUMBER(SEARCH("unable to locate acct", tblDocketedComments[[#This Row],[Docketed Consumer Comments]])), ISNUMBER(SEARCH("unknown", tblDocketedComments[[#This Row],[Docketed Consumer Comments]])), ISNUMBER(SEARCH("inactive", tblDocketedComments[[#This Row],[Docketed Consumer Comments]])) ), 0, 1 ) -> 1
A26: 45826 | B26: Wheatley | C26: Heather | D26: Surprise | E26: 85388 | F26: Opposed | G26: https://images.edocket.azcc.gov/docketpdf/E000044842.pdf | H26: 7397110970 | I26: R3-47 | J26: No | K26: No | L26: Yes | M26: No | N26: No | O26: Yes | P26: N | Q26: 45957 | V26: =IF( OR( ISNUMBER(SEARCH("unable to locate acct", tblDocketedComments[[#This Row],[Docketed Consumer Comments]])), ISNUMBER(SEARCH("unknown", tblDocketedComments[[#This Row],[Docketed Consumer Comments]])), ISNUMBER(SEARCH("inactive", tblDocketedComments[[#This Row],[Docketed Consumer Comments]])) ), 0, 1 ) -> 1
A27: 45826 | B27: Millbranth | C27: Mark | D27: Scottsdale | E27: 85266 | F27: Opposed | G27: https://images.edocket.azcc.gov/docketpdf/E000044842.pdf | H27: 5288831000 | I27: R3-47 | J27: No | K27: No | L27: Yes | M27: No | N27: No | O27: Yes | P27: N | Q27: 45957 | V27: =IF( OR( ISNUMBER(SEARCH("unable to locate acct", tblDocketedComments[[#This Row],[Docketed Consumer Comments]])), ISNUMBER(SEARCH("unknown", tblDocketedComments[[#This Row],[Docketed Consumer Comments]])), ISNUMBER(SEARCH("inactive", tblDocketedComments[[#This Row],[Docketed Consumer Comments]])) ), 0, 1 ) -> 1
A28: 45826 | B28: Wilson | C28: John | D28: Carefree | E28: Unknown | F28: Opposed | G28: https://images.edocket.azcc.gov/docketpdf/E000044846.pdf | H28: Unable to Locate Acct | U28: Not able to locate specific account | V28: =IF( OR( ISNUMBER(SEARCH("unable to locate acct", tblDocketedComments[[#This Row],[Docketed Consumer Comments]])), ISNUMBER(SEARCH("unknown", tblDocketedComments[[#This Row],[Docketed Consumer Comments]])), ISNUMBER(SEARCH("inactive", tblDocketedComments[[#This Row],[Docketed Consumer Comments]])) ), 0, 1 ) -> 1
A29: 45826 | B29: Geyer | C29: Jared | D29: Scottsdale | E29: 85254 | F29: Opposed | G29: https://images.edocket.azcc.gov/docketpdf/E000044846.pdf | H29: 7528633936 | I29: R-BASICL | J29: No | K29: No | L29: No MEP R3-47 ($36.88) | M29: No | N29: No | O29: Yes | P29: N | Q29: 45957 | U29: Estimated savings $37.01/12 = $3.08 potential monthly savings on MEP | V29: =IF( OR( ISNUMBER(SEARCH("unable to locate acct", tblDocketedComments[[#This Row],[Docketed Consumer Comments]])), ISNUMBER(SEARCH("unknown", tblDocketedComments[[#This Row],[Docketed Consumer Comments]])), ISNUMBER(SEARCH("inactive", tblDocketedComments[[#This Row],[Docketed Consumer Comments]])) ), 0, 1 ) -> 1
A30: 45826 | B30: Snyder | C30: Steven | D30: Phoenix | E30: 85029 | F30: Opposed | G30: https://images.edocket.azcc.gov/docketpdf/E000044846.pdf | H30: 4262494925 | I30: R3-47 | J30: No | K30: No | L30: No MEP R-XS ($110.29) | M30: No | N30: No | O30: Yes | P30: 45964 | Q30: 45957 | R30: 11/03 - LM | U30: Estimated savings $43.66/12 = $3.63 potential monthly savings on MEP | V30: =IF( OR( ISNUMBER(SEARCH("unable to locate acct", tblDocketedComments[[#This Row],[Docketed Consumer Comments]])), ISNUMBER(SEARCH("unknown", tblDocketedComments[[#This Row],[Docketed Consumer Comments]])), ISNUMBER(SEARCH("inactive", tblDocketedComments[[#This Row],[Docketed Consumer Comments]])) ), 0, 1 ) -> 1
A31: 45826 | B31: Buehler | C31: Mark | D31: Unknown | E31: Unknown | F31: Opposed | G31: https://images.edocket.azcc.gov/docketpdf/E000044840.pdf | H31: Unable to Locate Acct | U31: Not able to locate specific account | V31: =IF( OR( ISNUMBER(SEARCH("unable to locate acct", tblDocketedComments[[#This Row],[Docketed Consumer Comments]])), ISNUMBER(SEARCH("unknown", tblDocketedComments[[#This Row],[Docketed Consumer Comments]])), ISNUMBER(SEARCH("inactive", tblDocketedComments[[#This Row],[Docketed Consumer Comments]])) ), 0, 1 ) -> 1
A32: 45826 | B32: Kaplan | C32: Wayne | D32: Unknown | E32: Unknown | F32: Opposed | G32: https://images.edocket.azcc.gov/docketpdf/E000044840.pdf | H32: 4273250000 | I32: R-XS | J32: No | K32: No | L32: Yes | M32: No | N32: No | O32: Yes | P32: N | Q32: 45957 | V32: =IF( OR( ISNUMBER(SEARCH("unable to locate acct", tblDocketedComments[[#This Row],[Docketed Consumer Comments]])), ISNUMBER(SEARCH("unknown", tblDocketedComments[[#This Row],[Docketed Consumer Comments]])), ISNUMBER(SEARCH("inactive", tblDocketedComments[[#This Row],[Docketed Consumer Comments]])) ), 0, 1 ) -> 1
A33: 45826 | B33: Delgado | C33: Amber | D33: Unknown | E33: Unknown | F33: Opposed | G33: https://images.edocket.azcc.gov/docketpdf/E000044840.pdf | H33: 8714231000 | I33: R3-47 | J33: No | K33: No | L33: Yes | M33: No | N33: No | O33: Yes | P33: N | Q33: 45957 | R33: Changed rate to MEP on 10/6 | U33: Estimated savings $68.27/12 - $5.69 potential monthly savings on MEP | V33: =IF( OR( ISNUMBER(SEARCH("unable to locate acct", tblDocketedComments[[#This Row],[Docketed Consumer Comments]])), ISNUMBER(SEARCH("unknown", tblDocketedComments[[#This Row],[Docketed Consumer Comments]])), ISNUMBER(SEARCH("inactive", tblDocketedComments[[#This Row],[Docketed Consumer Comments]])) ), 0, 1 ) -> 1
A34: 45826 | B34: Reyes | C34: Michelle | D34: Glendale | E34: 85310 | F34: Opposed | G34: https://images.edocket.azcc.gov/docketpdf/E000044840.pdf | H34: Unable to Locate Acct | U34: Not able to locate specific account | V34: =IF( OR( ISNUMBER(SEARCH("unable to locate acct", tblDocketedComments[[#This Row],[Docketed Consumer Comments]])), ISNUMBER(SEARCH("unknown", tblDocketedComments[[#This Row],[Docketed Consumer Comments]])), ISNUMBER(SEARCH("inactive", tblDocketedComments[[#This Row],[Docketed Consumer Comments]])) ), 0, 1 ) -> 1
A35: 45826 | B35: Saporito | C35: Annette | D35: Cave Creek | E35: 85331 | F35: Opposed | G35: https://images.edocket.azcc.gov/docketpdf/E000044840.pdf | H35: 7980600000 | I35: RTOUE47 | J35: No | K35: No | L35: No R3-47 ($439.74) | M35: No | N35: No | O35: Yes | P35: 45964 | Q35: 45957 | R35: 11/03 - LM | U35: Estimated savings $433.16/12 = $36.09 potential monthly savings on MEP | V35: =IF( OR( ISNUMBER(SEARCH("unable to locate acct", tblDocketedComments[[#This Row],[Docketed Consumer Comments]])), ISNUMBER(SEARCH("unknown", tblDocketedComments[[#This Row],[Docketed Consumer Comments]])), ISNUMBER(SEARCH("inactive", tblDocketedComments[[#This Row],[Docketed Consumer Comments]])) ), 0, 1 ) -> 1
A36: 45827 | B36: Miller | C36: D | D36: Goodyear | E36: Unknown | F36: Opposed, thinks Budget billing is a scam | G36: https://images.edocket.azcc.gov/docketpdf/0000214768.pdf | H36: Unable to Locate Acct | U36: Not able to locate specific account | V36: =IF( OR( ISNUMBER(SEARCH("unable to locate acct", tblDocketedComments[[#This Row],[Docketed Consumer Comments]])), ISNUMBER(SEARCH("unknown", tblDocketedComments[[#This Row],[Docketed Consumer Comments]])), ISNUMBER(SEARCH("inactive", tblDocketedComments[[#This Row],[Docketed Consumer Comments]])) ), 0, 1 ) -> 1
A37: 45827 | B37: Gray | C37: Tim | D37: Buckeye | E37: Unknown | F37: Opposed | G37: https://images.edocket.azcc.gov/docketpdf/E000044863.pdf | H37: Unable to Locate Acct | U37: Not able to locate specific account | V37: =IF( OR( ISNUMBER(SEARCH("unable to locate acct", tblDocketedComments[[#This Row],[Docketed Consumer Comments]])), ISNUMBER(SEARCH("unknown", tblDocketedComments[[#This Row],[Docketed Consumer Comments]])), ISNUMBER(SEARCH("inactive", tblDocketedComments[[#This Row],[Docketed Consumer Comments]])) ), 0, 1 ) -> 1
A38: 45827 | B38: Garcia | C38: Amy | D38: Unknown | E38: Unknown | F38: Opposed | G38: https://images.edocket.azcc.gov/docketpdf/E000044863.pdf | H38: Unable to Locate Acct | U38: Not able to locate specific account | V38: =IF( OR( ISNUMBER(SEARCH("unable to locate acct", tblDocketedComments[[#This Row],[Docketed Consumer Comments]])), ISNUMBER(SEARCH("unknown", tblDocketedComments[[#This Row],[Docketed Consumer Comments]])), ISNUMBER(SEARCH("inactive", tblDocketedComments[[#This Row],[Docketed Consumer Comments]])) ), 0, 1 ) -> 1
A39: 45827 | B39: Merlino | C39: Teri | D39: Unknown | E39: Unknown | F39: Opposed | G39: https://images.edocket.azcc.gov/docketpdf/E000044863.pdf | H39: 3007031000 | I39: R3-47 | J39: No | K39: No | L39: Yes | M39: No | N39: No | O39: Yes | P39: N | Q39: 45957 | V39: =IF( OR( ISNUMBER(SEARCH("unable to locate acct", tblDocketedComments[[#This Row],[Docketed Consumer Comments]])), ISNUMBER(SEARCH("unknown", tblDocketedComments[[#This Row],[Docketed Consumer Comments]])), ISNUMBER(SEARCH("inactive", tblDocketedComments[[#This Row],[Docketed Consumer Comments]])) ), 0, 1 ) -> 1
A40: 45827 | B40: Escamilla | C40: Nephesh | D40: Phoenix | E40: Unknown | F40: Opposed | G40: https://images.edocket.azcc.gov/docketpdf/E000044866.pdf | H40: Unable to Locate Acct | V40: =IF( OR( ISNUMBER(SEARCH("unable to locate acct", tblDocketedComments[[#This Row],[Docketed Consumer Comments]])), ISNUMBER(SEARCH("unknown", tblDocketedComments[[#This Row],[Docketed Consumer Comments]])), ISNUMBER(SEARCH("inactive", tblDocketedComments[[#This Row],[Docketed Consumer Comments]])) ), 0, 1 ) -> 1
A41: 45827 | B41: van Dalen | C41: Danielle | D41: Surprise | E41: 85374 | F41: Opposed | G41: https://images.edocket.azcc.gov/docketpdf/E000044866.pdf | H41: 8025299133 | I41: R-BASIC | J41: No | K41: No | L41: Yes | M41: No | N41: No | O41: Yes | P41: N | Q41: 45957 | V41: =IF( OR( ISNUMBER(SEARCH("unable to locate acct", tblDocketedComments[[#This Row],[Docketed Consumer Comments]])), ISNUMBER(SEARCH("unknown", tblDocketedComments[[#This Row],[Docketed Consumer Comments]])), ISNUMBER(SEARCH("inactive", tblDocketedComments[[#This Row],[Docketed Consumer Comments]])) ), 0, 1 ) -> 1
A42: 45831 | B42: Crandall | C42: Debbie | D42: Goodyear | E42: 85338 | F42: Opposed | H42: Unable to Locate Acct | V42: =IF( OR( ISNUMBER(SEARCH("unable to locate acct", tblDocketedComments[[#This Row],[Docketed Consumer Comments]])), ISNUMBER(SEARCH("unknown", tblDocketedComments[[#This Row],[Docketed Consumer Comments]])), ISNUMBER(SEARCH("inactive", tblDocketedComments[[#This Row],[Docketed Consumer Comments]])) ), 0, 1 ) -> 1
A43: 45831 | B43: Rodreguez | C43: Alexis | D43: Buckeye | E43: 85326 | F43: Opposed | H43: Unable to Locate Acct | V43: =IF( OR( ISNUMBER(SEARCH("unable to locate acct", tblDocketedComments[[#This Row],[Docketed Consumer Comments]])), ISNUMBER(SEARCH("unknown", tblDocketedComments[[#This Row],[Docketed Consumer Comments]])), ISNUMBER(SEARCH("inactive", tblDocketedComments[[#This Row],[Docketed Consumer Comments]])) ), 0, 1 ) -> 1
A44: 45831 | B44: Schilling | C44: David | D44: Buckeye | E44: Unknown | F44: Opposed | H44: 0799340889 | I44: R-BASIC | J44: No | K44: No | L44: No-Mep R3-47($87.55) | M44: No | N44: No | O44: Yes | P44: N | Q44: 45957 | V44: =IF( OR( ISNUMBER(SEARCH("unable to locate acct", tblDocketedComments[[#This Row],[Docketed Consumer Comments]])), ISNUMBER(SEARCH("unknown", tblDocketedComments[[#This Row],[Docketed Consumer Comments]])), ISNUMBER(SEARCH("inactive", tblDocketedComments[[#This Row],[Docketed Consumer Comments]])) ), 0, 1 ) -> 1
A45: 45831 | B45: Luther | C45: Jonathan | D45: Phoenix | E45: 85006 | F45: Opposed | H45: 9229380000 | I45: RTOUE47 | J45: No | K45: No | L45: No-MEP R3-47($5.29) | M45: No | N45: No | O45: Yes | P45: N | Q45: 45957 | V45: =IF( OR( ISNUMBER(SEARCH("unable to locate acct", tblDocketedComments[[#This Row],[Docketed Consumer Comments]])), ISNUMBER(SEARCH("unknown", tblDocketedComments[[#This Row],[Docketed Consumer Comments]])), ISNUMBER(SEARCH("inactive", tblDocketedComments[[#This Row],[Docketed Consumer Comments]])) ), 0, 1 ) -> 1
A46: 45831 | B46: McKenzie | C46: Christine | D46: Phoenix | E46: 85085 | F46: Opposed | H46: Inactive Acct | V46: =IF( OR( ISNUMBER(SEARCH("unable to locate acct", tblDocketedComments[[#This Row],[Docketed Consumer Comments]])), ISNUMBER(SEARCH("unknown", tblDocketedComments[[#This Row],[Docketed Consumer Comments]])), ISNUMBER(SEARCH("inactive", tblDocketedComments[[#This Row],[Docketed Consumer Comments]])) ), 0, 1 ) -> 1
A47: 45831 | B47: Porter | C47: Kristal | D47: Peoria | E47: 85383 | F47: Opposed | H47: 7501590000 | I47: R3-47 | J47: No | K47: No | L47: Yes | M47: No | N47: No | O47: Yes | P47: N | Q47: 45957 | V47: =IF( OR( ISNUMBER(SEARCH("unable to locate acct", tblDocketedComments[[#This Row],[Docketed Consumer Comments]])), ISNUMBER(SEARCH("unknown", tblDocketedComments[[#This Row],[Docketed Consumer Comments]])), ISNUMBER(SEARCH("inactive", tblDocketedComments[[#This Row],[Docketed Consumer Comments]])) ), 0, 1 ) -> 1
A48: 45831 | B48: Fullerton | C48: Dale | D48: Unknown | E48: Unknown | F48: Opposed | H48: Unable to Locate Acct | V48: =IF( OR( ISNUMBER(SEARCH("unable to locate acct", tblDocketedComments[[#This Row],[Docketed Consumer Comments]])), ISNUMBER(SEARCH("unknown", tblDocketedComments[[#This Row],[Docketed Consumer Comments]])), ISNUMBER(SEARCH("inactive", tblDocketedComments[[#This Row],[Docketed Consumer Comments]])) ), 0, 1 ) -> 1
A49: 45831 | B49: Gill | C49: Thomas | D49: Unknown | E49: Unknown | F49: Opposed | H49: Multiple Cust Found | V49: =IF( OR( ISNUMBER(SEARCH("unable to locate acct", tblDocketedComments[[#This Row],[Docketed Consumer Comments]])), ISNUMBER(SEARCH("unknown", tblDocketedComments[[#This Row],[Docketed Consumer Comments]])), ISNUMBER(SEARCH("inactive", tblDocketedComments[[#This Row],[Docketed Consumer Comments]])) ), 0, 1 ) -> 1
A50: 45831 | B50: McGibbon | C50: Charles | D50: Chino Valley | E50: 86323 | F50: Opposed | G50: https://images.edocket.azcc.gov/docketpdf/E000044947.pdf | H50: 4707610000 | I50: R-XS | J50: No | K50: No | L50: Yes | M50: No | N50: No | O50: Yes | P50: N | Q50: 45958 | V50: =IF( OR( ISNUMBER(SEARCH("unable to locate acct", tblDocketedComments[[#This Row],[Docketed Consumer Comments]])), ISNUMBER(SEARCH("unknown", tblDocketedComments[[#This Row],[Docketed Consumer Comments]])), ISNUMBER(SEARCH("inactive", tblDocketedComments[[#This Row],[Docketed Consumer Comments]])) ), 0, 1 ) -> 1
A51: 45833 | B51: Wolski | C51: Chris | D51: Unknown | E51: Unknown | F51: Opposed | H51: Unable to Locate Acct | V51: =IF( OR( ISNUMBER(SEARCH("unable to locate acct", tblDocketedComments[[#This Row],[Docketed Consumer Comments]])), ISNUMBER(SEARCH("unknown", tblDocketedComments[[#This Row],[Docketed Consumer Comments]])), ISNUMBER(SEARCH("inactive", tblDocketedComments[[#This Row],[Docketed Consumer Comments]])) ), 0, 1 ) -> 1
A52: 45835 | B52: Ancha | C52: Bob | D52: Scottsdale | E52: 85260 | F52: Opposed | G52: https://images.edocket.azcc.gov/docketpdf/E000044979.pdf | H52: Unable to Locate Acct | V52: =IF( OR( ISNUMBER(SEARCH("unable to locate acct", tblDocketedComments[[#This Row],[Docketed Consumer Comments]])), ISNUMBER(SEARCH("unknown", tblDocketedComments[[#This Row],[Docketed Consumer Comments]])), ISNUMBER(SEARCH("inactive", tblDocketedComments[[#This Row],[Docketed Consumer Comments]])) ), 0, 1 ) -> 1
A53: 45839 | B53: Sanchez | C53: Isabella | D53: Phoenix | E53: 85032 | F53: Opposed | G53: https://images.edocket.azcc.gov/docketpdf/E000045059.pdf | H53: 1164092226 | I53: R-BASIC | J53: No | K53: No | L53: Yes | M53: No | N53: No | O53: Yes | P53: N | Q53: 45958 | U53: Estimated savings $42.27/12 = $3.52 potential monthly savings on MEP | V53: =IF( OR( ISNUMBER(SEARCH("unable to locate acct", tblDocketedComments[[#This Row],[Docketed Consumer Comments]])), ISNUMBER(SEARCH("unknown", tblDocketedComments[[#This Row],[Docketed Consumer Comments]])), ISNUMBER(SEARCH("inactive", tblDocketedComments[[#This Row],[Docketed Consumer Comments]])) ), 0, 1 ) -> 1
A54: 45840 | B54: Hardy | C54: James | D54: Unknown | E54: Unknown | F54: Opposed | G54: https://images.edocket.azcc.gov/docketpdf/E000045067.pdf | H54: Unable to Locate Acct | U54: Not able to locate specific account | V54: =IF( OR( ISNUMBER(SEARCH("unable to locate acct", tblDocketedComments[[#This Row],[Docketed Consumer Comments]])), ISNUMBER(SEARCH("unknown", tblDocketedComments[[#This Row],[Docketed Consumer Comments]])), ISNUMBER(SEARCH("inactive", tblDocketedComments[[#This Row],[Docketed Consumer Comments]])) ), 0, 1 ) -> 1
A55: 45840 | B55: Franklin | C55: Jeff | D55: Unknown | E55: Unknown | F55: Opposed | G55: https://images.edocket.azcc.gov/docketpdf/E000045067.pdf | H55: Unable to Locate Acct | U55: Not able to locate specific account | V55: =IF( OR( ISNUMBER(SEARCH("unable to locate acct", tblDocketedComments[[#This Row],[Docketed Consumer Comments]])), ISNUMBER(SEARCH("unknown", tblDocketedComments[[#This Row],[Docketed Consumer Comments]])), ISNUMBER(SEARCH("inactive", tblDocketedComments[[#This Row],[Docketed Consumer Comments]])) ), 0, 1 ) -> 1
A56: 45845 | B56: Hertzfield | C56: Carol | D56: Phoenix | E56: 85022 | F56: Opposed | G56: https://images.edocket.azcc.gov/docketpdf/E000045130.pdf | H56: Unable to Locate Acct | V56: =IF( OR( ISNUMBER(SEARCH("unable to locate acct", tblDocketedComments[[#This Row],[Docketed Consumer Comments]])), ISNUMBER(SEARCH("unknown", tblDocketedComments[[#This Row],[Docketed Consumer Comments]])), ISNUMBER(SEARCH("inactive", tblDocketedComments[[#This Row],[Docketed Consumer Comments]])) ), 0, 1 ) -> 1
A57: 45846 | B57: Beiser | C57: Antoinette | D57: Sedona | E57: 86351 | F57: Opposed | G57: https://images.edocket.azcc.gov/docketpdf/E000045169.pdf | H57: 7150589750 | I57: R-BASICL | J57: No | K57: No | L57: No MEP R3-47($267.12) | M57: No | N57: No | O57: Yes | P57: 45964 | Q57: 45958 | R57: 11/03 - No answer and no voicemail | V57: =IF( OR( ISNUMBER(SEARCH("unable to locate acct", tblDocketedComments[[#This Row],[Docketed Consumer Comments]])), ISNUMBER(SEARCH("unknown", tblDocketedComments[[#This Row],[Docketed Consumer Comments]])), ISNUMBER(SEARCH("inactive", tblDocketedComments[[#This Row],[Docketed Consumer Comments]])) ), 0, 1 ) -> 1
A58: 45847 | B58: Underwood | C58: Revis | D58: Litchfield Park | E58: 85340 | F58: Opposed | G58: https://images.edocket.azcc.gov/docketpdf/E000045209.pdf | H58: 9558930000 | I58: EPR-6w/E-12 | J58: No | K58: No | L58: Info Not Avail | M58: No | N58: No | O58: Yes | P58: N | Q58: 45958 | V58: =IF( OR( ISNUMBER(SEARCH("unable to locate acct", tblDocketedComments[[#This Row],[Docketed Consumer Comments]])), ISNUMBER(SEARCH("unknown", tblDocketedComments[[#This Row],[Docketed Consumer Comments]])), ISNUMBER(SEARCH("inactive", tblDocketedComments[[#This Row],[Docketed Consumer Comments]])) ), 0, 1 ) -> 1
A59: 45847 | B59: Hacker | C59: Dennis | D59: Phoenix | E59: 85029 | F59: Pole Attachments | G59: https://images.edocket.azcc.gov/docketpdf/E000045207.pdf | H59: 7633370000 | I59: RCPw/R3-47 | J59: No | K59: No | L59: Yes | M59: No | N59: No | O59: Yes | P59: N | Q59: 45958 | V59: =IF( OR( ISNUMBER(SEARCH("unable to locate acct", tblDocketedComments[[#This Row],[Docketed Consumer Comments]])), ISNUMBER(SEARCH("unknown", tblDocketedComments[[#This Row],[Docketed Consumer Comments]])), ISNUMBER(SEARCH("inactive", tblDocketedComments[[#This Row],[Docketed Consumer Comments]])) ), 0, 1 ) -> 1
A60: 45848 | B60: Dushoff | C60: Rachel | D60: Corrales, NM | E60: 87048 | F60: Opposed | G60: https://images.edocket.azcc.gov/docketpdf/E000045226.pdf | H60: Unable to Locate Acct | V60: =IF( OR( ISNUMBER(SEARCH("unable to locate acct", tblDocketedComments[[#This Row],[Docketed Consumer Comments]])), ISNUMBER(SEARCH("unknown", tblDocketedComments[[#This Row],[Docketed Consumer Comments]])), ISNUMBER(SEARCH("inactive", tblDocketedComments[[#This Row],[Docketed Consumer Comments]])) ), 0, 1 ) -> 1
A61: 45848 | B61: Wiehl | C61: Sarah | D61: Sedona | E61: 86336 | F61: Opposed / Greed | G61: https://images.edocket.azcc.gov/docketpdf/E000045226.pdf | H61: Inactive Acct | V61: =IF( OR( ISNUMBER(SEARCH("unable to locate acct", tblDocketedComments[[#This Row],[Docketed Consumer Comments]])), ISNUMBER(SEARCH("unknown", tblDocketedComments[[#This Row],[Docketed Consumer Comments]])), ISNUMBER(SEARCH("inactive", tblDocketedComments[[#This Row],[Docketed Consumer Comments]])) ), 0, 1 ) -> 1
A62: 45852 | B62: Rizzi | C62: Carol | D62: Unknown | E62: Unknown | F62: Opposed | G62: https://images.edocket.azcc.gov/docketpdf/E000045267.pdf | H62: 3049940000 | I62: R-XS | J62: No | K62: No | L62: AMI Opt Out | M62: No | N62: No | O62: Yes | P62: N | Q62: 45958 | V62: =IF( OR( ISNUMBER(SEARCH("unable to locate acct", tblDocketedComments[[#This Row],[Docketed Consumer Comments]])), ISNUMBER(SEARCH("unknown", tblDocketedComments[[#This Row],[Docketed Consumer Comments]])), ISNUMBER(SEARCH("inactive", tblDocketedComments[[#This Row],[Docketed Consumer Comments]])) ), 0, 1 ) -> 1
A63: 45852 | B63: Snyder | C63: Steven | D63: Prescott Valley | E63: 86314 | F63: Opposed | G63: https://images.edocket.azcc.gov/docketpdf/E000045267.pdf | H63: 3736855436 | I63: RCPw/R3-47 | J63: No | K63: No | L63: Yes | M63: No | N63: No | O63: Yes | P63: N | Q63: 45958 | V63: =IF( OR( ISNUMBER(SEARCH("unable to locate acct", tblDocketedComments[[#This Row],[Docketed Consumer Comments]])), ISNUMBER(SEARCH("unknown", tblDocketedComments[[#This Row],[Docketed Consumer Comments]])), ISNUMBER(SEARCH("inactive", tblDocketedComments[[#This Row],[Docketed Consumer Comments]])) ), 0, 1 ) -> 1
A64: 45854 | B64: Starr | C64: Valerie | D64: Payson | E64: 85541 | F64: Opposed / Greed | G64: https://images.edocket.azcc.gov/docketpdf/E000045309.pdf | H64: 8135798464 | I64: R-BASICL | J64: No | K64: No | L64: No MEP R3-47 ($337.28) | M64: No | N64: No | O64: Yes | P64: 45964 | Q64: 45958 | R64: 11/03 - LM | U64: Estimated savings $432.84/12 = $36.07 potential monthly savings on MEP | V64: =IF( OR( ISNUMBER(SEARCH("unable to locate acct", tblDocketedComments[[#This Row],[Docketed Consumer Comments]])), ISNUMBER(SEARCH("unknown", tblDocketedComments[[#This Row],[Docketed Consumer Comments]])), ISNUMBER(SEARCH("inactive", tblDocketedComments[[#This Row],[Docketed Consumer Comments]])) ), 0, 1 ) -> 1
A65: 45859 | B65: Hill | C65: Teresa | D65: Phoenix | E65: 85029 | F65: Senior/Fixed Income/ Data Centers | G65: https://images.edocket.azcc.gov/docketpdf/E000045376.pdf | H65: 5307300000 | I65: R3-47 | J65: No | K65: No | L65: No MEP R-XS ($136.97) | M65: No | N65: No | O65: Yes | P65: 45964 | Q65: 45958 | R65: 11/03 - Customer will callback at a more convenient time to discuss MEP | V65: =IF( OR( ISNUMBER(SEARCH("unable to locate acct", tblDocketedComments[[#This Row],[Docketed Consumer Comments]])), ISNUMBER(SEARCH("unknown", tblDocketedComments[[#This Row],[Docketed Consumer Comments]])), ISNUMBER(SEARCH("inactive", tblDocketedComments[[#This Row],[Docketed Consumer Comments]])) ), 0, 1 ) -> 1
A66: 45861 | B66: Seabrook | C66: Michelle | D66: Phoenix | E66: 85054 | F66: Opposed | G66: https://images.edocket.azcc.gov/docketpdf/E000045426.pdf | H66: 3616936085 | I66: R-BASICL | J66: No | K66: No | L66: No MEP R-BASIC ($170.13) | M66: No | N66: No | O66: Yes | P66: N | Q66: 45958 | R66: Will be automatically reassigned soon | V66: =IF( OR( ISNUMBER(SEARCH("unable to locate acct", tblDocketedComments[[#This Row],[Docketed Consumer Comments]])), ISNUMBER(SEARCH("unknown", tblDocketedComments[[#This Row],[Docketed Consumer Comments]])), ISNUMBER(SEARCH("inactive", tblDocketedComments[[#This Row],[Docketed Consumer Comments]])) ), 0, 1 ) -> 1
A67: 45861 | B67: Grube | C67: Wayne | D67: Unknown | E67: Unknown | F67: Get more nuclear online | G67: https://images.edocket.azcc.gov/docketpdf/E000045426.pdf | H67: Unable to Locate Acct | V67: =IF( OR( ISNUMBER(SEARCH("unable to locate acct", tblDocketedComments[[#This Row],[Docketed Consumer Comments]])), ISNUMBER(SEARCH("unknown", tblDocketedComments[[#This Row],[Docketed Consumer Comments]])), ISNUMBER(SEARCH("inactive", tblDocketedComments[[#This Row],[Docketed Consumer Comments]])) ), 0, 1 ) -> 1
A68: 45883 | B68: Sternberg | C68: Karen | D68: Sedona | E68: 85336 | F68: Comments are about water rates | G68: https://images.edocket.azcc.gov/docketpdf/E000045814.pdf | H68: 4285810000 | I68: R-XS | J68: No | K68: No | L68: Yes | M68: No | N68: No | O68: Yes | P68: N | Q68: 45958 | U68: Comments are about water rate increases | V68: =IF( OR( ISNUMBER(SEARCH("unable to locate acct", tblDocketedComments[[#This Row],[Docketed Consumer Comments]])), ISNUMBER(SEARCH("unknown", tblDocketedComments[[#This Row],[Docketed Consumer Comments]])), ISNUMBER(SEARCH("inactive", tblDocketedComments[[#This Row],[Docketed Consumer Comments]])) ), 0, 1 ) -> 1
A69: 45883 | B69: Waterman | C69: Kathleen | D69: Phoenix | E69: 85023 | F69: Opposed | G69: https://images.edocket.azcc.gov/docketpdf/E000045814.pdf | H69: Unable to Locate Acct | V69: =IF( OR( ISNUMBER(SEARCH("unable to locate acct", tblDocketedComments[[#This Row],[Docketed Consumer Comments]])), ISNUMBER(SEARCH("unknown", tblDocketedComments[[#This Row],[Docketed Consumer Comments]])), ISNUMBER(SEARCH("inactive", tblDocketedComments[[#This Row],[Docketed Consumer Comments]])) ), 0, 1 ) -> 1
A70: 45895 | B70: Coleman | C70: John | D70: Maricopa | E70: 85139 | F70: Neutral | G70: https://images.edocket.azcc.gov/docketpdf/E000046007.pdf | H70: Unable to Locate Acct | V70: =IF( OR( ISNUMBER(SEARCH("unable to locate acct", tblDocketedComments[[#This Row],[Docketed Consumer Comments]])), ISNUMBER(SEARCH("unknown", tblDocketedComments[[#This Row],[Docketed Consumer Comments]])), ISNUMBER(SEARCH("inactive", tblDocketedComments[[#This Row],[Docketed Consumer Comments]])) ), 0, 1 ) -> 1
A71: 45898 | B71: Hines | C71: Rohna | D71: Unknown | E71: Unknown | F71: Opposed | G71: https://images.edocket.azcc.gov/docketpdf/E000046100.pdf | H71: 9376851000 | I71: RTOUE47 | J71: Yes | K71: No | L71: No MEP R-XS($77.28) | M71: No | N71: No | O71: Yes | P71: N | Q71: 45958 | V71: =IF( OR( ISNUMBER(SEARCH("unable to locate acct", tblDocketedComments[[#This Row],[Docketed Consumer Comments]])), ISNUMBER(SEARCH("unknown", tblDocketedComments[[#This Row],[Docketed Consumer Comments]])), ISNUMBER(SEARCH("inactive", tblDocketedComments[[#This Row],[Docketed Consumer Comments]])) ), 0, 1 ) -> 1
A72: 45902 | B72: Lovato | C72: Tiffany | D72: Surprise | E72: 85374 | F72: Opposed | G72: https://images.edocket.azcc.gov/docketpdf/E000046155.pdf | H72: 2721067262 | I72: R-BASIC | J72: N | K72: No | L72: Yes | M72: No | N72: No | O72: Yes | P72: N | Q72: 45967 | V72: =IF( OR( ISNUMBER(SEARCH("unable to locate acct", tblDocketedComments[[#This Row],[Docketed Consumer Comments]])), ISNUMBER(SEARCH("unknown", tblDocketedComments[[#This Row],[Docketed Consumer Comments]])), ISNUMBER(SEARCH("inactive", tblDocketedComments[[#This Row],[Docketed Consumer Comments]])) ), 0, 1 ) -> 1
A73: 45902 | B73: DeLano | C73: James | D73: Scottsdale | E73: 85254 | F73: opposed | G73: https://images.edocket.azcc.gov/docketpdf/E000046155.pdf | H73: Unable to Locate Acct | V73: =IF( OR( ISNUMBER(SEARCH("unable to locate acct", tblDocketedComments[[#This Row],[Docketed Consumer Comments]])), ISNUMBER(SEARCH("unknown", tblDocketedComments[[#This Row],[Docketed Consumer Comments]])), ISNUMBER(SEARCH("inactive", tblDocketedComments[[#This Row],[Docketed Consumer Comments]])) ), 0, 1 ) -> 1
A74: 56859 | B74: King | C74: Debra | D74: Peoria | E74: 85382 | F74: opposed | G74: https://images.edocket.azcc.gov/docketpdf/E000046155.pdf | H74: Unable to Locate Acct | V74: =IF( OR( ISNUMBER(SEARCH("unable to locate acct", tblDocketedComments[[#This Row],[Docketed Consumer Comments]])), ISNUMBER(SEARCH("unknown", tblDocketedComments[[#This Row],[Docketed Consumer Comments]])), ISNUMBER(SEARCH("inactive", tblDocketedComments[[#This Row],[Docketed Consumer Comments]])) ), 0, 1 ) -> 1
A75: 45902 | B75: Wray | C75: Brett | D75: Surprise | E75: 85387 | F75: Form letter | G75: https://images.edocket.azcc.gov/docketpdf/E000046155.pdf | H75: Unable to Locate Acct | V75: =IF( OR( ISNUMBER(SEARCH("unable to locate acct", tblDocketedComments[[#This Row],[Docketed Consumer Comments]])), ISNUMBER(SEARCH("unknown", tblDocketedComments[[#This Row],[Docketed Consumer Comments]])), ISNUMBER(SEARCH("inactive", tblDocketedComments[[#This Row],[Docketed Consumer Comments]])) ), 0, 1 ) -> 1
A76: 45902 | B76: Read | C76: David | D76: Peoria | E76: 85381 | F76: Opposed | G76: https://images.edocket.azcc.gov/docketpdf/E000046155.pdf | H76: 5237011424 | I76: RTOUE47 | J76: No | K76: No | L76: Yes | M76: No | N76: No | O76: Yes | P76: N | Q76: 45958 | V76: =IF( OR( ISNUMBER(SEARCH("unable to locate acct", tblDocketedComments[[#This Row],[Docketed Consumer Comments]])), ISNUMBER(SEARCH("unknown", tblDocketedComments[[#This Row],[Docketed Consumer Comments]])), ISNUMBER(SEARCH("inactive", tblDocketedComments[[#This Row],[Docketed Consumer Comments]])) ), 0, 1 ) -> 1
A77: 45902 | B77: First | C77: Lakisha | D77: Buckeye | E77: 85326 | F77: Opposed | G77: https://images.edocket.azcc.gov/docketpdf/E000046155.pdf | H77: Unable to Locate Acct | V77: =IF( OR( ISNUMBER(SEARCH("unable to locate acct", tblDocketedComments[[#This Row],[Docketed Consumer Comments]])), ISNUMBER(SEARCH("unknown", tblDocketedComments[[#This Row],[Docketed Consumer Comments]])), ISNUMBER(SEARCH("inactive", tblDocketedComments[[#This Row],[Docketed Consumer Comments]])) ), 0, 1 ) -> 1
A78: 45902 | B78: Huynh | C78: Nam | D78: Buckeye | E78: 85326 | F78: Opposed | G78: https://images.edocket.azcc.gov/docketpdf/E000046155.pdf | H78: 6062541000 | I78: R3-47 | J78: No | K78: No | L78: Yes | M78: No | N78: No | O78: Yes | P78: N | Q78: 45958 | V78: =IF( OR( ISNUMBER(SEARCH("unable to locate acct", tblDocketedComments[[#This Row],[Docketed Consumer Comments]])), ISNUMBER(SEARCH("unknown", tblDocketedComments[[#This Row],[Docketed Consumer Comments]])), ISNUMBER(SEARCH("inactive", tblDocketedComments[[#This Row],[Docketed Consumer Comments]])) ), 0, 1 ) -> 1
A79: 45902 | B79: Walker | C79: William | D79: Phoenix | E79: 85016 | F79: Form letter | G79: https://images.edocket.azcc.gov/docketpdf/E000046155.pdf | H79: Multiple Cust Found | V79: =IF( OR( ISNUMBER(SEARCH("unable to locate acct", tblDocketedComments[[#This Row],[Docketed Consumer Comments]])), ISNUMBER(SEARCH("unknown", tblDocketedComments[[#This Row],[Docketed Consumer Comments]])), ISNUMBER(SEARCH("inactive", tblDocketedComments[[#This Row],[Docketed Consumer Comments]])) ), 0, 1 ) -> 1
A80: 45902 | B80: Simmons | C80: Jennifer | D80: Scottsdale | E80: 85260 | F80: Opposed | G80: https://images.edocket.azcc.gov/docketpdf/E000046155.pdf | H80: 2882986476 | I80: RTOUE47 | J80: No | K80: No | L80: No MEP R3-47 ($61.45) | M80: No | N80: No | O80: Yes | P80: N | Q80: 45957 | V80: =IF( OR( ISNUMBER(SEARCH("unable to locate acct", tblDocketedComments[[#This Row],[Docketed Consumer Comments]])), ISNUMBER(SEARCH("unknown", tblDocketedComments[[#This Row],[Docketed Consumer Comments]])), ISNUMBER(SEARCH("inactive", tblDocketedComments[[#This Row],[Docketed Consumer Comments]])) ), 0, 1 ) -> 1
A81: 45902 | B81: Wood | C81: Ethan | D81: Phoenix | E81: 85085 | F81: Form letter | G81: https://images.edocket.azcc.gov/docketpdf/E000046155.pdf | H81: 7846277073 | I81: R3-47 | J81: No | K81: No | L81: Yes | M81: No | N81: No | O81: Yes | P81: N | Q81: 45958 | V81: =IF( OR( ISNUMBER(SEARCH("unable to locate acct", tblDocketedComments[[#This Row],[Docketed Consumer Comments]])), ISNUMBER(SEARCH("unknown", tblDocketedComments[[#This Row],[Docketed Consumer Comments]])), ISNUMBER(SEARCH("inactive", tblDocketedComments[[#This Row],[Docketed Consumer Comments]])) ), 0, 1 ) -> 1
A82: 45902 | B82: Keller | C82: John | D82: Phoenix | E82: 85027 | F82: Opposed | G82: https://images.edocket.azcc.gov/docketpdf/E000046155.pdf | H82: 7692260000 | I82: R3-47 | J82: No | K82: No | L82: Yes | M82: No | N82: No | O82: Yes | P82: N | Q82: 45958 | V82: =IF( OR( ISNUMBER(SEARCH("unable to locate acct", tblDocketedComments[[#This Row],[Docketed Consumer Comments]])), ISNUMBER(SEARCH("unknown", tblDocketedComments[[#This Row],[Docketed Consumer Comments]])), ISNUMBER(SEARCH("inactive", tblDocketedComments[[#This Row],[Docketed Consumer Comments]])) ), 0, 1 ) -> 1
A83: 45902 | B83: Vint | C83: Shannon | D83: Phoenix | E83: 85027 | F83: Form letter | G83: https://images.edocket.azcc.gov/docketpdf/E000046155.pdf | H83: 1113187095 | I83: R-BASIC | J83: No | K83: No | L83: Yes | M83: No | N83: No | O83: Yes | P83: N | Q83: 45958 | V83: =IF( OR( ISNUMBER(SEARCH("unable to locate acct", tblDocketedComments[[#This Row],[Docketed Consumer Comments]])), ISNUMBER(SEARCH("unknown", tblDocketedComments[[#This Row],[Docketed Consumer Comments]])), ISNUMBER(SEARCH("inactive", tblDocketedComments[[#This Row],[Docketed Consumer Comments]])) ), 0, 1 ) -> 1
A84: 45902 | B84: Snyder | C84: Corey | D84: Phoenix | E84: 85008 | F84: Form letter | G84: https://images.edocket.azcc.gov/docketpdf/E000046155.pdf | H84: 6584830202 | I84: R-BASICL | J84: No | K84: No | L84: No MEP R3-47 ($1,048.14) | M84: No | N84: No | O84: Yes | P84: 45932 | Q84: 45685 | R84: 10/02 - LM | V84: =IF( OR( ISNUMBER(SEARCH("unable to locate acct", tblDocketedComments[[#This Row],[Docketed Consumer Comments]])), ISNUMBER(SEARCH("unknown", tblDocketedComments[[#This Row],[Docketed Consumer Comments]])), ISNUMBER(SEARCH("inactive", tblDocketedComments[[#This Row],[Docketed Consumer Comments]])) ), 0, 1 ) -> 1
A85: 45902 | B85: Alexander | C85: Jacob | D85: Peoria | E85: 85345 | F85: Form letter | G85: https://images.edocket.azcc.gov/docketpdf/E000046155.pdf | H85: 6178141000 | I85: R3-47 | J85: No | K85: No | L85: Yes | M85: Yes | N85: 175.19 | O85: Yes | P85: N | Q85: 45958 | V85: =IF( OR( ISNUMBER(SEARCH("unable to locate acct", tblDocketedComments[[#This Row],[Docketed Consumer Comments]])), ISNUMBER(SEARCH("unknown", tblDocketedComments[[#This Row],[Docketed Consumer Comments]])), ISNUMBER(SEARCH("inactive", tblDocketedComments[[#This Row],[Docketed Consumer Comments]])) ), 0, 1 ) -> 1
A86: 45902 | B86: Poe | C86: Leighton | D86: Phoenix | E86: 85004 | F86: Form letter | G86: https://images.edocket.azcc.gov/docketpdf/E000046155.pdf | H86: 5855923100 | I86: R-BASIC | J86: No | K86: No | L86: No MEP RTOUE47($74.06) | M86: No | N86: No | O86: Yes | P86: N | Q86: 45958 | V86: =IF( OR( ISNUMBER(SEARCH("unable to locate acct", tblDocketedComments[[#This Row],[Docketed Consumer Comments]])), ISNUMBER(SEARCH("unknown", tblDocketedComments[[#This Row],[Docketed Consumer Comments]])), ISNUMBER(SEARCH("inactive", tblDocketedComments[[#This Row],[Docketed Consumer Comments]])) ), 0, 1 ) -> 1
A87: 45902 | B87: Charapata | C87: Maxwell | D87: Phoenix | E87: 85027 | F87: Opposed | G87: https://images.edocket.azcc.gov/docketpdf/E000046155.pdf | H87: 2779220471 | I87: RTOUE47 | J87: No | K87: No | L87: No-MEP R3-47(23.66) | M87: No | N87: No | O87: Yes | P87: N | Q87: 45958 | V87: =IF( OR( ISNUMBER(SEARCH("unable to locate acct", tblDocketedComments[[#This Row],[Docketed Consumer Comments]])), ISNUMBER(SEARCH("unknown", tblDocketedComments[[#This Row],[Docketed Consumer Comments]])), ISNUMBER(SEARCH("inactive", tblDocketedComments[[#This Row],[Docketed Consumer Comments]])) ), 0, 1 ) -> 1
A88: 45902 | B88: Lafond | C88: Ciara | D88: Buckeye | E88: 85326 | F88: Opposed | G88: https://images.edocket.azcc.gov/docketpdf/E000046155.pdf | H88: 7245245699 | I88: RTOUE47 | J88: No | K88: No | L88: Yes | M88: No | N88: No | O88: Yes | P88: N | Q88: 45958 | V88: =IF( OR( ISNUMBER(SEARCH("unable to locate acct", tblDocketedComments[[#This Row],[Docketed Consumer Comments]])), ISNUMBER(SEARCH("unknown", tblDocketedComments[[#This Row],[Docketed Consumer Comments]])), ISNUMBER(SEARCH("inactive", tblDocketedComments[[#This Row],[Docketed Consumer Comments]])) ), 0, 1 ) -> 1
A89: 45902 | B89: O'Gorman | C89: Erin | D89: Prescott Valley | E89: 86314 | F89: Opposed | G89: https://images.edocket.azcc.gov/docketpdf/E000046155.pdf | H89: 0644019886 | I89: R-BASIC | J89: No | K89: No | L89: No-MEP R3-47($141.01) | M89: Yes | N89: 605.93 | O89: Yes | P89: 45932 | R89: 10/02 - LM | V89: =IF( OR( ISNUMBER(SEARCH("unable to locate acct", tblDocketedComments[[#This Row],[Docketed Consumer Comments]])), ISNUMBER(SEARCH("unknown", tblDocketedComments[[#This Row],[Docketed Consumer Comments]])), ISNUMBER(SEARCH("inactive", tblDocketedComments[[#This Row],[Docketed Consumer Comments]])) ), 0, 1 ) -> 1
A90: 45902 | B90: Lara | C90: Gerardo | D90: Glendale | E90: 85306 | F90: Form letter | G90: https://images.edocket.azcc.gov/docketpdf/E000046155.pdf | H90: 6799425771 | I90: R-BASICL | J90: No | K90: No | L90: No MEP R3-47(249.30) | M90: Yes | N90: 591.48 | O90: Yes | P90: 45932 | Q90: 45968 | R90: 10/02 - LM - COR initiated rate change to MEP on 10/23 | V90: =IF( OR( ISNUMBER(SEARCH("unable to locate acct", tblDocketedComments[[#This Row],[Docketed Consumer Comments]])), ISNUMBER(SEARCH("unknown", tblDocketedComments[[#This Row],[Docketed Consumer Comments]])), ISNUMBER(SEARCH("inactive", tblDocketedComments[[#This Row],[Docketed Consumer Comments]])) ), 0, 1 ) -> 1
A91: 45902 | B91: Howell | C91: Chris | D91: Surprise | E91: 85387 | F91: Form letter | G91: https://images.edocket.azcc.gov/docketpdf/E000046155.pdf | H91: 6635023227 | I91: RTOUE47 | J91: No | K91: No | L91: No MEP R3-47($2.91) | M91: No | N91: No | O91: Yes | P91: N | Q91: 45968 | V91: =IF( OR( ISNUMBER(SEARCH("unable to locate acct", tblDocketedComments[[#This Row],[Docketed Consumer Comments]])), ISNUMBER(SEARCH("unknown", tblDocketedComments[[#This Row],[Docketed Consumer Comments]])), ISNUMBER(SEARCH("inactive", tblDocketedComments[[#This Row],[Docketed Consumer Comments]])) ), 0, 1 ) -> 1
A92: 45902 | B92: Torres | C92: Kyle | D92: Phoenix | E92: 85020 | F92: Form letter | G92: https://images.edocket.azcc.gov/docketpdf/E000046155.pdf | H92: 9505905227 | I92: R-BASIC | J92: No | K92: No | L92: No MEP R3-47($18.99) | M92: No | N92: No | O92: Yes | P92: N | Q92: 45968 | V92: =IF( OR( ISNUMBER(SEARCH("unable to locate acct", tblDocketedComments[[#This Row],[Docketed Consumer Comments]])), ISNUMBER(SEARCH("unknown", tblDocketedComments[[#This Row],[Docketed Consumer Comments]])), ISNUMBER(SEARCH("inactive", tblDocketedComments[[#This Row],[Docketed Consumer Comments]])) ), 0, 1 ) -> 1
A93: 45902 | B93: Tighe | C93: Paul | D93: Litchfield Park | E93: 85340 | F93: Opposed | G93: https://images.edocket.azcc.gov/docketpdf/E000046155.pdf | H93: 9937021000 | I93: R3-47 | J93: No | K93: No | L93: Yes | M93: No | N93: No | O93: Yes | P93: N | Q93: 45968 | V93: =IF( OR( ISNUMBER(SEARCH("unable to locate acct", tblDocketedComments[[#This Row],[Docketed Consumer Comments]])), ISNUMBER(SEARCH("unknown", tblDocketedComments[[#This Row],[Docketed Consumer Comments]])), ISNUMBER(SEARCH("inactive", tblDocketedComments[[#This Row],[Docketed Consumer Comments]])) ), 0, 1 ) -> 1
A94: 45902 | B94: Ward | C94: Karen | D94: Surprise | E94: 85387 | F94: Opposed | G94: https://images.edocket.azcc.gov/docketpdf/E000046155.pdf | H94: 7949496672 | I94: R-XS | J94: Yes | K94: No | L94: Yes | M94: No | N94: No | O94: Yes | P94: N | Q94: 45968 | V94: =IF( OR( ISNUMBER(SEARCH("unable to locate acct", tblDocketedComments[[#This Row],[Docketed Consumer Comments]])), ISNUMBER(SEARCH("unknown", tblDocketedComments[[#This Row],[Docketed Consumer Comments]])), ISNUMBER(SEARCH("inactive", tblDocketedComments[[#This Row],[Docketed Consumer Comments]])) ), 0, 1 ) -> 1
A95: 45902 | B95: Anderson | C95: James | D95: Phoenix | E95: 85020 | F95: Form letter | G95: https://images.edocket.azcc.gov/docketpdf/E000046155.pdf | H95: Multiple Cust Found | V95: =IF( OR( ISNUMBER(SEARCH("unable to locate acct", tblDocketedComments[[#This Row],[Docketed Consumer Comments]])), ISNUMBER(SEARCH("unknown", tblDocketedComments[[#This Row],[Docketed Consumer Comments]])), ISNUMBER(SEARCH("inactive", tblDocketedComments[[#This Row],[Docketed Consumer Comments]])) ), 0, 1 ) -> 1
A96: 45902 | B96: Nash | C96: Destiny | D96: Chandler | E96: 85225 | F96: Opposed | G96: https://images.edocket.azcc.gov/docketpdf/E000046155.pdf | H96: 8712521000 | I96: R3-47 | J96: No | K96: No | L96: Yes | M96: No | N96: No | O96: Yes | P96: N | Q96: 45968 | V96: =IF( OR( ISNUMBER(SEARCH("unable to locate acct", tblDocketedComments[[#This Row],[Docketed Consumer Comments]])), ISNUMBER(SEARCH("unknown", tblDocketedComments[[#This Row],[Docketed Consumer Comments]])), ISNUMBER(SEARCH("inactive", tblDocketedComments[[#This Row],[Docketed Consumer Comments]])) ), 0, 1 ) -> 1
A97: 45902 | B97: Wilkymacky | C97: Abby | D97: Phoenix | E97: 85006 | F97: Opposed | G97: https://images.edocket.azcc.gov/docketpdf/E000046155.pdf | H97: 2584149193 | I97: RTOUE47 | J97: No | K97: No | L97: Yes | M97: No | N97: No | O97: Yes | P97: N | Q97: 45968 | V97: =IF( OR( ISNUMBER(SEARCH("unable to locate acct", tblDocketedComments[[#This Row],[Docketed Consumer Comments]])), ISNUMBER(SEARCH("unknown", tblDocketedComments[[#This Row],[Docketed Consumer Comments]])), ISNUMBER(SEARCH("inactive", tblDocketedComments[[#This Row],[Docketed Consumer Comments]])) ), 0, 1 ) -> 1
A98: 45902 | B98: Melendez | C98: Jose | D98: Surprise | E98: 85388 | F98: Opposed | G98: https://images.edocket.azcc.gov/docketpdf/E000046155.pdf | H98: 3811821000 | I98: RTOUE47 | J98: No | K98: No | L98: No MEP R3-47 ($128.91) | M98: No | N98: No | O98: Yes | P98: 45932 | Q98: 45968 | R98: 10/02 - LM | V98: =IF( OR( ISNUMBER(SEARCH("unable to locate acct", tblDocketedComments[[#This Row],[Docketed Consumer Comments]])), ISNUMBER(SEARCH("unknown", tblDocketedComments[[#This Row],[Docketed Consumer Comments]])), ISNUMBER(SEARCH("inactive", tblDocketedComments[[#This Row],[Docketed Consumer Comments]])) ), 0, 1 ) -> 1
A99: 45902 | B99: Crosbie | C99: David | D99: Goodyear | E99: 85338 | F99: Opposed | G99: https://images.edocket.azcc.gov/docketpdf/E000046155.pdf | H99: 0814350000 | I99: RTOUE47 | J99: No | K99: No | L99: Yes | M99: No | N99: No | O99: Yes | P99: N | Q99: 45968 | V99: =IF( OR( ISNUMBER(SEARCH("unable to locate acct", tblDocketedComments[[#This Row],[Docketed Consumer Comments]])), ISNUMBER(SEARCH("unknown", tblDocketedComments[[#This Row],[Docketed Consumer Comments]])), ISNUMBER(SEARCH("inactive", tblDocketedComments[[#This Row],[Docketed Consumer Comments]])) ), 0, 1 ) -> 1
A100: 45902 | B100: Kong | C100: Joseph | D100: Peoria | E100: 85345 | F100: Opposed | G100: https://images.edocket.azcc.gov/docketpdf/E000046155.pdf | H100: Unable to Locate Acct | V100: =IF( OR( ISNUMBER(SEARCH("unable to locate acct", tblDocketedComments[[#This Row],[Docketed Consumer Comments]])), ISNUMBER(SEARCH("unknown", tblDocketedComments[[#This Row],[Docketed Consumer Comments]])), ISNUMBER(SEARCH("inactive", tblDocketedComments[[#This Row],[Docketed Consumer Comments]])) ), 0, 1 ) -> 1
...

Sheet 📋 Build Guides
A1: ═══════════════════════════════════════════════
A2: POWER APPS BUILD GUIDE — APS Rate Case Call Tracker
A3: ═══════════════════════════════════════════════
A5: PREREQUISITES
A6: • This Excel file must be on SharePoint or OneDrive for Business
A7: • You need Power Apps access (included with M365 Business/Enterprise)
A8: • The file has an Excel Table called tblCallTracker on the Call Tracker sheet
A10: STEP 1: CREATE THE APP (5 min)
A11: 1. Go to make.powerapps.com
A12: 2. Click + Create → Start with data → Excel
A13: 3. Connect to your SharePoint site → navigate to this Excel file
A14: 4. Select tblCallTracker → Click Connect
... A145: Issue | Text | Customer complaint | Read-only

Sheet Call Queue
A1: Date Added | B1: Last Name | C1: First Name | D1: City | E1: Zip code | F1: Issue / Complaint | G1: 📄 Link | H1: Account # | I1: Rate Plan | J1: E3? | K1: MCP? | L1: MEP Status | M1: PA? | N1: Payoff Balance | O1: Team Reviewed | P1: Response Y(date)/N | Q1: Last date of Account review | R1: Notes | S1: ACC Inquiry Sent to CA | T1: APS CA Referral | U1: Comments | V1: MEP Status (Clean) | W1: ✏️ Associate | X1: ✏️ Date Called | Y1: ✏️ VM? | Z1: ✏️ Outcome | AA1: ✏️ Notes | AB1: Priority
A2: {=IFERROR(_xlfn._xlws.FILTER('Docketed Comments'!A2:A1949,('Docketed Comments'!H2:H1949<>"Unable to Locate Acct")*('Docketed Comments'!H2:H1949<>"")*('Docketed Comments'!H2:H1949<>0)*(_xlfn.XMATCH('Docketed Comments'!H2:H1949,'Docketed Comments'!H$2:H$1949)=_xlfn.SEQUENCE(1948))),"")} -> 45797 | B2: {=IFERROR(_xlfn._xlws.FILTER('Docketed Comments'!B2:B1949,('Docketed Comments'!H2:H1949<>"Unable to Locate Acct")*('Docketed Comments'!H2:H1949<>"")*('Docketed Comments'!H2:H1949<>0)*(_xlfn.XMATCH('Docketed Comments'!H2:H1949,'Docketed Comments'!H$2:H$1949)=_xlfn.SEQUENCE(1948))),"")} -> Wall | C2: {=IFERROR(_xlfn._xlws.FILTER('Docketed Comments'!C2:C1949,('Docketed Comments'!H2:H1949<>"Unable to Locate Acct")*('Docketed Comments'!H2:H1949<>"")*('Docketed Comments'!H2:H1949<>0)*(_xlfn.XMATCH('Docketed Comments'!H2:H1949,'Docketed Comments'!H$2:H$1949)=_xlfn.SEQUENCE(1948))),"")} -> Rae | D2: {=IFERROR(_xlfn._xlws.FILTER('Docketed Comments'!D2:D1949,('Docketed Comments'!H2:H1949<>"Unable to Locate Acct")*('Docketed Comments'!H2:H1949<>"")*('Docketed Comments'!H2:H1949<>0)*(_xlfn.XMATCH('Docketed Comments'!H2:H1949,'Docketed Comments'!H$2:H$1949)=_xlfn.SEQUENCE(1948))),"")} -> Glendale | E2: {=IFERROR(_xlfn._xlws.FILTER('Docketed Comments'!E2:E1949,('Docketed Comments'!H2:H1949<>"Unable to Locate Acct")*('Docketed Comments'!H2:H1949<>"")*('Docketed Comments'!H2:H1949<>0)*(_xlfn.XMATCH('Docketed Comments'!H2:H1949,'Docketed Comments'!H$2:H$1949)=_xlfn.SEQUENCE(1948))),"")} -> Unknown | F2: {=IFERROR(_xlfn._xlws.FILTER('Docketed Comments'!F2:F1949,('Docketed Comments'!H2:H1949<>"Unable to Locate Acct")*('Docketed Comments'!H2:H1949<>"")*('Docketed Comments'!H2:H1949<>0)*(_xlfn.XMATCH('Docketed Comments'!H2:H1949,'Docketed Comments'!H$2:H$1949)=_xlfn.SEQUENCE(1948))),"")} -> Opposed | G2: {=IFERROR(_xlfn._xlws.FILTER('Docketed Comments'!G2:G1949,('Docketed Comments'!H2:H1949<>"Unable to Locate Acct")*('Docketed Comments'!H2:H1949<>"")*('Docketed Comments'!H2:H1949<>0)*(_xlfn.XMATCH('Docketed Comments'!H2:H1949,'Docketed Comments'!H$2:H$1949)=_xlfn.SEQUENCE(1948))),"")} -> https://images.edocket.azcc.gov/docketpdf/E000044126.pdf | H2: 5494061000 | I2: {=IFERROR(_xlfn._xlws.FILTER('Docketed Comments'!I2:I1949,('Docketed Comments'!H2:H1949<>"Unable to Locate Acct")*('Docketed Comments'!H2:H1949<>"")*('Docketed Comments'!H2:H1949<>0)*(_xlfn.XMATCH('Docketed Comments'!H2:H1949,'Docketed Comments'!H$2:H$1949)=_xlfn.SEQUENCE(1948))),"")} -> R3-47 | J2: {=IFERROR(_xlfn._xlws.FILTER('Docketed Comments'!J2:J1949,('Docketed Comments'!H2:H1949<>"Unable to Locate Acct")*('Docketed Comments'!H2:H1949<>"")*('Docketed Comments'!H2:H1949<>0)*(_xlfn.XMATCH('Docketed Comments'!H2:H1949,'Docketed Comments'!H$2:H$1949)=_xlfn.SEQUENCE(1948))),"")} -> No | K2: {=IFERROR(_xlfn._xlws.FILTER('Docketed Comments'!K2:K1949,('Docketed Comments'!H2:H1949<>"Unable to Locate Acct")*('Docketed Comments'!H2:H1949<>"")*('Docketed Comments'!H2:H1949<>0)*(_xlfn.XMATCH('Docketed Comments'!H2:H1949,'Docketed Comments'!H$2:H$1949)=_xlfn.SEQUENCE(1948))),"")} -> No | L2: {=IFERROR(_xlfn._xlws.FILTER('Docketed Comments'!L2:L1949,('Docketed Comments'!H2:H1949<>"Unable to Locate Acct")*('Docketed Comments'!H2:H1949<>"")*('Docketed Comments'!H2:H1949<>0)*(_xlfn.XMATCH('Docketed Comments'!H2:H1949,'Docketed Comments'!H$2:H$1949)=_xlfn.SEQUENCE(1948))),"")} -> Yes | M2: {=IFERROR(_xlfn._xlws.FILTER('Docketed Comments'!M2:M1949,('Docketed Comments'!H2:H1949<>"Unable to Locate Acct")*('Docketed Comments'!H2:H1949<>"")*('Docketed Comments'!H2:H1949<>0)*(_xlfn.XMATCH('Docketed Comments'!H2:H1949,'Docketed Comments'!H$2:H$1949)=_xlfn.SEQUENCE(1948))),"")} -> No | N2: {=IFERROR(_xlfn._xlws.FILTER('Docketed Comments'!N2:N1949,('Docketed Comments'!H2:H1949<>"Unable to Locate Acct")*('Docketed Comments'!H2:H1949<>"")*('Docketed Comments'!H2:H1949<>0)*(_xlfn.XMATCH('Docketed Comments'!H2:H1949,'Docketed Comments'!H$2:H$1949)=_xlfn.SEQUENCE(1948))),"")} -> No | O2: {=IFERROR(_xlfn._xlws.FILTER('Docketed Comments'!O2:O1949,('Docketed Comments'!H2:H1949<>"Unable to Locate Acct")*('Docketed Comments'!H2:H1949<>"")*('Docketed Comments'!H2:H1949<>0)*(_xlfn.XMATCH('Docketed Comments'!H2:H1949,'Docketed Comments'!H$2:H$1949)=_xlfn.SEQUENCE(1948))),"")} -> Yes | P2: {=IFERROR(_xlfn._xlws.FILTER('Docketed Comments'!P2:P1949,('Docketed Comments'!H2:H1949<>"Unable to Locate Acct")*('Docketed Comments'!H2:H1949<>"")*('Docketed Comments'!H2:H1949<>0)*(_xlfn.XMATCH('Docketed Comments'!H2:H1949,'Docketed Comments'!H$2:H$1949)=_xlfn.SEQUENCE(1948))),"")} -> N | Q2: {=IFERROR(_xlfn._xlws.FILTER('Docketed Comments'!Q2:Q1949,('Docketed Comments'!H2:H1949<>"Unable to Locate Acct")*('Docketed Comments'!H2:H1949<>"")*('Docketed Comments'!H2:H1949<>0)*(_xlfn.XMATCH('Docketed Comments'!H2:H1949,'Docketed Comments'!H$2:H$1949)=_xlfn.SEQUENCE(1948))),"")} -> 45589 | R2: {=IFERROR(_xlfn._xlws.FILTER('Docketed Comments'!R2:R1949,('Docketed Comments'!H2:H1949<>"Unable to Locate Acct")*('Docketed Comments'!H2:H1949<>"")*('Docketed Comments'!H2:H1949<>0)*(_xlfn.XMATCH('Docketed Comments'!H2:H1949,'Docketed Comments'!H$2:H$1949)=_xlfn.SEQUENCE(1948))),"")} -> 0 | S2: {=IFERROR(_xlfn._xlws.FILTER('Docketed Comments'!S2:S1949,('Docketed Comments'!H2:H1949<>"Unable to Locate Acct")*('Docketed Comments'!H2:H1949<>"")*('Docketed Comments'!H2:H1949<>0)*(_xlfn.XMATCH('Docketed Comments'!H2:H1949,'Docketed Comments'!H$2:H$1949)=_xlfn.SEQUENCE(1948))),"")} -> 0 | T2: {=IFERROR(_xlfn._xlws.FILTER('Docketed Comments'!T2:T1949,('Docketed Comments'!H2:H1949<>"Unable to Locate Acct")*('Docketed Comments'!H2:H1949<>"")*('Docketed Comments'!H2:H1949<>0)*(_xlfn.XMATCH('Docketed Comments'!H2:H1949,'Docketed Comments'!H$2:H$1949)=_xlfn.SEQUENCE(1948))),"")} -> 0 | U2: {=IFERROR(_xlfn._xlws.FILTER('Docketed Comments'!U2:U1949,('Docketed Comments'!H2:H1949<>"Unable to Locate Acct")*('Docketed Comments'!H2:H1949<>"")*('Docketed Comments'!H2:H1949<>0)*(_xlfn.XMATCH('Docketed Comments'!H2:H1949,'Docketed Comments'!H$2:H$1949)=_xlfn.SEQUENCE(1948))),"")} -> Also filed 6/10, 6/12, 6/16 | V2: =IF(OR(LEFT(TRIM(L2),3)="Yes",TRIM(L2)="Y"),"✅ On Best Plan",IF(OR(L2="Frozen Rate",L2="Frozen Plan"),"❄ Frozen Rate",IF(OR(L2="Not able to Compare",L2="Info Not Avail",L2="NA",L2=""),"⚠ Unknown","❌ Not on Best Plan"))) -> ✅ On Best Plan | W2: =IFERROR(_xlfn.XLOOKUP(TEXT(H2,"0000000000"),'📞 Call Tracker'!A$2:A$2000,'📞 Call Tracker'!B$2:B$2000,""),"") -> Joaquin | X2: =IFERROR(_xlfn.XLOOKUP(TEXT(H2,"0000000000"),'📞 Call Tracker'!A$2:A$2000,'📞 Call Tracker'!C$2:C$2000,""),"") -> 45997 | Y2: =IFERROR(_xlfn.XLOOKUP(TEXT(H2,"0000000000"),'📞 Call Tracker'!A$2:A$2000,'📞 Call Tracker'!D$2:D$2000,""),"") -> YES | Z2: =IFERROR(_xlfn.XLOOKUP(TEXT(H2,"0000000000"),'📞 Call Tracker'!A$2:A$2000,'📞 Call Tracker'!E$2:E$2000,""),"") -> 0 | AA2: =IFERROR(_xlfn.XLOOKUP(TEXT(H2,"0000000000"),'📞 Call Tracker'!A$2:A$2000,'📞 Call Tracker'!F$2:F$2000,""),"") -> LEFT VOICE MAIL | AB2: =IF(OR(H2="",X2<>""),99,IF(AND(NOT(OR(LEFT(TRIM(L2),3)="Yes",TRIM(L2)="Y",L2="Frozen Rate",L2="Frozen Plan",L2="Not able to Compare",L2="Info Not Avail",L2="NA",L2="")),AND(N2<>"No",N2<>"")),1,IF(NOT(OR(LEFT(TRIM(L2),3)="Yes",TRIM(L2)="Y",L2="Frozen Rate",L2="Frozen Plan",L2="Not able to Compare",L2="Info Not Avail",L2="NA",L2="")),2,IF(AND(N2<>"No",N2<>""),3,4)))) -> 99
A3: 45798 | B3: Gwiazda | C3: Patricia | D3: Youngtown | E3: 85363 | F3: Opposed | G3: https://images.edocket.azcc.gov/docketpdf/E000044147.pdf | H3: 2074850000 | I3: RCPw/RTOUE47 | J3: No | K3: No | L3: No - MEP is R3-47 ($65.13) | M3: No | N3: No | O3: Yes | P3: N | Q3: 45589 | R3: MEP Annual Savings - $67.68 - Didn't Contact | S3: 0 | T3: 0 | U3: 0 | V3: =IF(OR(LEFT(TRIM(L3),3)="Yes",TRIM(L3)="Y"),"✅ On Best Plan",IF(OR(L3="Frozen Rate",L3="Frozen Plan"),"❄ Frozen Rate",IF(OR(L3="Not able to Compare",L3="Info Not Avail",L3="NA",L3=""),"⚠ Unknown","❌ Not on Best Plan"))) -> ❌ Not on Best Plan | W3: =IFERROR(_xlfn.XLOOKUP(TEXT(H3,"0000000000"),'📞 Call Tracker'!A$2:A$2000,'📞 Call Tracker'!B$2:B$2000,""),"") -> Joaquin | X3: =IFERROR(_xlfn.XLOOKUP(TEXT(H3,"0000000000"),'📞 Call Tracker'!A$2:A$2000,'📞 Call Tracker'!C$2:C$2000,""),"") -> 45997 | Y3: =IFERROR(_xlfn.XLOOKUP(TEXT(H3,"0000000000"),'📞 Call Tracker'!A$2:A$2000,'📞 Call Tracker'!D$2:D$2000,""),"") -> 0 | Z3: =IFERROR(_xlfn.XLOOKUP(TEXT(H3,"0000000000"),'📞 Call Tracker'!A$2:A$2000,'📞 Call Tracker'!E$2:E$2000,""),"") -> 0 | AA3: =IFERROR(_xlfn.XLOOKUP(TEXT(H3,"0000000000"),'📞 Call Tracker'!A$2:A$2000,'📞 Call Tracker'!F$2:F$2000,""),"") -> DID TALK PHILLIPS,CRYSTAL OFFER REVIEW ACCT | AB3: =IF(OR(H3="",X3<>""),99,IF(AND(NOT(OR(LEFT(TRIM(L3),3)="Yes",TRIM(L3)="Y",L3="Frozen Rate",L3="Frozen Plan",L3="Not able to Compare",L3="Info Not Avail",L3="NA",L3="")),AND(N3<>"No",N3<>"")),1,IF(NOT(OR(LEFT(TRIM(L3),3)="Yes",TRIM(L3)="Y",L3="Frozen Rate",L3="Frozen Plan",L3="Not able to Compare",L3="Info Not Avail",L3="NA",L3="")),2,IF(AND(N3<>"No",N3<>""),3,4)))) -> 99
A4: 45798 | B4: Phillips | C4: Crystal | D4: Young | E4: 85554 | F4: Opposed | G4: https://images.edocket.azcc.gov/docketpdf/E000044147.pdf | H4: 4823746138 | I4: R3-47 | J4: No | K4: No | L4: Yes | M4: No | N4: No | O4: Yes | P4: N | Q4: 45589 | R4: 0 | S4: 0 | T4: 0 | U4: 0 | V4: =IF(OR(LEFT(TRIM(L4),3)="Yes",TRIM(L4)="Y"),"✅ On Best Plan",IF(OR(L4="Frozen Rate",L4="Frozen Plan"),"❄ Frozen Rate",IF(OR(L4="Not able to Compare",L4="Info Not Avail",L4="NA",L4=""),"⚠ Unknown","❌ Not on Best Plan"))) -> ✅ On Best Plan | W4: =IFERROR(_xlfn.XLOOKUP(TEXT(H4,"0000000000"),'📞 Call Tracker'!A$2:A$2000,'📞 Call Tracker'!B$2:B$2000,""),"") -> Joaquin | X4: =IFERROR(_xlfn.XLOOKUP(TEXT(H4,"0000000000"),'📞 Call Tracker'!A$2:A$2000,'📞 Call Tracker'!C$2:C$2000,""),"") -> 45997 | Y4: =IFERROR(_xlfn.XLOOKUP(TEXT(H4,"0000000000"),'📞 Call Tracker'!A$2:A$2000,'📞 Call Tracker'!D$2:D$2000,""),"") -> YES | Z4: =IFERROR(_xlfn.XLOOKUP(TEXT(H4,"0000000000"),'📞 Call Tracker'!A$2:A$2000,'📞 Call Tracker'!E$2:E$2000,""),"") -> 0 | AA4: =IFERROR(_xlfn.XLOOKUP(TEXT(H4,"0000000000"),'📞 Call Tracker'!A$2:A$2000,'📞 Call Tracker'!F$2:F$2000,""),"") -> LEFT VOICE MAIL | AB4: =IF(OR(H4="",X4<>""),99,IF(AND(NOT(OR(LEFT(TRIM(L4),3)="Yes",TRIM(L4)="Y",L4="Frozen Rate",L4="Frozen Plan",L4="Not able to Compare",L4="Info Not Avail",L4="NA",L4="")),AND(N4<>"No",N4<>"")),1,IF(NOT(OR(LEFT(TRIM(L4),3)="Yes",TRIM(L4)="Y",L4="Frozen Rate",L4="Frozen Plan",L4="Not able to Compare",L4="Info Not Avail",L4="NA",L4="")),2,IF(AND(N4<>"No",N4<>""),3,4)))) -> 99
A5: 45799 | B5: Beame | C5: Sndney | D5: Unknown | E5: Unknown | F5: Opposed/Senior/fixed income | G5: https://images.edocket.azcc.gov/docketpdf/E000044169.pdf | H5: 8991140195 | I5: R-BASICL | J5: No | K5: No | L5: No - MEP R3-47 ($192.78) | M5: No | N5: No | O5: Yes | P5: 45964 | Q5: 45954 | R5: 11/03 - Customer agreed to change to their MEP | S5: 0 | T5: 0 | U5: Estimated savings $225.94/12 = $18.82 potential monthly savings on MEP | V5: =IF(OR(LEFT(TRIM(L5),3)="Yes",TRIM(L5)="Y"),"✅ On Best Plan",IF(OR(L5="Frozen Rate",L5="Frozen Plan"),"❄ Frozen Rate",IF(OR(L5="Not able to Compare",L5="Info Not Avail",L5="NA",L5=""),"⚠ Unknown","❌ Not on Best Plan"))) -> ❌ Not on Best Plan | W5: =IFERROR(_xlfn.XLOOKUP(TEXT(H5,"0000000000"),'📞 Call Tracker'!A$2:A$2000,'📞 Call Tracker'!B$2:B$2000,""),"") -> Joaquin | X5: =IFERROR(_xlfn.XLOOKUP(TEXT(H5,"0000000000"),'📞 Call Tracker'!A$2:A$2000,'📞 Call Tracker'!C$2:C$2000,""),"") -> 45997 | Y5: =IFERROR(_xlfn.XLOOKUP(TEXT(H5,"0000000000"),'📞 Call Tracker'!A$2:A$2000,'📞 Call Tracker'!D$2:D$2000,""),"") -> 0 | Z5: =IFERROR(_xlfn.XLOOKUP(TEXT(H5,"0000000000"),'📞 Call Tracker'!A$2:A$2000,'📞 Call Tracker'!E$2:E$2000,""),"") -> 0 | AA5: =IFERROR(_xlfn.XLOOKUP(TEXT(H5,"0000000000"),'📞 Call Tracker'!A$2:A$2000,'📞 Call Tracker'!F$2:F$2000,""),"") -> CLOSED ACCT 07/09/2015 | AB5: =IF(OR(H5="",X5<>""),99,IF(AND(NOT(OR(LEFT(TRIM(L5),3)="Yes",TRIM(L5)="Y",L5="Frozen Rate",L5="Frozen Plan",L5="Not able to Compare",L5="Info Not Avail",L5="NA",L5="")),AND(N5<>"No",N5<>"")),1,IF(NOT(OR(LEFT(TRIM(L5),3)="Yes",TRIM(L5)="Y",L5="Frozen Rate",L5="Frozen Plan",L5="Not able to Compare",L5="Info Not Avail",L5="NA",L5="")),2,IF(AND(N5<>"No",N5<>""),3,4)))) -> 99
A6: 45800 | B6: Scoggins | C6: Troy | D6: Phoenix | E6: 85009 | F6: Opposed | G6: https://images.edocket.azcc.gov/docketpdf/E000044282.pdf | H6: Unknown | I6: 0 | J6: 0 | K6: 0 | L6: 0 | M6: 0 | N6: 0 | O6: 0 | P6: 0 | Q6: 0 | R6: 0 | S6: 0 | T6: 0 | U6: Unable to locate account with name provided | V6: =IF(OR(LEFT(TRIM(L6),3)="Yes",TRIM(L6)="Y"),"✅ On Best Plan",IF(OR(L6="Frozen Rate",L6="Frozen Plan"),"❄ Frozen Rate",IF(OR(L6="Not able to Compare",L6="Info Not Avail",L6="NA",L6=""),"⚠ Unknown","❌ Not on Best Plan"))) -> ❌ Not on Best Plan | W6: =IFERROR(_xlfn.XLOOKUP(TEXT(H6,"0000000000"),'📞 Call Tracker'!A$2:A$2000,'📞 Call Tracker'!B$2:B$2000,""),"") | X6: =IFERROR(_xlfn.XLOOKUP(TEXT(H6,"0000000000"),'📞 Call Tracker'!A$2:A$2000,'📞 Call Tracker'!C$2:C$2000,""),"") | Y6: =IFERROR(_xlfn.XLOOKUP(TEXT(H6,"0000000000"),'📞 Call Tracker'!A$2:A$2000,'📞 Call Tracker'!D$2:D$2000,""),"") | Z6: =IFERROR(_xlfn.XLOOKUP(TEXT(H6,"0000000000"),'📞 Call Tracker'!A$2:A$2000,'📞 Call Tracker'!E$2:E$2000,""),"") | AA6: =IFERROR(_xlfn.XLOOKUP(TEXT(H6,"0000000000"),'📞 Call Tracker'!A$2:A$2000,'📞 Call Tracker'!F$2:F$2000,""),"") | AB6: =IF(OR(H6="",X6<>""),99,IF(AND(NOT(OR(LEFT(TRIM(L6),3)="Yes",TRIM(L6)="Y",L6="Frozen Rate",L6="Frozen Plan",L6="Not able to Compare",L6="Info Not Avail",L6="NA",L6="")),AND(N6<>"No",N6<>"")),1,IF(NOT(OR(LEFT(TRIM(L6),3)="Yes",TRIM(L6)="Y",L6="Frozen Rate",L6="Frozen Plan",L6="Not able to Compare",L6="Info Not Avail",L6="NA",L6="")),2,IF(AND(N6<>"No",N6<>""),3,4)))) -> 1
A7: 45804 | B7: Nuccio | C7: Tina | D7: Cave Creek | E7: 85331 | F7: Opposed | G7: https://images.edocket.azcc.gov/docketpdf/E000044298.pdf | H7: 5900820000 | I7: R3-47 | J7: No | K7: No | L7: Yes | M7: No | N7: No | O7: Yes | P7: N | Q7: 45954 | R7: 0 | S7: 0 | T7: 0 | U7: 0 | V7: =IF(OR(LEFT(TRIM(L7),3)="Yes",TRIM(L7)="Y"),"✅ On Best Plan",IF(OR(L7="Frozen Rate",L7="Frozen Plan"),"❄ Frozen Rate",IF(OR(L7="Not able to Compare",L7="Info Not Avail",L7="NA",L7=""),"⚠ Unknown","❌ Not on Best Plan"))) -> ✅ On Best Plan | W7: =IFERROR(_xlfn.XLOOKUP(TEXT(H7,"0000000000"),'📞 Call Tracker'!A$2:A$2000,'📞 Call Tracker'!B$2:B$2000,""),"") -> Michelle | X7: =IFERROR(_xlfn.XLOOKUP(TEXT(H7,"0000000000"),'📞 Call Tracker'!A$2:A$2000,'📞 Call Tracker'!C$2:C$2000,""),"") -> 46060 | Y7: =IFERROR(_xlfn.XLOOKUP(TEXT(H7,"0000000000"),'📞 Call Tracker'!A$2:A$2000,'📞 Call Tracker'!D$2:D$2000,""),"") -> YES | Z7: =IFERROR(_xlfn.XLOOKUP(TEXT(H7,"0000000000"),'📞 Call Tracker'!A$2:A$2000,'📞 Call Tracker'!E$2:E$2000,""),"") -> 0 | AA7: =IFERROR(_xlfn.XLOOKUP(TEXT(H7,"0000000000"),'📞 Call Tracker'!A$2:A$2000,'📞 Call Tracker'!F$2:F$2000,""),"") -> 0 | AB7: =IF(OR(H7="",X7<>""),99,IF(AND(NOT(OR(LEFT(TRIM(L7),3)="Yes",TRIM(L7)="Y",L7="Frozen Rate",L7="Frozen Plan",L7="Not able to Compare",L7="Info Not Avail",L7="NA",L7="")),AND(N7<>"No",N7<>"")),1,IF(NOT(OR(LEFT(TRIM(L7),3)="Yes",TRIM(L7)="Y",L7="Frozen Rate",L7="Frozen Plan",L7="Not able to Compare",L7="Info Not Avail",L7="NA",L7="")),2,IF(AND(N7<>"No",N7<>""),3,4)))) -> 99
A8: 45805 | B8: Henkel | C8: Dean | D8: Unknown | E8: Unknown | F8: Opposed | G8: https://images.edocket.azcc.gov/docketpdf/E000044312.pdf | H8: 1569851000 | I8: R-XS | J8: No | K8: No | L8: Yes | M8: No | N8: No | O8: Yes | P8: N | Q8: 45954 | R8: 0 | S8: 0 | T8: 0 | U8: 0 | V8: =IF(OR(LEFT(TRIM(L8),3)="Yes",TRIM(L8)="Y"),"✅ On Best Plan",IF(OR(L8="Frozen Rate",L8="Frozen Plan"),"❄ Frozen Rate",IF(OR(L8="Not able to Compare",L8="Info Not Avail",L8="NA",L8=""),"⚠ Unknown","❌ Not on Best Plan"))) -> ✅ On Best Plan | W8: =IFERROR(_xlfn.XLOOKUP(TEXT(H8,"0000000000"),'📞 Call Tracker'!A$2:A$2000,'📞 Call Tracker'!B$2:B$2000,""),"") -> 0 | X8: =IFERROR(_xlfn.XLOOKUP(TEXT(H8,"0000000000"),'📞 Call Tracker'!A$2:A$2000,'📞 Call Tracker'!C$2:C$2000,""),"") -> 0 | Y8: =IFERROR(_xlfn.XLOOKUP(TEXT(H8,"0000000000"),'📞 Call Tracker'!A$2:A$2000,'📞 Call Tracker'!D$2:D$2000,""),"") -> 0 | Z8: =IFERROR(_xlfn.XLOOKUP(TEXT(H8,"0000000000"),'📞 Call Tracker'!A$2:A$2000,'📞 Call Tracker'!E$2:E$2000,""),"") -> 0 | AA8: =IFERROR(_xlfn.XLOOKUP(TEXT(H8,"0000000000"),'📞 Call Tracker'!A$2:A$2000,'📞 Call Tracker'!F$2:F$2000,""),"") -> 0 | AB8: =IF(OR(H8="",X8<>""),99,IF(AND(NOT(OR(LEFT(TRIM(L8),3)="Yes",TRIM(L8)="Y",L8="Frozen Rate",L8="Frozen Plan",L8="Not able to Compare",L8="Info Not Avail",L8="NA",L8="")),AND(N8<>"No",N8<>"")),1,IF(NOT(OR(LEFT(TRIM(L8),3)="Yes",TRIM(L8)="Y",L8="Frozen Rate",L8="Frozen Plan",L8="Not able to Compare",L8="Info Not Avail",L8="NA",L8="")),2,IF(AND(N8<>"No",N8<>""),3,4)))) -> 99
A9: 45812 | B9: Paulsen | C9: Jodi | D9: Unknown | E9: Unknown | F9: Opposed | G9: https://images.edocket.azcc.gov/docketpdf/E000044514.pdf | H9: 7938430000 | I9: EPR-6w/ET-1 | J9: No | K9: No | L9: Not able to Compare | M9: No | N9: No | O9: Yes | P9: N | Q9: 45957 | R9: 0 | S9: 0 | T9: 0 | U9: 0 | V9: =IF(OR(LEFT(TRIM(L9),3)="Yes",TRIM(L9)="Y"),"✅ On Best Plan",IF(OR(L9="Frozen Rate",L9="Frozen Plan"),"❄ Frozen Rate",IF(OR(L9="Not able to Compare",L9="Info Not Avail",L9="NA",L9=""),"⚠ Unknown","❌ Not on Best Plan"))) -> ⚠ Unknown | W9: =IFERROR(_xlfn.XLOOKUP(TEXT(H9,"0000000000"),'📞 Call Tracker'!A$2:A$2000,'📞 Call Tracker'!B$2:B$2000,""),"") -> Joaquin | X9: =IFERROR(_xlfn.XLOOKUP(TEXT(H9,"0000000000"),'📞 Call Tracker'!A$2:A$2000,'📞 Call Tracker'!C$2:C$2000,""),"") -> 45997 | Y9: =IFERROR(_xlfn.XLOOKUP(TEXT(H9,"0000000000"),'📞 Call Tracker'!A$2:A$2000,'📞 Call Tracker'!D$2:D$2000,""),"") -> YES | Z9: =IFERROR(_xlfn.XLOOKUP(TEXT(H9,"0000000000"),'📞 Call Tracker'!A$2:A$2000,'📞 Call Tracker'!E$2:E$2000,""),"") -> 0 | AA9: =IFERROR(_xlfn.XLOOKUP(TEXT(H9,"0000000000"),'📞 Call Tracker'!A$2:A$2000,'📞 Call Tracker'!F$2:F$2000,""),"") -> 0 | AB9: =IF(OR(H9="",X9<>""),99,IF(AND(NOT(OR(LEFT(TRIM(L9),3)="Yes",TRIM(L9)="Y",L9="Frozen Rate",L9="Frozen Plan",L9="Not able to Compare",L9="Info Not Avail",L9="NA",L9="")),AND(N9<>"No",N9<>"")),1,IF(NOT(OR(LEFT(TRIM(L9),3)="Yes",TRIM(L9)="Y",L9="Frozen Rate",L9="Frozen Plan",L9="Not able to Compare",L9="Info Not Avail",L9="NA",L9="")),2,IF(AND(N9<>"No",N9<>""),3,4)))) -> 99
A10: 45813 | B10: Berto | C10: Kim & Dave | D10: Chino Valley | E10: Unknown | F10: Opposed | G10: https://images.edocket.azcc.gov/docketpdf/E000044536.pdf | H10: 2009184288 | I10: RCPw/RTOUE47 | J10: No | K10: No | L10: Yes | M10: No | N10: No | O10: Yes | P10: N | Q10: 45957 | R10: 0 | S10: 0 | T10: 0 | U10: 0 | V10: =IF(OR(LEFT(TRIM(L10),3)="Yes",TRIM(L10)="Y"),"✅ On Best Plan",IF(OR(L10="Frozen Rate",L10="Frozen Plan"),"❄ Frozen Rate",IF(OR(L10="Not able to Compare",L10="Info Not Avail",L10="NA",L10=""),"⚠ Unknown","❌ Not on Best Plan"))) -> ✅ On Best Plan | W10: =IFERROR(_xlfn.XLOOKUP(TEXT(H10,"0000000000"),'📞 Call Tracker'!A$2:A$2000,'📞 Call Tracker'!B$2:B$2000,""),"") -> Joaquin | X10: =IFERROR(_xlfn.XLOOKUP(TEXT(H10,"0000000000"),'📞 Call Tracker'!A$2:A$2000,'📞 Call Tracker'!C$2:C$2000,""),"") -> 45997 | Y10: =IFERROR(_xlfn.XLOOKUP(TEXT(H10,"0000000000"),'📞 Call Tracker'!A$2:A$2000,'📞 Call Tracker'!D$2:D$2000,""),"") -> 0 | Z10: =IFERROR(_xlfn.XLOOKUP(TEXT(H10,"0000000000"),'📞 Call Tracker'!A$2:A$2000,'📞 Call Tracker'!E$2:E$2000,""),"") -> 0 | AA10: =IFERROR(_xlfn.XLOOKUP(TEXT(H10,"0000000000"),'📞 Call Tracker'!A$2:A$2000,'📞 Call Tracker'!F$2:F$2000,""),"") -> DID TALK TO CORE OFFER TO REVIEW ACCT | AB10: =IF(OR(H10="",X10<>""),99,IF(AND(NOT(OR(LEFT(TRIM(L10),3)="Yes",TRIM(L10)="Y",L10="Frozen Rate",L10="Frozen Plan",L10="Not able to Compare",L10="Info Not Avail",L10="NA",L10="")),AND(N10<>"No",N10<>"")),1,IF(NOT(OR(LEFT(TRIM(L10),3)="Yes",TRIM(L10)="Y",L10="Frozen Rate",L10="Frozen Plan",L10="Not able to Compare",L10="Info Not Avail",L10="NA",L10="")),2,IF(AND(N10<>"No",N10<>""),3,4)))) -> 99
A11: 45813 | B11: Misamore | C11: Bruce | D11: Sedona | E11: 86336 | F11: Opposed | G11: https://images.edocket.azcc.gov/docketpdf/E000044536.pdf | H11: Inactive Acct | I11: 0 | J11: No | K11: 0 | L11: 0 | M11: 0 | N11: 0 | O11: 0 | P11: 0 | Q11: 0 | R11: 0 | S11: 0 | T11: 0 | U11: 0 | V11: =IF(OR(LEFT(TRIM(L11),3)="Yes",TRIM(L11)="Y"),"✅ On Best Plan",IF(OR(L11="Frozen Rate",L11="Frozen Plan"),"❄ Frozen Rate",IF(OR(L11="Not able to Compare",L11="Info Not Avail",L11="NA",L11=""),"⚠ Unknown","❌ Not on Best Plan"))) -> ❌ Not on Best Plan | W11: =IFERROR(_xlfn.XLOOKUP(TEXT(H11,"0000000000"),'📞 Call Tracker'!A$2:A$2000,'📞 Call Tracker'!B$2:B$2000,""),"") | X11: =IFERROR(_xlfn.XLOOKUP(TEXT(H11,"0000000000"),'📞 Call Tracker'!A$2:A$2000,'📞 Call Tracker'!C$2:C$2000,""),"") | Y11: =IFERROR(_xlfn.XLOOKUP(TEXT(H11,"0000000000"),'📞 Call Tracker'!A$2:A$2000,'📞 Call Tracker'!D$2:D$2000,""),"") | Z11: =IFERROR(_xlfn.XLOOKUP(TEXT(H11,"0000000000"),'📞 Call Tracker'!A$2:A$2000,'📞 Call Tracker'!E$2:E$2000,""),"") | AA11: =IFERROR(_xlfn.XLOOKUP(TEXT(H11,"0000000000"),'📞 Call Tracker'!A$2:A$2000,'📞 Call Tracker'!F$2:F$2000,""),"") | AB11: =IF(OR(H11="",X11<>""),99,IF(AND(NOT(OR(LEFT(TRIM(L11),3)="Yes",TRIM(L11)="Y",L11="Frozen Rate",L11="Frozen Plan",L11="Not able to Compare",L11="Info Not Avail",L11="NA",L11="")),AND(N11<>"No",N11<>"")),1,IF(NOT(OR(LEFT(TRIM(L11),3)="Yes",TRIM(L11)="Y",L11="Frozen Rate",L11="Frozen Plan",L11="Not able to Compare",L11="Info Not Avail",L11="NA",L11="")),2,IF(AND(N11<>"No",N11<>""),3,4)))) -> 1
A12: 45814 | B12: Shroyer | C12: Mary Lynne | D12: Sun City | E12: 85351 | F12: Opposed | G12: https://images.edocket.azcc.gov/docketpdf/E000044648.pdf | H12: 1163301000 | I12: R-XS | J12: No | K12: No | L12: Yes | M12: No | N12: No | O12: Yes | P12: N | Q12: 45957 | R12: 0 | S12: 0 | T12: 0 | U12: 0 | V12: =IF(OR(LEFT(TRIM(L12),3)="Yes",TRIM(L12)="Y"),"✅ On Best Plan",IF(OR(L12="Frozen Rate",L12="Frozen Plan"),"❄ Frozen Rate",IF(OR(L12="Not able to Compare",L12="Info Not Avail",L12="NA",L12=""),"⚠ Unknown","❌ Not on Best Plan"))) -> ✅ On Best Plan | W12: =IFERROR(_xlfn.XLOOKUP(TEXT(H12,"0000000000"),'📞 Call Tracker'!A$2:A$2000,'📞 Call Tracker'!B$2:B$2000,""),"") -> Joaquin | X12: =IFERROR(_xlfn.XLOOKUP(TEXT(H12,"0000000000"),'📞 Call Tracker'!A$2:A$2000,'📞 Call Tracker'!C$2:C$2000,""),"") -> 45997 | Y12: =IFERROR(_xlfn.XLOOKUP(TEXT(H12,"0000000000"),'📞 Call Tracker'!A$2:A$2000,'📞 Call Tracker'!D$2:D$2000,""),"") -> YES | Z12: =IFERROR(_xlfn.XLOOKUP(TEXT(H12,"0000000000"),'📞 Call Tracker'!A$2:A$2000,'📞 Call Tracker'!E$2:E$2000,""),"") -> 0 | AA12: =IFERROR(_xlfn.XLOOKUP(TEXT(H12,"0000000000"),'📞 Call Tracker'!A$2:A$2000,'📞 Call Tracker'!F$2:F$2000,""),"") -> CORE ON BB PROGRAM | AB12: =IF(OR(H12="",X12<>""),99,IF(AND(NOT(OR(LEFT(TRIM(L12),3)="Yes",TRIM(L12)="Y",L12="Frozen Rate",L12="Frozen Plan",L12="Not able to Compare",L12="Info Not Avail",L12="NA",L12="")),AND(N12<>"No",N12<>"")),1,IF(NOT(OR(LEFT(TRIM(L12),3)="Yes",TRIM(L12)="Y",L12="Frozen Rate",L12="Frozen Plan",L12="Not able to Compare",L12="Info Not Avail",L12="NA",L12="")),2,IF(AND(N12<>"No",N12<>""),3,4)))) -> 99
A13: 45821 | B13: Driscoll | C13: David & Donna | D13: Unknown | E13: Unknown | F13: Opposed | G13: https://images.edocket.azcc.gov/docketpdf/E000044766.pdf | H13: 6242500593 | I13: RCPw/RTOUE47 | J13: No | K13: No | L13: No - MEP R3-47($151.35) | M13: No | N13: No | O13: Yes | P13: N | Q13: 45957 | R13: Prior ACC Complaint customer - Solar customer does not want to be on demand rate. | S13: 0 | T13: 0 | U13: 0 | V13: =IF(OR(LEFT(TRIM(L13),3)="Yes",TRIM(L13)="Y"),"✅ On Best Plan",IF(OR(L13="Frozen Rate",L13="Frozen Plan"),"❄ Frozen Rate",IF(OR(L13="Not able to Compare",L13="Info Not Avail",L13="NA",L13=""),"⚠ Unknown","❌ Not on Best Plan"))) -> ❌ Not on Best Plan | W13: =IFERROR(_xlfn.XLOOKUP(TEXT(H13,"0000000000"),'📞 Call Tracker'!A$2:A$2000,'📞 Call Tracker'!B$2:B$2000,""),"") -> Joaquin | X13: =IFERROR(_xlfn.XLOOKUP(TEXT(H13,"0000000000"),'📞 Call Tracker'!A$2:A$2000,'📞 Call Tracker'!C$2:C$2000,""),"") -> 45997 | Y13: =IFERROR(_xlfn.XLOOKUP(TEXT(H13,"0000000000"),'📞 Call Tracker'!A$2:A$2000,'📞 Call Tracker'!D$2:D$2000,""),"") -> YES | Z13: =IFERROR(_xlfn.XLOOKUP(TEXT(H13,"0000000000"),'📞 Call Tracker'!A$2:A$2000,'📞 Call Tracker'!E$2:E$2000,""),"") -> 0 | AA13: =IFERROR(_xlfn.XLOOKUP(TEXT(H13,"0000000000"),'📞 Call Tracker'!A$2:A$2000,'📞 Call Tracker'!F$2:F$2000,""),"") -> CORE ON BB PROGRAM | AB13: =IF(OR(H13="",X13<>""),99,IF(AND(NOT(OR(LEFT(TRIM(L13),3)="Yes",TRIM(L13)="Y",L13="Frozen Rate",L13="Frozen Plan",L13="Not able to Compare",L13="Info Not Avail",L13="NA",L13="")),AND(N13<>"No",N13<>"")),1,IF(NOT(OR(LEFT(TRIM(L13),3)="Yes",TRIM(L13)="Y",L13="Frozen Rate",L13="Frozen Plan",L13="Not able to Compare",L13="Info Not Avail",L13="NA",L13="")),2,IF(AND(N13<>"No",N13<>""),3,4)))) -> 99
A14: 45825 | B14: Neal | C14: Michelle | D14: Glendale | E14: 85308 | F14: Opposed | G14: https://images.edocket.azcc.gov/docketpdf/E000044799.pdf | H14: 1565756559 | I14: R3-47 | J14: No | K14: No | L14: Yes | M14: No | N14: No | O14: Yes | P14: N | Q14: 45957 | R14: 0 | S14: 0 | T14: 0 | U14: 0 | V14: =IF(OR(LEFT(TRIM(L14),3)="Yes",TRIM(L14)="Y"),"✅ On Best Plan",IF(OR(L14="Frozen Rate",L14="Frozen Plan"),"❄ Frozen Rate",IF(OR(L14="Not able to Compare",L14="Info Not Avail",L14="NA",L14=""),"⚠ Unknown","❌ Not on Best Plan"))) -> ✅ On Best Plan | W14: =IFERROR(_xlfn.XLOOKUP(TEXT(H14,"0000000000"),'📞 Call Tracker'!A$2:A$2000,'📞 Call Tracker'!B$2:B$2000,""),"") -> Joaquin | X14: =IFERROR(_xlfn.XLOOKUP(TEXT(H14,"0000000000"),'📞 Call Tracker'!A$2:A$2000,'📞 Call Tracker'!C$2:C$2000,""),"") -> 45997 | Y14: =IFERROR(_xlfn.XLOOKUP(TEXT(H14,"0000000000"),'📞 Call Tracker'!A$2:A$2000,'📞 Call Tracker'!D$2:D$2000,""),"") -> YES | Z14: =IFERROR(_xlfn.XLOOKUP(TEXT(H14,"0000000000"),'📞 Call Tracker'!A$2:A$2000,'📞 Call Tracker'!E$2:E$2000,""),"") -> 0 | AA14: =IFERROR(_xlfn.XLOOKUP(TEXT(H14,"0000000000"),'📞 Call Tracker'!A$2:A$2000,'📞 Call Tracker'!F$2:F$2000,""),"") -> IS ON DEMAND & IS VERY HIGH | AB14: =IF(OR(H14="",X14<>""),99,IF(AND(NOT(OR(LEFT(TRIM(L14),3)="Yes",TRIM(L14)="Y",L14="Frozen Rate",L14="Frozen Plan",L14="Not able to Compare",L14="Info Not Avail",L14="NA",L14="")),AND(N14<>"No",N14<>"")),1,IF(NOT(OR(LEFT(TRIM(L14),3)="Yes",TRIM(L14)="Y",L14="Frozen Rate",L14="Frozen Plan",L14="Not able to Compare",L14="Info Not Avail",L14="NA",L14="")),2,IF(AND(N14<>"No",N14<>""),3,4)))) -> 99
A15: 45826 | B15: Witte | C15: Jessica | D15: Scottsdale | E15: 85254 | F15: Opposed | G15: https://images.edocket.azcc.gov/docketpdf/E000044842.pdf | H15: 7413433376 | I15: R-BASIC | J15: No | K15: No | L15: Yes | M15: No | N15: No | O15: Yes | P15: N | Q15: 45957 | R15: 0 | S15: 0 | T15: 0 | U15: 0 | V15: =IF(OR(LEFT(TRIM(L15),3)="Yes",TRIM(L15)="Y"),"✅ On Best Plan",IF(OR(L15="Frozen Rate",L15="Frozen Plan"),"❄ Frozen Rate",IF(OR(L15="Not able to Compare",L15="Info Not Avail",L15="NA",L15=""),"⚠ Unknown","❌ Not on Best Plan"))) -> ✅ On Best Plan | W15: =IFERROR(_xlfn.XLOOKUP(TEXT(H15,"0000000000"),'📞 Call Tracker'!A$2:A$2000,'📞 Call Tracker'!B$2:B$2000,""),"") -> 0 | X15: =IFERROR(_xlfn.XLOOKUP(TEXT(H15,"0000000000"),'📞 Call Tracker'!A$2:A$2000,'📞 Call Tracker'!C$2:C$2000,""),"") -> 0 | Y15: =IFERROR(_xlfn.XLOOKUP(TEXT(H15,"0000000000"),'📞 Call Tracker'!A$2:A$2000,'📞 Call Tracker'!D$2:D$2000,""),"") -> 0 | Z15: =IFERROR(_xlfn.XLOOKUP(TEXT(H15,"0000000000"),'📞 Call Tracker'!A$2:A$2000,'📞 Call Tracker'!E$2:E$2000,""),"") -> 0 | AA15: =IFERROR(_xlfn.XLOOKUP(TEXT(H15,"0000000000"),'📞 Call Tracker'!A$2:A$2000,'📞 Call Tracker'!F$2:F$2000,""),"") -> 0 | AB15: =IF(OR(H15="",X15<>""),99,IF(AND(NOT(OR(LEFT(TRIM(L15),3)="Yes",TRIM(L15)="Y",L15="Frozen Rate",L15="Frozen Plan",L15="Not able to Compare",L15="Info Not Avail",L15="NA",L15="")),AND(N15<>"No",N15<>"")),1,IF(NOT(OR(LEFT(TRIM(L15),3)="Yes",TRIM(L15)="Y",L15="Frozen Rate",L15="Frozen Plan",L15="Not able to Compare",L15="Info Not Avail",L15="NA",L15="")),2,IF(AND(N15<>"No",N15<>""),3,4)))) -> 99
A16: 45826 | B16: Figueroa | C16: Enrique | D16: Gilbert | E16: 85233 | F16: Opposed | G16: https://images.edocket.azcc.gov/docketpdf/E000044842.pdf | H16: 6601188228 | I16: R3-47 | J16: No | K16: No | L16: Yes | M16: No | N16: No | O16: Yes | P16: N | Q16: 45957 | R16: 0 | S16: 0 | T16: 0 | U16: 0 | V16: =IF(OR(LEFT(TRIM(L16),3)="Yes",TRIM(L16)="Y"),"✅ On Best Plan",IF(OR(L16="Frozen Rate",L16="Frozen Plan"),"❄ Frozen Rate",IF(OR(L16="Not able to Compare",L16="Info Not Avail",L16="NA",L16=""),"⚠ Unknown","❌ Not on Best Plan"))) -> ✅ On Best Plan | W16: =IFERROR(_xlfn.XLOOKUP(TEXT(H16,"0000000000"),'📞 Call Tracker'!A$2:A$2000,'📞 Call Tracker'!B$2:B$2000,""),"") -> Michelle | X16: =IFERROR(_xlfn.XLOOKUP(TEXT(H16,"0000000000"),'📞 Call Tracker'!A$2:A$2000,'📞 Call Tracker'!C$2:C$2000,""),"") -> 45997 | Y16: =IFERROR(_xlfn.XLOOKUP(TEXT(H16,"0000000000"),'📞 Call Tracker'!A$2:A$2000,'📞 Call Tracker'!D$2:D$2000,""),"") -> NO | Z16: =IFERROR(_xlfn.XLOOKUP(TEXT(H16,"0000000000"),'📞 Call Tracker'!A$2:A$2000,'📞 Call Tracker'!E$2:E$2000,""),"") -> 0 | AA16: =IFERROR(_xlfn.XLOOKUP(TEXT(H16,"0000000000"),'📞 Call Tracker'!A$2:A$2000,'📞 Call Tracker'!F$2:F$2000,""),"") -> PHONE DISCONNECTED / NOT ON BEST PLAN | AB16: =IF(OR(H16="",X16<>""),99,IF(AND(NOT(OR(LEFT(TRIM(L16),3)="Yes",TRIM(L16)="Y",L16="Frozen Rate",L16="Frozen Plan",L16="Not able to Compare",L16="Info Not Avail",L16="NA",L16="")),AND(N16<>"No",N16<>"")),1,IF(NOT(OR(LEFT(TRIM(L16),3)="Yes",TRIM(L16)="Y",L16="Frozen Rate",L16="Frozen Plan",L16="Not able to Compare",L16="Info Not Avail",L16="NA",L16="")),2,IF(AND(N16<>"No",N16<>""),3,4)))) -> 99
A17: 45826 | B17: Wheatley | C17: Heather | D17: Surprise | E17: 85388 | F17: Opposed | G17: https://images.edocket.azcc.gov/docketpdf/E000044842.pdf | H17: 7397110970 | I17: R3-47 | J17: No | K17: No | L17: Yes | M17: No | N17: No | O17: Yes | P17: N | Q17: 45957 | R17: 0 | S17: 0 | T17: 0 | U17: 0 | V17: =IF(OR(LEFT(TRIM(L17),3)="Yes",TRIM(L17)="Y"),"✅ On Best Plan",IF(OR(L17="Frozen Rate",L17="Frozen Plan"),"❄ Frozen Rate",IF(OR(L17="Not able to Compare",L17="Info Not Avail",L17="NA",L17=""),"⚠ Unknown","❌ Not on Best Plan"))) -> ✅ On Best Plan | W17: =IFERROR(_xlfn.XLOOKUP(TEXT(H17,"0000000000"),'📞 Call Tracker'!A$2:A$2000,'📞 Call Tracker'!B$2:B$2000,""),"") -> 0 | X17: =IFERROR(_xlfn.XLOOKUP(TEXT(H17,"0000000000"),'📞 Call Tracker'!A$2:A$2000,'📞 Call Tracker'!C$2:C$2000,""),"") -> 0 | Y17: =IFERROR(_xlfn.XLOOKUP(TEXT(H17,"0000000000"),'📞 Call Tracker'!A$2:A$2000,'📞 Call Tracker'!D$2:D$2000,""),"") -> 0 | Z17: =IFERROR(_xlfn.XLOOKUP(TEXT(H17,"0000000000"),'📞 Call Tracker'!A$2:A$2000,'📞 Call Tracker'!E$2:E$2000,""),"") -> 0 | AA17: =IFERROR(_xlfn.XLOOKUP(TEXT(H17,"0000000000"),'📞 Call Tracker'!A$2:A$2000,'📞 Call Tracker'!F$2:F$2000,""),"") -> 0 | AB17: =IF(OR(H17="",X17<>""),99,IF(AND(NOT(OR(LEFT(TRIM(L17),3)="Yes",TRIM(L17)="Y",L17="Frozen Rate",L17="Frozen Plan",L17="Not able to Compare",L17="Info Not Avail",L17="NA",L17="")),AND(N17<>"No",N17<>"")),1,IF(NOT(OR(LEFT(TRIM(L17),3)="Yes",TRIM(L17)="Y",L17="Frozen Rate",L17="Frozen Plan",L17="Not able to Compare",L17="Info Not Avail",L17="NA",L17="")),2,IF(AND(N17<>"No",N17<>""),3,4)))) -> 99
A18: 45826 | B18: Millbranth | C18: Mark | D18: Scottsdale | E18: 85266 | F18: Opposed | G18: https://images.edocket.azcc.gov/docketpdf/E000044842.pdf | H18: 5288831000 | I18: R3-47 | J18: No | K18: No | L18: Yes | M18: No | N18: No | O18: Yes | P18: N | Q18: 45957 | R18: 0 | S18: 0 | T18: 0 | U18: 0 | V18: =IF(OR(LEFT(TRIM(L18),3)="Yes",TRIM(L18)="Y"),"✅ On Best Plan",IF(OR(L18="Frozen Rate",L18="Frozen Plan"),"❄ Frozen Rate",IF(OR(L18="Not able to Compare",L18="Info Not Avail",L18="NA",L18=""),"⚠ Unknown","❌ Not on Best Plan"))) -> ✅ On Best Plan | W18: =IFERROR(_xlfn.XLOOKUP(TEXT(H18,"0000000000"),'📞 Call Tracker'!A$2:A$2000,'📞 Call Tracker'!B$2:B$2000,""),"") -> Michelle | X18: =IFERROR(_xlfn.XLOOKUP(TEXT(H18,"0000000000"),'📞 Call Tracker'!A$2:A$2000,'📞 Call Tracker'!C$2:C$2000,""),"") -> 46060 | Y18: =IFERROR(_xlfn.XLOOKUP(TEXT(H18,"0000000000"),'📞 Call Tracker'!A$2:A$2000,'📞 Call Tracker'!D$2:D$2000,""),"") -> NO | Z18: =IFERROR(_xlfn.XLOOKUP(TEXT(H18,"0000000000"),'📞 Call Tracker'!A$2:A$2000,'📞 Call Tracker'!E$2:E$2000,""),"") -> 0 | AA18: =IFERROR(_xlfn.XLOOKUP(TEXT(H18,"0000000000"),'📞 Call Tracker'!A$2:A$2000,'📞 Call Tracker'!F$2:F$2000,""),"") -> UNHAPPY W/ RATE CASE | AB18: =IF(OR(H18="",X18<>""),99,IF(AND(NOT(OR(LEFT(TRIM(L18),3)="Yes",TRIM(L18)="Y",L18="Frozen Rate",L18="Frozen Plan",L18="Not able to Compare",L18="Info Not Avail",L18="NA",L18="")),AND(N18<>"No",N18<>"")),1,IF(NOT(OR(LEFT(TRIM(L18),3)="Yes",TRIM(L18)="Y",L18="Frozen Rate",L18="Frozen Plan",L18="Not able to Compare",L18="Info Not Avail",L18="NA",L18="")),2,IF(AND(N18<>"No",N18<>""),3,4)))) -> 99
A19: 45826 | B19: Geyer | C19: Jared | D19: Scottsdale | E19: 85254 | F19: Opposed | G19: https://images.edocket.azcc.gov/docketpdf/E000044846.pdf | H19: 7528633936 | I19: R-BASICL | J19: No | K19: No | L19: No MEP R3-47 ($36.88) | M19: No | N19: No | O19: Yes | P19: N | Q19: 45957 | R19: 0 | S19: 0 | T19: 0 | U19: Estimated savings $37.01/12 = $3.08 potential monthly savings on MEP | V19: =IF(OR(LEFT(TRIM(L19),3)="Yes",TRIM(L19)="Y"),"✅ On Best Plan",IF(OR(L19="Frozen Rate",L19="Frozen Plan"),"❄ Frozen Rate",IF(OR(L19="Not able to Compare",L19="Info Not Avail",L19="NA",L19=""),"⚠ Unknown","❌ Not on Best Plan"))) -> ❌ Not on Best Plan | W19: =IFERROR(_xlfn.XLOOKUP(TEXT(H19,"0000000000"),'📞 Call Tracker'!A$2:A$2000,'📞 Call Tracker'!B$2:B$2000,""),"") -> Joaquin | X19: =IFERROR(_xlfn.XLOOKUP(TEXT(H19,"0000000000"),'📞 Call Tracker'!A$2:A$2000,'📞 Call Tracker'!C$2:C$2000,""),"") -> 46011 | Y19: =IFERROR(_xlfn.XLOOKUP(TEXT(H19,"0000000000"),'📞 Call Tracker'!A$2:A$2000,'📞 Call Tracker'!D$2:D$2000,""),"") -> NO | Z19: =IFERROR(_xlfn.XLOOKUP(TEXT(H19,"0000000000"),'📞 Call Tracker'!A$2:A$2000,'📞 Call Tracker'!E$2:E$2000,""),"") -> 0 | AA19: =IFERROR(_xlfn.XLOOKUP(TEXT(H19,"0000000000"),'📞 Call Tracker'!A$2:A$2000,'📞 Call Tracker'!F$2:F$2000,""),"") -> REFUSED TOTAKE CALL HUNG UP | AB19: =IF(OR(H19="",X19<>""),99,IF(AND(NOT(OR(LEFT(TRIM(L19),3)="Yes",TRIM(L19)="Y",L19="Frozen Rate",L19="Frozen Plan",L19="Not able to Compare",L19="Info Not Avail",L19="NA",L19="")),AND(N19<>"No",N19<>"")),1,IF(NOT(OR(LEFT(TRIM(L19),3)="Yes",TRIM(L19)="Y",L19="Frozen Rate",L19="Frozen Plan",L19="Not able to Compare",L19="Info Not Avail",L19="NA",L19="")),2,IF(AND(N19<>"No",N19<>""),3,4)))) -> 99
A20: 45826 | B20: Snyder | C20: Steven | D20: Phoenix | E20: 85029 | F20: Opposed | G20: https://images.edocket.azcc.gov/docketpdf/E000044846.pdf | H20: 4262494925 | I20: R3-47 | J20: No | K20: No | L20: No MEP R-XS ($110.29) | M20: No | N20: No | O20: Yes | P20: 45964 | Q20: 45957 | R20: 11/03 - LM | S20: 0 | T20: 0 | U20: Estimated savings $43.66/12 = $3.63 potential monthly savings on MEP | V20: =IF(OR(LEFT(TRIM(L20),3)="Yes",TRIM(L20)="Y"),"✅ On Best Plan",IF(OR(L20="Frozen Rate",L20="Frozen Plan"),"❄ Frozen Rate",IF(OR(L20="Not able to Compare",L20="Info Not Avail",L20="NA",L20=""),"⚠ Unknown","❌ Not on Best Plan"))) -> ❌ Not on Best Plan | W20: =IFERROR(_xlfn.XLOOKUP(TEXT(H20,"0000000000"),'📞 Call Tracker'!A$2:A$2000,'📞 Call Tracker'!B$2:B$2000,""),"") -> Michelle | X20: =IFERROR(_xlfn.XLOOKUP(TEXT(H20,"0000000000"),'📞 Call Tracker'!A$2:A$2000,'📞 Call Tracker'!C$2:C$2000,""),"") -> 45997 | Y20: =IFERROR(_xlfn.XLOOKUP(TEXT(H20,"0000000000"),'📞 Call Tracker'!A$2:A$2000,'📞 Call Tracker'!D$2:D$2000,""),"") -> NO | Z20: =IFERROR(_xlfn.XLOOKUP(TEXT(H20,"0000000000"),'📞 Call Tracker'!A$2:A$2000,'📞 Call Tracker'!E$2:E$2000,""),"") -> 0 | AA20: =IFERROR(_xlfn.XLOOKUP(TEXT(H20,"0000000000"),'📞 Call Tracker'!A$2:A$2000,'📞 Call Tracker'!F$2:F$2000,""),"") -> DID NOT WANT TO TALK / NOT ON BEST RATE PLAN | AB20: =IF(OR(H20="",X20<>""),99,IF(AND(NOT(OR(LEFT(TRIM(L20),3)="Yes",TRIM(L20)="Y",L20="Frozen Rate",L20="Frozen Plan",L20="Not able to Compare",L20="Info Not Avail",L20="NA",L20="")),AND(N20<>"No",N20<>"")),1,IF(NOT(OR(LEFT(TRIM(L20),3)="Yes",TRIM(L20)="Y",L20="Frozen Rate",L20="Frozen Plan",L20="Not able to Compare",L20="Info Not Avail",L20="NA",L20="")),2,IF(AND(N20<>"No",N20<>""),3,4)))) -> 99
A21: 45826 | B21: Kaplan | C21: Wayne | D21: Unknown | E21: Unknown | F21: Opposed | G21: https://images.edocket.azcc.gov/docketpdf/E000044840.pdf | H21: 4273250000 | I21: R-XS | J21: No | K21: No | L21: Yes | M21: No | N21: No | O21: Yes | P21: N | Q21: 45957 | R21: 0 | S21: 0 | T21: 0 | U21: 0 | V21: =IF(OR(LEFT(TRIM(L21),3)="Yes",TRIM(L21)="Y"),"✅ On Best Plan",IF(OR(L21="Frozen Rate",L21="Frozen Plan"),"❄ Frozen Rate",IF(OR(L21="Not able to Compare",L21="Info Not Avail",L21="NA",L21=""),"⚠ Unknown","❌ Not on Best Plan"))) -> ✅ On Best Plan | W21: =IFERROR(_xlfn.XLOOKUP(TEXT(H21,"0000000000"),'📞 Call Tracker'!A$2:A$2000,'📞 Call Tracker'!B$2:B$2000,""),"") -> Michelle | X21: =IFERROR(_xlfn.XLOOKUP(TEXT(H21,"0000000000"),'📞 Call Tracker'!A$2:A$2000,'📞 Call Tracker'!C$2:C$2000,""),"") -> 45997 | Y21: =IFERROR(_xlfn.XLOOKUP(TEXT(H21,"0000000000"),'📞 Call Tracker'!A$2:A$2000,'📞 Call Tracker'!D$2:D$2000,""),"") -> NO | Z21: =IFERROR(_xlfn.XLOOKUP(TEXT(H21,"0000000000"),'📞 Call Tracker'!A$2:A$2000,'📞 Call Tracker'!E$2:E$2000,""),"") -> 0 | AA21: =IFERROR(_xlfn.XLOOKUP(TEXT(H21,"0000000000"),'📞 Call Tracker'!A$2:A$2000,'📞 Call Tracker'!F$2:F$2000,""),"") -> VERY UP SET ABOUT THE RATES POSSIBLY GOING UP | AB21: =IF(OR(H21="",X21<>""),99,IF(AND(NOT(OR(LEFT(TRIM(L21),3)="Yes",TRIM(L21)="Y",L21="Frozen Rate",L21="Frozen Plan",L21="Not able to Compare",L21="Info Not Avail",L21="NA",L21="")),AND(N21<>"No",N21<>"")),1,IF(NOT(OR(LEFT(TRIM(L21),3)="Yes",TRIM(L21)="Y",L21="Frozen Rate",L21="Frozen Plan",L21="Not able to Compare",L21="Info Not Avail",L21="NA",L21="")),2,IF(AND(N21<>"No",N21<>""),3,4)))) -> 99
A22: 45826 | B22: Delgado | C22: Amber | D22: Unknown | E22: Unknown | F22: Opposed | G22: https://images.edocket.azcc.gov/docketpdf/E000044840.pdf | H22: 8714231000 | I22: R3-47 | J22: No | K22: No | L22: Yes | M22: No | N22: No | O22: Yes | P22: N | Q22: 45957 | R22: Changed rate to MEP on 10/6 | S22: 0 | T22: 0 | U22: Estimated savings $68.27/12 - $5.69 potential monthly savings on MEP | V22: =IF(OR(LEFT(TRIM(L22),3)="Yes",TRIM(L22)="Y"),"✅ On Best Plan",IF(OR(L22="Frozen Rate",L22="Frozen Plan"),"❄ Frozen Rate",IF(OR(L22="Not able to Compare",L22="Info Not Avail",L22="NA",L22=""),"⚠ Unknown","❌ Not on Best Plan"))) -> ✅ On Best Plan | W22: =IFERROR(_xlfn.XLOOKUP(TEXT(H22,"0000000000"),'📞 Call Tracker'!A$2:A$2000,'📞 Call Tracker'!B$2:B$2000,""),"") -> Michelle | X22: =IFERROR(_xlfn.XLOOKUP(TEXT(H22,"0000000000"),'📞 Call Tracker'!A$2:A$2000,'📞 Call Tracker'!C$2:C$2000,""),"") -> 46060 | Y22: =IFERROR(_xlfn.XLOOKUP(TEXT(H22,"0000000000"),'📞 Call Tracker'!A$2:A$2000,'📞 Call Tracker'!D$2:D$2000,""),"") -> YES | Z22: =IFERROR(_xlfn.XLOOKUP(TEXT(H22,"0000000000"),'📞 Call Tracker'!A$2:A$2000,'📞 Call Tracker'!E$2:E$2000,""),"") -> 0 | AA22: =IFERROR(_xlfn.XLOOKUP(TEXT(H22,"0000000000"),'📞 Call Tracker'!A$2:A$2000,'📞 Call Tracker'!F$2:F$2000,""),"") -> LEFT VM, ON BEST PLAN, NOT ON BB, NOT E-3 | AB22: =IF(OR(H22="",X22<>""),99,IF(AND(NOT(OR(LEFT(TRIM(L22),3)="Yes",TRIM(L22)="Y",L22="Frozen Rate",L22="Frozen Plan",L22="Not able to Compare",L22="Info Not Avail",L22="NA",L22="")),AND(N22<>"No",N22<>"")),1,IF(NOT(OR(LEFT(TRIM(L22),3)="Yes",TRIM(L22)="Y",L22="Frozen Rate",L22="Frozen Plan",L22="Not able to Compare",L22="Info Not Avail",L22="NA",L22="")),2,IF(AND(N22<>"No",N22<>""),3,4)))) -> 99
A23: 45826 | B23: Saporito | C23: Annette | D23: Cave Creek | E23: 85331 | F23: Opposed | G23: https://images.edocket.azcc.gov/docketpdf/E000044840.pdf | H23: 7980600000 | I23: RTOUE47 | J23: No | K23: No | L23: No R3-47 ($439.74) | M23: No | N23: No | O23: Yes | P23: 45964 | Q23: 45957 | R23: 11/03 - LM | S23: 0 | T23: 0 | U23: Estimated savings $433.16/12 = $36.09 potential monthly savings on MEP | V23: =IF(OR(LEFT(TRIM(L23),3)="Yes",TRIM(L23)="Y"),"✅ On Best Plan",IF(OR(L23="Frozen Rate",L23="Frozen Plan"),"❄ Frozen Rate",IF(OR(L23="Not able to Compare",L23="Info Not Avail",L23="NA",L23=""),"⚠ Unknown","❌ Not on Best Plan"))) -> ❌ Not on Best Plan | W23: =IFERROR(_xlfn.XLOOKUP(TEXT(H23,"0000000000"),'📞 Call Tracker'!A$2:A$2000,'📞 Call Tracker'!B$2:B$2000,""),"") -> Joaquin | X23: =IFERROR(_xlfn.XLOOKUP(TEXT(H23,"0000000000"),'📞 Call Tracker'!A$2:A$2000,'📞 Call Tracker'!C$2:C$2000,""),"") -> 46011 | Y23: =IFERROR(_xlfn.XLOOKUP(TEXT(H23,"0000000000"),'📞 Call Tracker'!A$2:A$2000,'📞 Call Tracker'!D$2:D$2000,""),"") -> YES | Z23: =IFERROR(_xlfn.XLOOKUP(TEXT(H23,"0000000000"),'📞 Call Tracker'!A$2:A$2000,'📞 Call Tracker'!E$2:E$2000,""),"") -> 0 | AA23: =IFERROR(_xlfn.XLOOKUP(TEXT(H23,"0000000000"),'📞 Call Tracker'!A$2:A$2000,'📞 Call Tracker'!F$2:F$2000,""),"") -> LEFT VOICE MESSAGE | AB23: =IF(OR(H23="",X23<>""),99,IF(AND(NOT(OR(LEFT(TRIM(L23),3)="Yes",TRIM(L23)="Y",L23="Frozen Rate",L23="Frozen Plan",L23="Not able to Compare",L23="Info Not Avail",L23="NA",L23="")),AND(N23<>"No",N23<>"")),1,IF(NOT(OR(LEFT(TRIM(L23),3)="Yes",TRIM(L23)="Y",L23="Frozen Rate",L23="Frozen Plan",L23="Not able to Compare",L23="Info Not Avail",L23="NA",L23="")),2,IF(AND(N23<>"No",N23<>""),3,4)))) -> 99
A24: 45827 | B24: Merlino | C24: Teri | D24: Unknown | E24: Unknown | F24: Opposed | G24: https://images.edocket.azcc.gov/docketpdf/E000044863.pdf | H24: 3007031000 | I24: R3-47 | J24: No | K24: No | L24: Yes | M24: No | N24: No | O24: Yes | P24: N | Q24: 45957 | R24: 0 | S24: 0 | T24: 0 | U24: 0 | V24: =IF(OR(LEFT(TRIM(L24),3)="Yes",TRIM(L24)="Y"),"✅ On Best Plan",IF(OR(L24="Frozen Rate",L24="Frozen Plan"),"❄ Frozen Rate",IF(OR(L24="Not able to Compare",L24="Info Not Avail",L24="NA",L24=""),"⚠ Unknown","❌ Not on Best Plan"))) -> ✅ On Best Plan | W24: =IFERROR(_xlfn.XLOOKUP(TEXT(H24,"0000000000"),'📞 Call Tracker'!A$2:A$2000,'📞 Call Tracker'!B$2:B$2000,""),"") -> Michelle | X24: =IFERROR(_xlfn.XLOOKUP(TEXT(H24,"0000000000"),'📞 Call Tracker'!A$2:A$2000,'📞 Call Tracker'!C$2:C$2000,""),"") -> 46060 | Y24: =IFERROR(_xlfn.XLOOKUP(TEXT(H24,"0000000000"),'📞 Call Tracker'!A$2:A$2000,'📞 Call Tracker'!D$2:D$2000,""),"") -> NO | Z24: =IFERROR(_xlfn.XLOOKUP(TEXT(H24,"0000000000"),'📞 Call Tracker'!A$2:A$2000,'📞 Call Tracker'!E$2:E$2000,""),"") -> 0 | AA24: =IFERROR(_xlfn.XLOOKUP(TEXT(H24,"0000000000"),'📞 Call Tracker'!A$2:A$2000,'📞 Call Tracker'!F$2:F$2000,""),"") -> DID NOT WANT TO SPEAK WITH ME AND HUNG UP | AB24: =IF(OR(H24="",X24<>""),99,IF(AND(NOT(OR(LEFT(TRIM(L24),3)="Yes",TRIM(L24)="Y",L24="Frozen Rate",L24="Frozen Plan",L24="Not able to Compare",L24="Info Not Avail",L24="NA",L24="")),AND(N24<>"No",N24<>"")),1,IF(NOT(OR(LEFT(TRIM(L24),3)="Yes",TRIM(L24)="Y",L24="Frozen Rate",L24="Frozen Plan",L24="Not able to Compare",L24="Info Not Avail",L24="NA",L24="")),2,IF(AND(N24<>"No",N24<>""),3,4)))) -> 99
A25: 45827 | B25: van Dalen | C25: Danielle | D25: Surprise | E25: 85374 | F25: Opposed | G25: https://images.edocket.azcc.gov/docketpdf/E000044866.pdf | H25: 8025299133 | I25: R-BASIC | J25: No | K25: No | L25: Yes | M25: No | N25: No | O25: Yes | P25: N | Q25: 45957 | R25: 0 | S25: 0 | T25: 0 | U25: 0 | V25: =IF(OR(LEFT(TRIM(L25),3)="Yes",TRIM(L25)="Y"),"✅ On Best Plan",IF(OR(L25="Frozen Rate",L25="Frozen Plan"),"❄ Frozen Rate",IF(OR(L25="Not able to Compare",L25="Info Not Avail",L25="NA",L25=""),"⚠ Unknown","❌ Not on Best Plan"))) -> ✅ On Best Plan | W25: =IFERROR(_xlfn.XLOOKUP(TEXT(H25,"0000000000"),'📞 Call Tracker'!A$2:A$2000,'📞 Call Tracker'!B$2:B$2000,""),"") -> 0 | X25: =IFERROR(_xlfn.XLOOKUP(TEXT(H25,"0000000000"),'📞 Call Tracker'!A$2:A$2000,'📞 Call Tracker'!C$2:C$2000,""),"") -> 0 | Y25: =IFERROR(_xlfn.XLOOKUP(TEXT(H25,"0000000000"),'📞 Call Tracker'!A$2:A$2000,'📞 Call Tracker'!D$2:D$2000,""),"") -> 0 | Z25: =IFERROR(_xlfn.XLOOKUP(TEXT(H25,"0000000000"),'📞 Call Tracker'!A$2:A$2000,'📞 Call Tracker'!E$2:E$2000,""),"") -> 0 | AA25: =IFERROR(_xlfn.XLOOKUP(TEXT(H25,"0000000000"),'📞 Call Tracker'!A$2:A$2000,'📞 Call Tracker'!F$2:F$2000,""),"") -> 0 | AB25: =IF(OR(H25="",X25<>""),99,IF(AND(NOT(OR(LEFT(TRIM(L25),3)="Yes",TRIM(L25)="Y",L25="Frozen Rate",L25="Frozen Plan",L25="Not able to Compare",L25="Info Not Avail",L25="NA",L25="")),AND(N25<>"No",N25<>"")),1,IF(NOT(OR(LEFT(TRIM(L25),3)="Yes",TRIM(L25)="Y",L25="Frozen Rate",L25="Frozen Plan",L25="Not able to Compare",L25="Info Not Avail",L25="NA",L25="")),2,IF(AND(N25<>"No",N25<>""),3,4)))) -> 99
A26: 45831 | B26: Schilling | C26: David | D26: Buckeye | E26: Unknown | F26: Opposed | G26: 0 | H26: 0799340889 | I26: R-BASIC | J26: No | K26: No | L26: No-Mep R3-47($87.55) | M26: No | N26: No | O26: Yes | P26: N | Q26: 45957 | R26: 0 | S26: 0 | T26: 0 | U26: 0 | V26: =IF(OR(LEFT(TRIM(L26),3)="Yes",TRIM(L26)="Y"),"✅ On Best Plan",IF(OR(L26="Frozen Rate",L26="Frozen Plan"),"❄ Frozen Rate",IF(OR(L26="Not able to Compare",L26="Info Not Avail",L26="NA",L26=""),"⚠ Unknown","❌ Not on Best Plan"))) -> ❌ Not on Best Plan | W26: =IFERROR(_xlfn.XLOOKUP(TEXT(H26,"0000000000"),'📞 Call Tracker'!A$2:A$2000,'📞 Call Tracker'!B$2:B$2000,""),"") -> Joaquin | X26: =IFERROR(_xlfn.XLOOKUP(TEXT(H26,"0000000000"),'📞 Call Tracker'!A$2:A$2000,'📞 Call Tracker'!C$2:C$2000,""),"") -> 46011 | Y26: =IFERROR(_xlfn.XLOOKUP(TEXT(H26,"0000000000"),'📞 Call Tracker'!A$2:A$2000,'📞 Call Tracker'!D$2:D$2000,""),"") -> YES | Z26: =IFERROR(_xlfn.XLOOKUP(TEXT(H26,"0000000000"),'📞 Call Tracker'!A$2:A$2000,'📞 Call Tracker'!E$2:E$2000,""),"") -> 0 | AA26: =IFERROR(_xlfn.XLOOKUP(TEXT(H26,"0000000000"),'📞 Call Tracker'!A$2:A$2000,'📞 Call Tracker'!F$2:F$2000,""),"") -> LEFT VOICE MESSAGE | AB26: =IF(OR(H26="",X26<>""),99,IF(AND(NOT(OR(LEFT(TRIM(L26),3)="Yes",TRIM(L26)="Y",L26="Frozen Rate",L26="Frozen Plan",L26="Not able to Compare",L26="Info Not Avail",L26="NA",L26="")),AND(N26<>"No",N26<>"")),1,IF(NOT(OR(LEFT(TRIM(L26),3)="Yes",TRIM(L26)="Y",L26="Frozen Rate",L26="Frozen Plan",L26="Not able to Compare",L26="Info Not Avail",L26="NA",L26="")),2,IF(AND(N26<>"No",N26<>""),3,4)))) -> 99
A27: 45831 | B27: Luther | C27: Jonathan | D27: Phoenix | E27: 85006 | F27: Opposed | G27: 0 | H27: 9229380000 | I27: RTOUE47 | J27: No | K27: No | L27: No-MEP R3-47($5.29) | M27: No | N27: No | O27: Yes | P27: N | Q27: 45957 | R27: 0 | S27: 0 | T27: 0 | U27: 0 | V27: =IF(OR(LEFT(TRIM(L27),3)="Yes",TRIM(L27)="Y"),"✅ On Best Plan",IF(OR(L27="Frozen Rate",L27="Frozen Plan"),"❄ Frozen Rate",IF(OR(L27="Not able to Compare",L27="Info Not Avail",L27="NA",L27=""),"⚠ Unknown","❌ Not on Best Plan"))) -> ❌ Not on Best Plan | W27: =IFERROR(_xlfn.XLOOKUP(TEXT(H27,"0000000000"),'📞 Call Tracker'!A$2:A$2000,'📞 Call Tracker'!B$2:B$2000,""),"") -> Joaquin | X27: =IFERROR(_xlfn.XLOOKUP(TEXT(H27,"0000000000"),'📞 Call Tracker'!A$2:A$2000,'📞 Call Tracker'!C$2:C$2000,""),"") -> 46011 | Y27: =IFERROR(_xlfn.XLOOKUP(TEXT(H27,"0000000000"),'📞 Call Tracker'!A$2:A$2000,'📞 Call Tracker'!D$2:D$2000,""),"") -> YES | Z27: =IFERROR(_xlfn.XLOOKUP(TEXT(H27,"0000000000"),'📞 Call Tracker'!A$2:A$2000,'📞 Call Tracker'!E$2:E$2000,""),"") -> 0 | AA27: =IFERROR(_xlfn.XLOOKUP(TEXT(H27,"0000000000"),'📞 Call Tracker'!A$2:A$2000,'📞 Call Tracker'!F$2:F$2000,""),"") -> LEFT VOICE MESSAGE | AB27: =IF(OR(H27="",X27<>""),99,IF(AND(NOT(OR(LEFT(TRIM(L27),3)="Yes",TRIM(L27)="Y",L27="Frozen Rate",L27="Frozen Plan",L27="Not able to Compare",L27="Info Not Avail",L27="NA",L27="")),AND(N27<>"No",N27<>"")),1,IF(NOT(OR(LEFT(TRIM(L27),3)="Yes",TRIM(L27)="Y",L27="Frozen Rate",L27="Frozen Plan",L27="Not able to Compare",L27="Info Not Avail",L27="NA",L27="")),2,IF(AND(N27<>"No",N27<>""),3,4)))) -> 99
A28: 45831 | B28: Porter | C28: Kristal | D28: Peoria | E28: 85383 | F28: Opposed | G28: 0 | H28: 7501590000 | I28: R3-47 | J28: No | K28: No | L28: Yes | M28: No | N28: No | O28: Yes | P28: N | Q28: 45957 | R28: 0 | S28: 0 | T28: 0 | U28: 0 | V28: =IF(OR(LEFT(TRIM(L28),3)="Yes",TRIM(L28)="Y"),"✅ On Best Plan",IF(OR(L28="Frozen Rate",L28="Frozen Plan"),"❄ Frozen Rate",IF(OR(L28="Not able to Compare",L28="Info Not Avail",L28="NA",L28=""),"⚠ Unknown","❌ Not on Best Plan"))) -> ✅ On Best Plan | W28: =IFERROR(_xlfn.XLOOKUP(TEXT(H28,"0000000000"),'📞 Call Tracker'!A$2:A$2000,'📞 Call Tracker'!B$2:B$2000,""),"") -> Michelle | X28: =IFERROR(_xlfn.XLOOKUP(TEXT(H28,"0000000000"),'📞 Call Tracker'!A$2:A$2000,'📞 Call Tracker'!C$2:C$2000,""),"") -> 46060 | Y28: =IFERROR(_xlfn.XLOOKUP(TEXT(H28,"0000000000"),'📞 Call Tracker'!A$2:A$2000,'📞 Call Tracker'!D$2:D$2000,""),"") -> NO | Z28: =IFERROR(_xlfn.XLOOKUP(TEXT(H28,"0000000000"),'📞 Call Tracker'!A$2:A$2000,'📞 Call Tracker'!E$2:E$2000,""),"") -> 0 | AA28: =IFERROR(_xlfn.XLOOKUP(TEXT(H28,"0000000000"),'📞 Call Tracker'!A$2:A$2000,'📞 Call Tracker'!F$2:F$2000,""),"") -> PHONE WAS PICKED UP AND HUNG UP | AB28: =IF(OR(H28="",X28<>""),99,IF(AND(NOT(OR(LEFT(TRIM(L28),3)="Yes",TRIM(L28)="Y",L28="Frozen Rate",L28="Frozen Plan",L28="Not able to Compare",L28="Info Not Avail",L28="NA",L28="")),AND(N28<>"No",N28<>"")),1,IF(NOT(OR(LEFT(TRIM(L28),3)="Yes",TRIM(L28)="Y",L28="Frozen Rate",L28="Frozen Plan",L28="Not able to Compare",L28="Info Not Avail",L28="NA",L28="")),2,IF(AND(N28<>"No",N28<>""),3,4)))) -> 99
A29: 45831 | B29: Gill | C29: Thomas | D29: Unknown | E29: Unknown | F29: Opposed | G29: 0 | H29: Multiple Cust Found | I29: 0 | J29: 0 | K29: 0 | L29: 0 | M29: 0 | N29: 0 | O29: 0 | P29: 0 | Q29: 0 | R29: 0 | S29: 0 | T29: 0 | U29: 0 | V29: =IF(OR(LEFT(TRIM(L29),3)="Yes",TRIM(L29)="Y"),"✅ On Best Plan",IF(OR(L29="Frozen Rate",L29="Frozen Plan"),"❄ Frozen Rate",IF(OR(L29="Not able to Compare",L29="Info Not Avail",L29="NA",L29=""),"⚠ Unknown","❌ Not on Best Plan"))) -> ❌ Not on Best Plan | W29: =IFERROR(_xlfn.XLOOKUP(TEXT(H29,"0000000000"),'📞 Call Tracker'!A$2:A$2000,'📞 Call Tracker'!B$2:B$2000,""),"") | X29: =IFERROR(_xlfn.XLOOKUP(TEXT(H29,"0000000000"),'📞 Call Tracker'!A$2:A$2000,'📞 Call Tracker'!C$2:C$2000,""),"") | Y29: =IFERROR(_xlfn.XLOOKUP(TEXT(H29,"0000000000"),'📞 Call Tracker'!A$2:A$2000,'📞 Call Tracker'!D$2:D$2000,""),"") | Z29: =IFERROR(_xlfn.XLOOKUP(TEXT(H29,"0000000000"),'📞 Call Tracker'!A$2:A$2000,'📞 Call Tracker'!E$2:E$2000,""),"") | AA29: =IFERROR(_xlfn.XLOOKUP(TEXT(H29,"0000000000"),'📞 Call Tracker'!A$2:A$2000,'📞 Call Tracker'!F$2:F$2000,""),"") | AB29: =IF(OR(H29="",X29<>""),99,IF(AND(NOT(OR(LEFT(TRIM(L29),3)="Yes",TRIM(L29)="Y",L29="Frozen Rate",L29="Frozen Plan",L29="Not able to Compare",L29="Info Not Avail",L29="NA",L29="")),AND(N29<>"No",N29<>"")),1,IF(NOT(OR(LEFT(TRIM(L29),3)="Yes",TRIM(L29)="Y",L29="Frozen Rate",L29="Frozen Plan",L29="Not able to Compare",L29="Info Not Avail",L29="NA",L29="")),2,IF(AND(N29<>"No",N29<>""),3,4)))) -> 1
A30: 45831 | B30: McGibbon | C30: Charles | D30: Chino Valley | E30: 86323 | F30: Opposed | G30: https://images.edocket.azcc.gov/docketpdf/E000044947.pdf | H30: 4707610000 | I30: R-XS | J30: No | K30: No | L30: Yes | M30: No | N30: No | O30: Yes | P30: N | Q30: 45958 | R30: 0 | S30: 0 | T30: 0 | U30: 0 | V30: =IF(OR(LEFT(TRIM(L30),3)="Yes",TRIM(L30)="Y"),"✅ On Best Plan",IF(OR(L30="Frozen Rate",L30="Frozen Plan"),"❄ Frozen Rate",IF(OR(L30="Not able to Compare",L30="Info Not Avail",L30="NA",L30=""),"⚠ Unknown","❌ Not on Best Plan"))) -> ✅ On Best Plan | W30: =IFERROR(_xlfn.XLOOKUP(TEXT(H30,"0000000000"),'📞 Call Tracker'!A$2:A$2000,'📞 Call Tracker'!B$2:B$2000,""),"") -> Joaquin | X30: =IFERROR(_xlfn.XLOOKUP(TEXT(H30,"0000000000"),'📞 Call Tracker'!A$2:A$2000,'📞 Call Tracker'!C$2:C$2000,""),"") -> 46067 | Y30: =IFERROR(_xlfn.XLOOKUP(TEXT(H30,"0000000000"),'📞 Call Tracker'!A$2:A$2000,'📞 Call Tracker'!D$2:D$2000,""),"") -> YES | Z30: =IFERROR(_xlfn.XLOOKUP(TEXT(H30,"0000000000"),'📞 Call Tracker'!A$2:A$2000,'📞 Call Tracker'!E$2:E$2000,""),"") -> 0 | AA30: =IFERROR(_xlfn.XLOOKUP(TEXT(H30,"0000000000"),'📞 Call Tracker'!A$2:A$2000,'📞 Call Tracker'!F$2:F$2000,""),"") -> LEFT VOICE MESSAGE | AB30: =IF(OR(H30="",X30<>""),99,IF(AND(NOT(OR(LEFT(TRIM(L30),3)="Yes",TRIM(L30)="Y",L30="Frozen Rate",L30="Frozen Plan",L30="Not able to Compare",L30="Info Not Avail",L30="NA",L30="")),AND(N30<>"No",N30<>"")),1,IF(NOT(OR(LEFT(TRIM(L30),3)="Yes",TRIM(L30)="Y",L30="Frozen Rate",L30="Frozen Plan",L30="Not able to Compare",L30="Info Not Avail",L30="NA",L30="")),2,IF(AND(N30<>"No",N30<>""),3,4)))) -> 99
A31: 45839 | B31: Sanchez | C31: Isabella | D31: Phoenix | E31: 85032 | F31: Opposed | G31: https://images.edocket.azcc.gov/docketpdf/E000045059.pdf | H31: 1164092226 | I31: R-BASIC | J31: No | K31: No | L31: Yes | M31: No | N31: No | O31: Yes | P31: N | Q31: 45958 | R31: 0 | S31: 0 | T31: 0 | U31: Estimated savings $42.27/12 = $3.52 potential monthly savings on MEP | V31: =IF(OR(LEFT(TRIM(L31),3)="Yes",TRIM(L31)="Y"),"✅ On Best Plan",IF(OR(L31="Frozen Rate",L31="Frozen Plan"),"❄ Frozen Rate",IF(OR(L31="Not able to Compare",L31="Info Not Avail",L31="NA",L31=""),"⚠ Unknown","❌ Not on Best Plan"))) -> ✅ On Best Plan | W31: =IFERROR(_xlfn.XLOOKUP(TEXT(H31,"0000000000"),'📞 Call Tracker'!A$2:A$2000,'📞 Call Tracker'!B$2:B$2000,""),"") -> Michelle | X31: =IFERROR(_xlfn.XLOOKUP(TEXT(H31,"0000000000"),'📞 Call Tracker'!A$2:A$2000,'📞 Call Tracker'!C$2:C$2000,""),"") -> 46060 | Y31: =IFERROR(_xlfn.XLOOKUP(TEXT(H31,"0000000000"),'📞 Call Tracker'!A$2:A$2000,'📞 Call Tracker'!D$2:D$2000,""),"") -> YES | Z31: =IFERROR(_xlfn.XLOOKUP(TEXT(H31,"0000000000"),'📞 Call Tracker'!A$2:A$2000,'📞 Call Tracker'!E$2:E$2000,""),"") -> 0 | AA31: =IFERROR(_xlfn.XLOOKUP(TEXT(H31,"0000000000"),'📞 Call Tracker'!A$2:A$2000,'📞 Call Tracker'!F$2:F$2000,""),"") -> LEFT VM, NOT ON BEST PLAN, NOT BB, NOT E-3 | AB31: =IF(OR(H31="",X31<>""),99,IF(AND(NOT(OR(LEFT(TRIM(L31),3)="Yes",TRIM(L31)="Y",L31="Frozen Rate",L31="Frozen Plan",L31="Not able to Compare",L31="Info Not Avail",L31="NA",L31="")),AND(N31<>"No",N31<>"")),1,IF(NOT(OR(LEFT(TRIM(L31),3)="Yes",TRIM(L31)="Y",L31="Frozen Rate",L31="Frozen Plan",L31="Not able to Compare",L31="Info Not Avail",L31="NA",L31="")),2,IF(AND(N31<>"No",N31<>""),3,4)))) -> 99
A32: 45846 | B32: Beiser | C32: Antoinette | D32: Sedona | E32: 86351 | F32: Opposed | G32: https://images.edocket.azcc.gov/docketpdf/E000045169.pdf | H32: 7150589750 | I32: R-BASICL | J32: No | K32: No | L32: No MEP R3-47($267.12) | M32: No | N32: No | O32: Yes | P32: 45964 | Q32: 45958 | R32: 11/03 - No answer and no voicemail | S32: 0 | T32: 0 | U32: 0 | V32: =IF(OR(LEFT(TRIM(L32),3)="Yes",TRIM(L32)="Y"),"✅ On Best Plan",IF(OR(L32="Frozen Rate",L32="Frozen Plan"),"❄ Frozen Rate",IF(OR(L32="Not able to Compare",L32="Info Not Avail",L32="NA",L32=""),"⚠ Unknown","❌ Not on Best Plan"))) -> ❌ Not on Best Plan | W32: =IFERROR(_xlfn.XLOOKUP(TEXT(H32,"0000000000"),'📞 Call Tracker'!A$2:A$2000,'📞 Call Tracker'!B$2:B$2000,""),"") -> Joaquin | X32: =IFERROR(_xlfn.XLOOKUP(TEXT(H32,"0000000000"),'📞 Call Tracker'!A$2:A$2000,'📞 Call Tracker'!C$2:C$2000,""),"") -> 46011 | Y32: =IFERROR(_xlfn.XLOOKUP(TEXT(H32,"0000000000"),'📞 Call Tracker'!A$2:A$2000,'📞 Call Tracker'!D$2:D$2000,""),"") -> 0 | Z32: =IFERROR(_xlfn.XLOOKUP(TEXT(H32,"0000000000"),'📞 Call Tracker'!A$2:A$2000,'📞 Call Tracker'!E$2:E$2000,""),"") -> Rate Change | AA32: =IFERROR(_xlfn.XLOOKUP(TEXT(H32,"0000000000"),'📞 Call Tracker'!A$2:A$2000,'📞 Call Tracker'!F$2:F$2000,""),"") -> RATE CHANGE | AB32: =IF(OR(H32="",X32<>""),99,IF(AND(NOT(OR(LEFT(TRIM(L32),3)="Yes",TRIM(L32)="Y",L32="Frozen Rate",L32="Frozen Plan",L32="Not able to Compare",L32="Info Not Avail",L32="NA",L32="")),AND(N32<>"No",N32<>"")),1,IF(NOT(OR(LEFT(TRIM(L32),3)="Yes",TRIM(L32)="Y",L32="Frozen Rate",L32="Frozen Plan",L32="Not able to Compare",L32="Info Not Avail",L32="NA",L32="")),2,IF(AND(N32<>"No",N32<>""),3,4)))) -> 99
A33: 45847 | B33: Underwood | C33: Revis | D33: Litchfield Park | E33: 85340 | F33: Opposed | G33: https://images.edocket.azcc.gov/docketpdf/E000045209.pdf | H33: 9558930000 | I33: EPR-6w/E-12 | J33: No | K33: No | L33: Info Not Avail | M33: No | N33: No | O33: Yes | P33: N | Q33: 45958 | R33: 0 | S33: 0 | T33: 0 | U33: 0 | V33: =IF(OR(LEFT(TRIM(L33),3)="Yes",TRIM(L33)="Y"),"✅ On Best Plan",IF(OR(L33="Frozen Rate",L33="Frozen Plan"),"❄ Frozen Rate",IF(OR(L33="Not able to Compare",L33="Info Not Avail",L33="NA",L33=""),"⚠ Unknown","❌ Not on Best Plan"))) -> ⚠ Unknown | W33: =IFERROR(_xlfn.XLOOKUP(TEXT(H33,"0000000000"),'📞 Call Tracker'!A$2:A$2000,'📞 Call Tracker'!B$2:B$2000,""),"") -> Michelle | X33: =IFERROR(_xlfn.XLOOKUP(TEXT(H33,"0000000000"),'📞 Call Tracker'!A$2:A$2000,'📞 Call Tracker'!C$2:C$2000,""),"") -> 46060 | Y33: =IFERROR(_xlfn.XLOOKUP(TEXT(H33,"0000000000"),'📞 Call Tracker'!A$2:A$2000,'📞 Call Tracker'!D$2:D$2000,""),"") -> YES | Z33: =IFERROR(_xlfn.XLOOKUP(TEXT(H33,"0000000000"),'📞 Call Tracker'!A$2:A$2000,'📞 Call Tracker'!E$2:E$2000,""),"") -> 0 | AA33: =IFERROR(_xlfn.XLOOKUP(TEXT(H33,"0000000000"),'📞 Call Tracker'!A$2:A$2000,'📞 Call Tracker'!F$2:F$2000,""),"") -> SOLAR ACCT | AB33: =IF(OR(H33="",X33<>""),99,IF(AND(NOT(OR(LEFT(TRIM(L33),3)="Yes",TRIM(L33)="Y",L33="Frozen Rate",L33="Frozen Plan",L33="Not able to Compare",L33="Info Not Avail",L33="NA",L33="")),AND(N33<>"No",N33<>"")),1,IF(NOT(OR(LEFT(TRIM(L33),3)="Yes",TRIM(L33)="Y",L33="Frozen Rate",L33="Frozen Plan",L33="Not able to Compare",L33="Info Not Avail",L33="NA",L33="")),2,IF(AND(N33<>"No",N33<>""),3,4)))) -> 99
A34: 45847 | B34: Hacker | C34: Dennis | D34: Phoenix | E34: 85029 | F34: Pole Attachments | G34: https://images.edocket.azcc.gov/docketpdf/E000045207.pdf | H34: 7633370000 | I34: RCPw/R3-47 | J34: No | K34: No | L34: Yes | M34: No | N34: No | O34: Yes | P34: N | Q34: 45958 | R34: 0 | S34: 0 | T34: 0 | U34: 0 | V34: =IF(OR(LEFT(TRIM(L34),3)="Yes",TRIM(L34)="Y"),"✅ On Best Plan",IF(OR(L34="Frozen Rate",L34="Frozen Plan"),"❄ Frozen Rate",IF(OR(L34="Not able to Compare",L34="Info Not Avail",L34="NA",L34=""),"⚠ Unknown","❌ Not on Best Plan"))) -> ✅ On Best Plan | W34: =IFERROR(_xlfn.XLOOKUP(TEXT(H34,"0000000000"),'📞 Call Tracker'!A$2:A$2000,'📞 Call Tracker'!B$2:B$2000,""),"") -> 0 | X34: =IFERROR(_xlfn.XLOOKUP(TEXT(H34,"0000000000"),'📞 Call Tracker'!A$2:A$2000,'📞 Call Tracker'!C$2:C$2000,""),"") -> 0 | Y34: =IFERROR(_xlfn.XLOOKUP(TEXT(H34,"0000000000"),'📞 Call Tracker'!A$2:A$2000,'📞 Call Tracker'!D$2:D$2000,""),"") -> 0 | Z34: =IFERROR(_xlfn.XLOOKUP(TEXT(H34,"0000000000"),'📞 Call Tracker'!A$2:A$2000,'📞 Call Tracker'!E$2:E$2000,""),"") -> 0 | AA34: =IFERROR(_xlfn.XLOOKUP(TEXT(H34,"0000000000"),'📞 Call Tracker'!A$2:A$2000,'📞 Call Tracker'!F$2:F$2000,""),"") -> 0 | AB34: =IF(OR(H34="",X34<>""),99,IF(AND(NOT(OR(LEFT(TRIM(L34),3)="Yes",TRIM(L34)="Y",L34="Frozen Rate",L34="Frozen Plan",L34="Not able to Compare",L34="Info Not Avail",L34="NA",L34="")),AND(N34<>"No",N34<>"")),1,IF(NOT(OR(LEFT(TRIM(L34),3)="Yes",TRIM(L34)="Y",L34="Frozen Rate",L34="Frozen Plan",L34="Not able to Compare",L34="Info Not Avail",L34="NA",L34="")),2,IF(AND(N34<>"No",N34<>""),3,4)))) -> 99
A35: 45852 | B35: Rizzi | C35: Carol | D35: Unknown | E35: Unknown | F35: Opposed | G35: https://images.edocket.azcc.gov/docketpdf/E000045267.pdf | H35: 3049940000 | I35: R-XS | J35: No | K35: No | L35: AMI Opt Out | M35: No | N35: No | O35: Yes | P35: N | Q35: 45958 | R35: 0 | S35: 0 | T35: 0 | U35: 0 | V35: =IF(OR(LEFT(TRIM(L35),3)="Yes",TRIM(L35)="Y"),"✅ On Best Plan",IF(OR(L35="Frozen Rate",L35="Frozen Plan"),"❄ Frozen Rate",IF(OR(L35="Not able to Compare",L35="Info Not Avail",L35="NA",L35=""),"⚠ Unknown","❌ Not on Best Plan"))) -> ❌ Not on Best Plan | W35: =IFERROR(_xlfn.XLOOKUP(TEXT(H35,"0000000000"),'📞 Call Tracker'!A$2:A$2000,'📞 Call Tracker'!B$2:B$2000,""),"") -> Michelle | X35: =IFERROR(_xlfn.XLOOKUP(TEXT(H35,"0000000000"),'📞 Call Tracker'!A$2:A$2000,'📞 Call Tracker'!C$2:C$2000,""),"") -> 46067 | Y35: =IFERROR(_xlfn.XLOOKUP(TEXT(H35,"0000000000"),'📞 Call Tracker'!A$2:A$2000,'📞 Call Tracker'!D$2:D$2000,""),"") -> YES | Z35: =IFERROR(_xlfn.XLOOKUP(TEXT(H35,"0000000000"),'📞 Call Tracker'!A$2:A$2000,'📞 Call Tracker'!E$2:E$2000,""),"") -> 0 | AA35: =IFERROR(_xlfn.XLOOKUP(TEXT(H35,"0000000000"),'📞 Call Tracker'!A$2:A$2000,'📞 Call Tracker'!F$2:F$2000,""),"") -> 0 | AB35: =IF(OR(H35="",X35<>""),99,IF(AND(NOT(OR(LEFT(TRIM(L35),3)="Yes",TRIM(L35)="Y",L35="Frozen Rate",L35="Frozen Plan",L35="Not able to Compare",L35="Info Not Avail",L35="NA",L35="")),AND(N35<>"No",N35<>"")),1,IF(NOT(OR(LEFT(TRIM(L35),3)="Yes",TRIM(L35)="Y",L35="Frozen Rate",L35="Frozen Plan",L35="Not able to Compare",L35="Info Not Avail",L35="NA",L35="")),2,IF(AND(N35<>"No",N35<>""),3,4)))) -> 99
A36: 45852 | B36: Snyder | C36: Steven | D36: Prescott Valley | E36: 86314 | F36: Opposed | G36: https://images.edocket.azcc.gov/docketpdf/E000045267.pdf | H36: 3736855436 | I36: RCPw/R3-47 | J36: No | K36: No | L36: Yes | M36: No | N36: No | O36: Yes | P36: N | Q36: 45958 | R36: 0 | S36: 0 | T36: 0 | U36: 0 | V36: =IF(OR(LEFT(TRIM(L36),3)="Yes",TRIM(L36)="Y"),"✅ On Best Plan",IF(OR(L36="Frozen Rate",L36="Frozen Plan"),"❄ Frozen Rate",IF(OR(L36="Not able to Compare",L36="Info Not Avail",L36="NA",L36=""),"⚠ Unknown","❌ Not on Best Plan"))) -> ✅ On Best Plan | W36: =IFERROR(_xlfn.XLOOKUP(TEXT(H36,"0000000000"),'📞 Call Tracker'!A$2:A$2000,'📞 Call Tracker'!B$2:B$2000,""),"") -> 0 | X36: =IFERROR(_xlfn.XLOOKUP(TEXT(H36,"0000000000"),'📞 Call Tracker'!A$2:A$2000,'📞 Call Tracker'!C$2:C$2000,""),"") -> 0 | Y36: =IFERROR(_xlfn.XLOOKUP(TEXT(H36,"0000000000"),'📞 Call Tracker'!A$2:A$2000,'📞 Call Tracker'!D$2:D$2000,""),"") -> 0 | Z36: =IFERROR(_xlfn.XLOOKUP(TEXT(H36,"0000000000"),'📞 Call Tracker'!A$2:A$2000,'📞 Call Tracker'!E$2:E$2000,""),"") -> 0 | AA36: =IFERROR(_xlfn.XLOOKUP(TEXT(H36,"0000000000"),'📞 Call Tracker'!A$2:A$2000,'📞 Call Tracker'!F$2:F$2000,""),"") -> 0 | AB36: =IF(OR(H36="",X36<>""),99,IF(AND(NOT(OR(LEFT(TRIM(L36),3)="Yes",TRIM(L36)="Y",L36="Frozen Rate",L36="Frozen Plan",L36="Not able to Compare",L36="Info Not Avail",L36="NA",L36="")),AND(N36<>"No",N36<>"")),1,IF(NOT(OR(LEFT(TRIM(L36),3)="Yes",TRIM(L36)="Y",L36="Frozen Rate",L36="Frozen Plan",L36="Not able to Compare",L36="Info Not Avail",L36="NA",L36="")),2,IF(AND(N36<>"No",N36<>""),3,4)))) -> 99
A37: 45854 | B37: Starr | C37: Valerie | D37: Payson | E37: 85541 | F37: Opposed / Greed | G37: https://images.edocket.azcc.gov/docketpdf/E000045309.pdf | H37: 8135798464 | I37: R-BASICL | J37: No | K37: No | L37: No MEP R3-47 ($337.28) | M37: No | N37: No | O37: Yes | P37: 45964 | Q37: 45958 | R37: 11/03 - LM | S37: 0 | T37: 0 | U37: Estimated savings $432.84/12 = $36.07 potential monthly savings on MEP | V37: =IF(OR(LEFT(TRIM(L37),3)="Yes",TRIM(L37)="Y"),"✅ On Best Plan",IF(OR(L37="Frozen Rate",L37="Frozen Plan"),"❄ Frozen Rate",IF(OR(L37="Not able to Compare",L37="Info Not Avail",L37="NA",L37=""),"⚠ Unknown","❌ Not on Best Plan"))) -> ❌ Not on Best Plan | W37: =IFERROR(_xlfn.XLOOKUP(TEXT(H37,"0000000000"),'📞 Call Tracker'!A$2:A$2000,'📞 Call Tracker'!B$2:B$2000,""),"") -> Joaquin | X37: =IFERROR(_xlfn.XLOOKUP(TEXT(H37,"0000000000"),'📞 Call Tracker'!A$2:A$2000,'📞 Call Tracker'!C$2:C$2000,""),"") -> 46011 | Y37: =IFERROR(_xlfn.XLOOKUP(TEXT(H37,"0000000000"),'📞 Call Tracker'!A$2:A$2000,'📞 Call Tracker'!D$2:D$2000,""),"") -> YES | Z37: =IFERROR(_xlfn.XLOOKUP(TEXT(H37,"0000000000"),'📞 Call Tracker'!A$2:A$2000,'📞 Call Tracker'!E$2:E$2000,""),"") -> 0 | AA37: =IFERROR(_xlfn.XLOOKUP(TEXT(H37,"0000000000"),'📞 Call Tracker'!A$2:A$2000,'📞 Call Tracker'!F$2:F$2000,""),"") -> BETTER RATE TIME OF USE WITH DEMAND | AB37: =IF(OR(H37="",X37<>""),99,IF(AND(NOT(OR(LEFT(TRIM(L37),3)="Yes",TRIM(L37)="Y",L37="Frozen Rate",L37="Frozen Plan",L37="Not able to Compare",L37="Info Not Avail",L37="NA",L37="")),AND(N37<>"No",N37<>"")),1,IF(NOT(OR(LEFT(TRIM(L37),3)="Yes",TRIM(L37)="Y",L37="Frozen Rate",L37="Frozen Plan",L37="Not able to Compare",L37="Info Not Avail",L37="NA",L37="")),2,IF(AND(N37<>"No",N37<>""),3,4)))) -> 99
A38: 45859 | B38: Hill | C38: Teresa | D38: Phoenix | E38: 85029 | F38: Senior/Fixed Income/ Data Centers | G38: https://images.edocket.azcc.gov/docketpdf/E000045376.pdf | H38: 5307300000 | I38: R3-47 | J38: No | K38: No | L38: No MEP R-XS ($136.97) | M38: No | N38: No | O38: Yes | P38: 45964 | Q38: 45958 | R38: 11/03 - Customer will callback at a more convenient time to discuss MEP | S38: 0 | T38: 0 | U38: 0 | V38: =IF(OR(LEFT(TRIM(L38),3)="Yes",TRIM(L38)="Y"),"✅ On Best Plan",IF(OR(L38="Frozen Rate",L38="Frozen Plan"),"❄ Frozen Rate",IF(OR(L38="Not able to Compare",L38="Info Not Avail",L38="NA",L38=""),"⚠ Unknown","❌ Not on Best Plan"))) -> ❌ Not on Best Plan | W38: =IFERROR(_xlfn.XLOOKUP(TEXT(H38,"0000000000"),'📞 Call Tracker'!A$2:A$2000,'📞 Call Tracker'!B$2:B$2000,""),"") -> Joaquin | X38: =IFERROR(_xlfn.XLOOKUP(TEXT(H38,"0000000000"),'📞 Call Tracker'!A$2:A$2000,'📞 Call Tracker'!C$2:C$2000,""),"") -> 46011 | Y38: =IFERROR(_xlfn.XLOOKUP(TEXT(H38,"0000000000"),'📞 Call Tracker'!A$2:A$2000,'📞 Call Tracker'!D$2:D$2000,""),"") -> 0 | Z38: =IFERROR(_xlfn.XLOOKUP(TEXT(H38,"0000000000"),'📞 Call Tracker'!A$2:A$2000,'📞 Call Tracker'!E$2:E$2000,""),"") -> Rate Change | AA38: =IFERROR(_xlfn.XLOOKUP(TEXT(H38,"0000000000"),'📞 Call Tracker'!A$2:A$2000,'📞 Call Tracker'!F$2:F$2000,""),"") -> WANTED INFO DATA CENTER RATES | AB38: =IF(OR(H38="",X38<>""),99,IF(AND(NOT(OR(LEFT(TRIM(L38),3)="Yes",TRIM(L38)="Y",L38="Frozen Rate",L38="Frozen Plan",L38="Not able to Compare",L38="Info Not Avail",L38="NA",L38="")),AND(N38<>"No",N38<>"")),1,IF(NOT(OR(LEFT(TRIM(L38),3)="Yes",TRIM(L38)="Y",L38="Frozen Rate",L38="Frozen Plan",L38="Not able to Compare",L38="Info Not Avail",L38="NA",L38="")),2,IF(AND(N38<>"No",N38<>""),3,4)))) -> 99
A39: 45861 | B39: Seabrook | C39: Michelle | D39: Phoenix | E39: 85054 | F39: Opposed | G39: https://images.edocket.azcc.gov/docketpdf/E000045426.pdf | H39: 3616936085 | I39: R-BASICL | J39: No | K39: No | L39: No MEP R-BASIC ($170.13) | M39: No | N39: No | O39: Yes | P39: N | Q39: 45958 | R39: Will be automatically reassigned soon | S39: 0 | T39: 0 | U39: 0 | V39: =IF(OR(LEFT(TRIM(L39),3)="Yes",TRIM(L39)="Y"),"✅ On Best Plan",IF(OR(L39="Frozen Rate",L39="Frozen Plan"),"❄ Frozen Rate",IF(OR(L39="Not able to Compare",L39="Info Not Avail",L39="NA",L39=""),"⚠ Unknown","❌ Not on Best Plan"))) -> ❌ Not on Best Plan | W39: =IFERROR(_xlfn.XLOOKUP(TEXT(H39,"0000000000"),'📞 Call Tracker'!A$2:A$2000,'📞 Call Tracker'!B$2:B$2000,""),"") -> Joaquin | X39: =IFERROR(_xlfn.XLOOKUP(TEXT(H39,"0000000000"),'📞 Call Tracker'!A$2:A$2000,'📞 Call Tracker'!C$2:C$2000,""),"") -> 46011 | Y39: =IFERROR(_xlfn.XLOOKUP(TEXT(H39,"0000000000"),'📞 Call Tracker'!A$2:A$2000,'📞 Call Tracker'!D$2:D$2000,""),"") -> NO | Z39: =IFERROR(_xlfn.XLOOKUP(TEXT(H39,"0000000000"),'📞 Call Tracker'!A$2:A$2000,'📞 Call Tracker'!E$2:E$2000,""),"") -> 0 | AA39: =IFERROR(_xlfn.XLOOKUP(TEXT(H39,"0000000000"),'📞 Call Tracker'!A$2:A$2000,'📞 Call Tracker'!F$2:F$2000,""),"") -> VOICE MAIL WAS FULL | AB39: =IF(OR(H39="",X39<>""),99,IF(AND(NOT(OR(LEFT(TRIM(L39),3)="Yes",TRIM(L39)="Y",L39="Frozen Rate",L39="Frozen Plan",L39="Not able to Compare",L39="Info Not Avail",L39="NA",L39="")),AND(N39<>"No",N39<>"")),1,IF(NOT(OR(LEFT(TRIM(L39),3)="Yes",TRIM(L39)="Y",L39="Frozen Rate",L39="Frozen Plan",L39="Not able to Compare",L39="Info Not Avail",L39="NA",L39="")),2,IF(AND(N39<>"No",N39<>""),3,4)))) -> 99
A40: 45883 | B40: Sternberg | C40: Karen | D40: Sedona | E40: 85336 | F40: Comments are about water rates | G40: https://images.edocket.azcc.gov/docketpdf/E000045814.pdf | H40: 4285810000 | I40: R-XS | J40: No | K40: No | L40: Yes | M40: No | N40: No | O40: Yes | P40: N | Q40: 45958 | R40: 0 | S40: 0 | T40: 0 | U40: Comments are about water rate increases | V40: =IF(OR(LEFT(TRIM(L40),3)="Yes",TRIM(L40)="Y"),"✅ On Best Plan",IF(OR(L40="Frozen Rate",L40="Frozen Plan"),"❄ Frozen Rate",IF(OR(L40="Not able to Compare",L40="Info Not Avail",L40="NA",L40=""),"⚠ Unknown","❌ Not on Best Plan"))) -> ✅ On Best Plan | W40: =IFERROR(_xlfn.XLOOKUP(TEXT(H40,"0000000000"),'📞 Call Tracker'!A$2:A$2000,'📞 Call Tracker'!B$2:B$2000,""),"") -> 0 | X40: =IFERROR(_xlfn.XLOOKUP(TEXT(H40,"0000000000"),'📞 Call Tracker'!A$2:A$2000,'📞 Call Tracker'!C$2:C$2000,""),"") -> 0 | Y40: =IFERROR(_xlfn.XLOOKUP(TEXT(H40,"0000000000"),'📞 Call Tracker'!A$2:A$2000,'📞 Call Tracker'!D$2:D$2000,""),"") -> 0 | Z40: =IFERROR(_xlfn.XLOOKUP(TEXT(H40,"0000000000"),'📞 Call Tracker'!A$2:A$2000,'📞 Call Tracker'!E$2:E$2000,""),"") -> 0 | AA40: =IFERROR(_xlfn.XLOOKUP(TEXT(H40,"0000000000"),'📞 Call Tracker'!A$2:A$2000,'📞 Call Tracker'!F$2:F$2000,""),"") -> 0 | AB40: =IF(OR(H40="",X40<>""),99,IF(AND(NOT(OR(LEFT(TRIM(L40),3)="Yes",TRIM(L40)="Y",L40="Frozen Rate",L40="Frozen Plan",L40="Not able to Compare",L40="Info Not Avail",L40="NA",L40="")),AND(N40<>"No",N40<>"")),1,IF(NOT(OR(LEFT(TRIM(L40),3)="Yes",TRIM(L40)="Y",L40="Frozen Rate",L40="Frozen Plan",L40="Not able to Compare",L40="Info Not Avail",L40="NA",L40="")),2,IF(AND(N40<>"No",N40<>""),3,4)))) -> 99
A41: 45898 | B41: Hines | C41: Rohna | D41: Unknown | E41: Unknown | F41: Opposed | G41: https://images.edocket.azcc.gov/docketpdf/E000046100.pdf | H41: 9376851000 | I41: RTOUE47 | J41: Yes | K41: No | L41: No MEP R-XS($77.28) | M41: No | N41: No | O41: Yes | P41: N | Q41: 45958 | R41: 0 | S41: 0 | T41: 0 | U41: 0 | V41: =IF(OR(LEFT(TRIM(L41),3)="Yes",TRIM(L41)="Y"),"✅ On Best Plan",IF(OR(L41="Frozen Rate",L41="Frozen Plan"),"❄ Frozen Rate",IF(OR(L41="Not able to Compare",L41="Info Not Avail",L41="NA",L41=""),"⚠ Unknown","❌ Not on Best Plan"))) -> ❌ Not on Best Plan | W41: =IFERROR(_xlfn.XLOOKUP(TEXT(H41,"0000000000"),'📞 Call Tracker'!A$2:A$2000,'📞 Call Tracker'!B$2:B$2000,""),"") -> Michelle | X41: =IFERROR(_xlfn.XLOOKUP(TEXT(H41,"0000000000"),'📞 Call Tracker'!A$2:A$2000,'📞 Call Tracker'!C$2:C$2000,""),"") -> 45997 | Y41: =IFERROR(_xlfn.XLOOKUP(TEXT(H41,"0000000000"),'📞 Call Tracker'!A$2:A$2000,'📞 Call Tracker'!D$2:D$2000,""),"") -> NO | Z41: =IFERROR(_xlfn.XLOOKUP(TEXT(H41,"0000000000"),'📞 Call Tracker'!A$2:A$2000,'📞 Call Tracker'!E$2:E$2000,""),"") -> 0 | AA41: =IFERROR(_xlfn.XLOOKUP(TEXT(H41,"0000000000"),'📞 Call Tracker'!A$2:A$2000,'📞 Call Tracker'!F$2:F$2000,""),"") -> ON PA, DID ADVISE BB AFTER PA IS DONE | AB41: =IF(OR(H41="",X41<>""),99,IF(AND(NOT(OR(LEFT(TRIM(L41),3)="Yes",TRIM(L41)="Y",L41="Frozen Rate",L41="Frozen Plan",L41="Not able to Compare",L41="Info Not Avail",L41="NA",L41="")),AND(N41<>"No",N41<>"")),1,IF(NOT(OR(LEFT(TRIM(L41),3)="Yes",TRIM(L41)="Y",L41="Frozen Rate",L41="Frozen Plan",L41="Not able to Compare",L41="Info Not Avail",L41="NA",L41="")),2,IF(AND(N41<>"No",N41<>""),3,4)))) -> 99
A42: 45902 | B42: Lovato | C42: Tiffany | D42: Surprise | E42: 85374 | F42: Opposed | G42: https://images.edocket.azcc.gov/docketpdf/E000046155.pdf | H42: 2721067262 | I42: R-BASIC | J42: N | K42: No | L42: Yes | M42: No | N42: No | O42: Yes | P42: N | Q42: 45967 | R42: 0 | S42: 0 | T42: 0 | U42: 0 | V42: =IF(OR(LEFT(TRIM(L42),3)="Yes",TRIM(L42)="Y"),"✅ On Best Plan",IF(OR(L42="Frozen Rate",L42="Frozen Plan"),"❄ Frozen Rate",IF(OR(L42="Not able to Compare",L42="Info Not Avail",L42="NA",L42=""),"⚠ Unknown","❌ Not on Best Plan"))) -> ✅ On Best Plan | W42: =IFERROR(_xlfn.XLOOKUP(TEXT(H42,"0000000000"),'📞 Call Tracker'!A$2:A$2000,'📞 Call Tracker'!B$2:B$2000,""),"") -> 0 | X42: =IFERROR(_xlfn.XLOOKUP(TEXT(H42,"0000000000"),'📞 Call Tracker'!A$2:A$2000,'📞 Call Tracker'!C$2:C$2000,""),"") -> 0 | Y42: =IFERROR(_xlfn.XLOOKUP(TEXT(H42,"0000000000"),'📞 Call Tracker'!A$2:A$2000,'📞 Call Tracker'!D$2:D$2000,""),"") -> 0 | Z42: =IFERROR(_xlfn.XLOOKUP(TEXT(H42,"0000000000"),'📞 Call Tracker'!A$2:A$2000,'📞 Call Tracker'!E$2:E$2000,""),"") -> 0 | AA42: =IFERROR(_xlfn.XLOOKUP(TEXT(H42,"0000000000"),'📞 Call Tracker'!A$2:A$2000,'📞 Call Tracker'!F$2:F$2000,""),"") -> 0 | AB42: =IF(OR(H42="",X42<>""),99,IF(AND(NOT(OR(LEFT(TRIM(L42),3)="Yes",TRIM(L42)="Y",L42="Frozen Rate",L42="Frozen Plan",L42="Not able to Compare",L42="Info Not Avail",L42="NA",L42="")),AND(N42<>"No",N42<>"")),1,IF(NOT(OR(LEFT(TRIM(L42),3)="Yes",TRIM(L42)="Y",L42="Frozen Rate",L42="Frozen Plan",L42="Not able to Compare",L42="Info Not Avail",L42="NA",L42="")),2,IF(AND(N42<>"No",N42<>""),3,4)))) -> 99
A43: 45902 | B43: Read | C43: David | D43: Peoria | E43: 85381 | F43: Opposed | G43: https://images.edocket.azcc.gov/docketpdf/E000046155.pdf | H43: 5237011424 | I43: RTOUE47 | J43: No | K43: No | L43: Yes | M43: No | N43: No | O43: Yes | P43: N | Q43: 45958 | R43: 0 | S43: 0 | T43: 0 | U43: 0 | V43: =IF(OR(LEFT(TRIM(L43),3)="Yes",TRIM(L43)="Y"),"✅ On Best Plan",IF(OR(L43="Frozen Rate",L43="Frozen Plan"),"❄ Frozen Rate",IF(OR(L43="Not able to Compare",L43="Info Not Avail",L43="NA",L43=""),"⚠ Unknown","❌ Not on Best Plan"))) -> ✅ On Best Plan | W43: =IFERROR(_xlfn.XLOOKUP(TEXT(H43,"0000000000"),'📞 Call Tracker'!A$2:A$2000,'📞 Call Tracker'!B$2:B$2000,""),"") -> Michelle | X43: =IFERROR(_xlfn.XLOOKUP(TEXT(H43,"0000000000"),'📞 Call Tracker'!A$2:A$2000,'📞 Call Tracker'!C$2:C$2000,""),"") -> 46067 | Y43: =IFERROR(_xlfn.XLOOKUP(TEXT(H43,"0000000000"),'📞 Call Tracker'!A$2:A$2000,'📞 Call Tracker'!D$2:D$2000,""),"") -> NO | Z43: =IFERROR(_xlfn.XLOOKUP(TEXT(H43,"0000000000"),'📞 Call Tracker'!A$2:A$2000,'📞 Call Tracker'!E$2:E$2000,""),"") -> 0 | AA43: =IFERROR(_xlfn.XLOOKUP(TEXT(H43,"0000000000"),'📞 Call Tracker'!A$2:A$2000,'📞 Call Tracker'!F$2:F$2000,""),"") -> SOLAR ACCT | AB43: =IF(OR(H43="",X43<>""),99,IF(AND(NOT(OR(LEFT(TRIM(L43),3)="Yes",TRIM(L43)="Y",L43="Frozen Rate",L43="Frozen Plan",L43="Not able to Compare",L43="Info Not Avail",L43="NA",L43="")),AND(N43<>"No",N43<>"")),1,IF(NOT(OR(LEFT(TRIM(L43),3)="Yes",TRIM(L43)="Y",L43="Frozen Rate",L43="Frozen Plan",L43="Not able to Compare",L43="Info Not Avail",L43="NA",L43="")),2,IF(AND(N43<>"No",N43<>""),3,4)))) -> 99
A44: 45902 | B44: Huynh | C44: Nam | D44: Buckeye | E44: 85326 | F44: Opposed | G44: https://images.edocket.azcc.gov/docketpdf/E000046155.pdf | H44: 6062541000 | I44: R3-47 | J44: No | K44: No | L44: Yes | M44: No | N44: No | O44: Yes | P44: N | Q44: 45958 | R44: 0 | S44: 0 | T44: 0 | U44: 0 | V44: =IF(OR(LEFT(TRIM(L44),3)="Yes",TRIM(L44)="Y"),"✅ On Best Plan",IF(OR(L44="Frozen Rate",L44="Frozen Plan"),"❄ Frozen Rate",IF(OR(L44="Not able to Compare",L44="Info Not Avail",L44="NA",L44=""),"⚠ Unknown","❌ Not on Best Plan"))) -> ✅ On Best Plan | W44: =IFERROR(_xlfn.XLOOKUP(TEXT(H44,"0000000000"),'📞 Call Tracker'!A$2:A$2000,'📞 Call Tracker'!B$2:B$2000,""),"") -> 0 | X44: =IFERROR(_xlfn.XLOOKUP(TEXT(H44,"0000000000"),'📞 Call Tracker'!A$2:A$2000,'📞 Call Tracker'!C$2:C$2000,""),"") -> 0 | Y44: =IFERROR(_xlfn.XLOOKUP(TEXT(H44,"0000000000"),'📞 Call Tracker'!A$2:A$2000,'📞 Call Tracker'!D$2:D$2000,""),"") -> 0 | Z44: =IFERROR(_xlfn.XLOOKUP(TEXT(H44,"0000000000"),'📞 Call Tracker'!A$2:A$2000,'📞 Call Tracker'!E$2:E$2000,""),"") -> 0 | AA44: =IFERROR(_xlfn.XLOOKUP(TEXT(H44,"0000000000"),'📞 Call Tracker'!A$2:A$2000,'📞 Call Tracker'!F$2:F$2000,""),"") -> 0 | AB44: =IF(OR(H44="",X44<>""),99,IF(AND(NOT(OR(LEFT(TRIM(L44),3)="Yes",TRIM(L44)="Y",L44="Frozen Rate",L44="Frozen Plan",L44="Not able to Compare",L44="Info Not Avail",L44="NA",L44="")),AND(N44<>"No",N44<>"")),1,IF(NOT(OR(LEFT(TRIM(L44),3)="Yes",TRIM(L44)="Y",L44="Frozen Rate",L44="Frozen Plan",L44="Not able to Compare",L44="Info Not Avail",L44="NA",L44="")),2,IF(AND(N44<>"No",N44<>""),3,4)))) -> 99
A45: 45902 | B45: Simmons | C45: Jennifer | D45: Scottsdale | E45: 85260 | F45: Opposed | G45: https://images.edocket.azcc.gov/docketpdf/E000046155.pdf | H45: 2882986476 | I45: RTOUE47 | J45: No | K45: No | L45: No MEP R3-47 ($61.45) | M45: No | N45: No | O45: Yes | P45: N | Q45: 45957 | R45: 0 | S45: 0 | T45: 0 | U45: 0 | V45: =IF(OR(LEFT(TRIM(L45),3)="Yes",TRIM(L45)="Y"),"✅ On Best Plan",IF(OR(L45="Frozen Rate",L45="Frozen Plan"),"❄ Frozen Rate",IF(OR(L45="Not able to Compare",L45="Info Not Avail",L45="NA",L45=""),"⚠ Unknown","❌ Not on Best Plan"))) -> ❌ Not on Best Plan | W45: =IFERROR(_xlfn.XLOOKUP(TEXT(H45,"0000000000"),'📞 Call Tracker'!A$2:A$2000,'📞 Call Tracker'!B$2:B$2000,""),"") -> Joaquin | X45: =IFERROR(_xlfn.XLOOKUP(TEXT(H45,"0000000000"),'📞 Call Tracker'!A$2:A$2000,'📞 Call Tracker'!C$2:C$2000,""),"") -> 46011 | Y45: =IFERROR(_xlfn.XLOOKUP(TEXT(H45,"0000000000"),'📞 Call Tracker'!A$2:A$2000,'📞 Call Tracker'!D$2:D$2000,""),"") -> YES | Z45: =IFERROR(_xlfn.XLOOKUP(TEXT(H45,"0000000000"),'📞 Call Tracker'!A$2:A$2000,'📞 Call Tracker'!E$2:E$2000,""),"") -> 0 | AA45: =IFERROR(_xlfn.XLOOKUP(TEXT(H45,"0000000000"),'📞 Call Tracker'!A$2:A$2000,'📞 Call Tracker'!F$2:F$2000,""),"") -> BETTER RATE TIME OF USE WITH DEMAND | AB45: =IF(OR(H45="",X45<>""),99,IF(AND(NOT(OR(LEFT(TRIM(L45),3)="Yes",TRIM(L45)="Y",L45="Frozen Rate",L45="Frozen Plan",L45="Not able to Compare",L45="Info Not Avail",L45="NA",L45="")),AND(N45<>"No",N45<>"")),1,IF(NOT(OR(LEFT(TRIM(L45),3)="Yes",TRIM(L45)="Y",L45="Frozen Rate",L45="Frozen Plan",L45="Not able to Compare",L45="Info Not Avail",L45="NA",L45="")),2,IF(AND(N45<>"No",N45<>""),3,4)))) -> 99
A46: 45902 | B46: Wood | C46: Ethan | D46: Phoenix | E46: 85085 | F46: Form letter | G46: https://images.edocket.azcc.gov/docketpdf/E000046155.pdf | H46: 7846277073 | I46: R3-47 | J46: No | K46: No | L46: Yes | M46: No | N46: No | O46: Yes | P46: N | Q46: 45958 | R46: 0 | S46: 0 | T46: 0 | U46: 0 | V46: =IF(OR(LEFT(TRIM(L46),3)="Yes",TRIM(L46)="Y"),"✅ On Best Plan",IF(OR(L46="Frozen Rate",L46="Frozen Plan"),"❄ Frozen Rate",IF(OR(L46="Not able to Compare",L46="Info Not Avail",L46="NA",L46=""),"⚠ Unknown","❌ Not on Best Plan"))) -> ✅ On Best Plan | W46: =IFERROR(_xlfn.XLOOKUP(TEXT(H46,"0000000000"),'📞 Call Tracker'!A$2:A$2000,'📞 Call Tracker'!B$2:B$2000,""),"") -> 0 | X46: =IFERROR(_xlfn.XLOOKUP(TEXT(H46,"0000000000"),'📞 Call Tracker'!A$2:A$2000,'📞 Call Tracker'!C$2:C$2000,""),"") -> 0 | Y46: =IFERROR(_xlfn.XLOOKUP(TEXT(H46,"0000000000"),'📞 Call Tracker'!A$2:A$2000,'📞 Call Tracker'!D$2:D$2000,""),"") -> 0 | Z46: =IFERROR(_xlfn.XLOOKUP(TEXT(H46,"0000000000"),'📞 Call Tracker'!A$2:A$2000,'📞 Call Tracker'!E$2:E$2000,""),"") -> 0 | AA46: =IFERROR(_xlfn.XLOOKUP(TEXT(H46,"0000000000"),'📞 Call Tracker'!A$2:A$2000,'📞 Call Tracker'!F$2:F$2000,""),"") -> 0 | AB46: =IF(OR(H46="",X46<>""),99,IF(AND(NOT(OR(LEFT(TRIM(L46),3)="Yes",TRIM(L46)="Y",L46="Frozen Rate",L46="Frozen Plan",L46="Not able to Compare",L46="Info Not Avail",L46="NA",L46="")),AND(N46<>"No",N46<>"")),1,IF(NOT(OR(LEFT(TRIM(L46),3)="Yes",TRIM(L46)="Y",L46="Frozen Rate",L46="Frozen Plan",L46="Not able to Compare",L46="Info Not Avail",L46="NA",L46="")),2,IF(AND(N46<>"No",N46<>""),3,4)))) -> 99
A47: 45902 | B47: Keller | C47: John | D47: Phoenix | E47: 85027 | F47: Opposed | G47: https://images.edocket.azcc.gov/docketpdf/E000046155.pdf | H47: 7692260000 | I47: R3-47 | J47: No | K47: No | L47: Yes | M47: No | N47: No | O47: Yes | P47: N | Q47: 45958 | R47: 0 | S47: 0 | T47: 0 | U47: 0 | V47: =IF(OR(LEFT(TRIM(L47),3)="Yes",TRIM(L47)="Y"),"✅ On Best Plan",IF(OR(L47="Frozen Rate",L47="Frozen Plan"),"❄ Frozen Rate",IF(OR(L47="Not able to Compare",L47="Info Not Avail",L47="NA",L47=""),"⚠ Unknown","❌ Not on Best Plan"))) -> ✅ On Best Plan | W47: =IFERROR(_xlfn.XLOOKUP(TEXT(H47,"0000000000"),'📞 Call Tracker'!A$2:A$2000,'📞 Call Tracker'!B$2:B$2000,""),"") -> Michelle | X47: =IFERROR(_xlfn.XLOOKUP(TEXT(H47,"0000000000"),'📞 Call Tracker'!A$2:A$2000,'📞 Call Tracker'!C$2:C$2000,""),"") -> 46067 | Y47: =IFERROR(_xlfn.XLOOKUP(TEXT(H47,"0000000000"),'📞 Call Tracker'!A$2:A$2000,'📞 Call Tracker'!D$2:D$2000,""),"") -> YES | Z47: =IFERROR(_xlfn.XLOOKUP(TEXT(H47,"0000000000"),'📞 Call Tracker'!A$2:A$2000,'📞 Call Tracker'!E$2:E$2000,""),"") -> 0 | AA47: =IFERROR(_xlfn.XLOOKUP(TEXT(H47,"0000000000"),'📞 Call Tracker'!A$2:A$2000,'📞 Call Tracker'!F$2:F$2000,""),"") -> 0 | AB47: =IF(OR(H47="",X47<>""),99,IF(AND(NOT(OR(LEFT(TRIM(L47),3)="Yes",TRIM(L47)="Y",L47="Frozen Rate",L47="Frozen Plan",L47="Not able to Compare",L47="Info Not Avail",L47="NA",L47="")),AND(N47<>"No",N47<>"")),1,IF(NOT(OR(LEFT(TRIM(L47),3)="Yes",TRIM(L47)="Y",L47="Frozen Rate",L47="Frozen Plan",L47="Not able to Compare",L47="Info Not Avail",L47="NA",L47="")),2,IF(AND(N47<>"No",N47<>""),3,4)))) -> 99
A48: 45902 | B48: Vint | C48: Shannon | D48: Phoenix | E48: 85027 | F48: Form letter | G48: https://images.edocket.azcc.gov/docketpdf/E000046155.pdf | H48: 1113187095 | I48: R-BASIC | J48: No | K48: No | L48: Yes | M48: No | N48: No | O48: Yes | P48: N | Q48: 45958 | R48: 0 | S48: 0 | T48: 0 | U48: 0 | V48: =IF(OR(LEFT(TRIM(L48),3)="Yes",TRIM(L48)="Y"),"✅ On Best Plan",IF(OR(L48="Frozen Rate",L48="Frozen Plan"),"❄ Frozen Rate",IF(OR(L48="Not able to Compare",L48="Info Not Avail",L48="NA",L48=""),"⚠ Unknown","❌ Not on Best Plan"))) -> ✅ On Best Plan | W48: =IFERROR(_xlfn.XLOOKUP(TEXT(H48,"0000000000"),'📞 Call Tracker'!A$2:A$2000,'📞 Call Tracker'!B$2:B$2000,""),"") -> 0 | X48: =IFERROR(_xlfn.XLOOKUP(TEXT(H48,"0000000000"),'📞 Call Tracker'!A$2:A$2000,'📞 Call Tracker'!C$2:C$2000,""),"") -> 0 | Y48: =IFERROR(_xlfn.XLOOKUP(TEXT(H48,"0000000000"),'📞 Call Tracker'!A$2:A$2000,'📞 Call Tracker'!D$2:D$2000,""),"") -> 0 | Z48: =IFERROR(_xlfn.XLOOKUP(TEXT(H48,"0000000000"),'📞 Call Tracker'!A$2:A$2000,'📞 Call Tracker'!E$2:E$2000,""),"") -> 0 | AA48: =IFERROR(_xlfn.XLOOKUP(TEXT(H48,"0000000000"),'📞 Call Tracker'!A$2:A$2000,'📞 Call Tracker'!F$2:F$2000,""),"") -> 0 | AB48: =IF(OR(H48="",X48<>""),99,IF(AND(NOT(OR(LEFT(TRIM(L48),3)="Yes",TRIM(L48)="Y",L48="Frozen Rate",L48="Frozen Plan",L48="Not able to Compare",L48="Info Not Avail",L48="NA",L48="")),AND(N48<>"No",N48<>"")),1,IF(NOT(OR(LEFT(TRIM(L48),3)="Yes",TRIM(L48)="Y",L48="Frozen Rate",L48="Frozen Plan",L48="Not able to Compare",L48="Info Not Avail",L48="NA",L48="")),2,IF(AND(N48<>"No",N48<>""),3,4)))) -> 99
A49: 45902 | B49: Snyder | C49: Corey | D49: Phoenix | E49: 85008 | F49: Form letter | G49: https://images.edocket.azcc.gov/docketpdf/E000046155.pdf | H49: 6584830202 | I49: R-BASICL | J49: No | K49: No | L49: No MEP R3-47 ($1,048.14) | M49: No | N49: No | O49: Yes | P49: 45932 | Q49: 45685 | R49: 10/02 - LM | S49: 0 | T49: 0 | U49: 0 | V49: =IF(OR(LEFT(TRIM(L49),3)="Yes",TRIM(L49)="Y"),"✅ On Best Plan",IF(OR(L49="Frozen Rate",L49="Frozen Plan"),"❄ Frozen Rate",IF(OR(L49="Not able to Compare",L49="Info Not Avail",L49="NA",L49=""),"⚠ Unknown","❌ Not on Best Plan"))) -> ❌ Not on Best Plan | W49: =IFERROR(_xlfn.XLOOKUP(TEXT(H49,"0000000000"),'📞 Call Tracker'!A$2:A$2000,'📞 Call Tracker'!B$2:B$2000,""),"") -> Joaquin | X49: =IFERROR(_xlfn.XLOOKUP(TEXT(H49,"0000000000"),'📞 Call Tracker'!A$2:A$2000,'📞 Call Tracker'!C$2:C$2000,""),"") -> 46011 | Y49: =IFERROR(_xlfn.XLOOKUP(TEXT(H49,"0000000000"),'📞 Call Tracker'!A$2:A$2000,'📞 Call Tracker'!D$2:D$2000,""),"") -> YES | Z49: =IFERROR(_xlfn.XLOOKUP(TEXT(H49,"0000000000"),'📞 Call Tracker'!A$2:A$2000,'📞 Call Tracker'!E$2:E$2000,""),"") -> 0 | AA49: =IFERROR(_xlfn.XLOOKUP(TEXT(H49,"0000000000"),'📞 Call Tracker'!A$2:A$2000,'📞 Call Tracker'!F$2:F$2000,""),"") -> BETTER RATE TIME OF USE WITH DEMAND $1046 | AB49: =IF(OR(H49="",X49<>""),99,IF(AND(NOT(OR(LEFT(TRIM(L49),3)="Yes",TRIM(L49)="Y",L49="Frozen Rate",L49="Frozen Plan",L49="Not able to Compare",L49="Info Not Avail",L49="NA",L49="")),AND(N49<>"No",N49<>"")),1,IF(NOT(OR(LEFT(TRIM(L49),3)="Yes",TRIM(L49)="Y",L49="Frozen Rate",L49="Frozen Plan",L49="Not able to Compare",L49="Info Not Avail",L49="NA",L49="")),2,IF(AND(N49<>"No",N49<>""),3,4)))) -> 99
A50: 45902 | B50: Alexander | C50: Jacob | D50: Peoria | E50: 85345 | F50: Form letter | G50: https://images.edocket.azcc.gov/docketpdf/E000046155.pdf | H50: 6178141000 | I50: R3-47 | J50: No | K50: No | L50: Yes | M50: Yes | N50: 175.19 | O50: Yes | P50: N | Q50: 45958 | R50: 0 | S50: 0 | T50: 0 | U50: 0 | V50: =IF(OR(LEFT(TRIM(L50),3)="Yes",TRIM(L50)="Y"),"✅ On Best Plan",IF(OR(L50="Frozen Rate",L50="Frozen Plan"),"❄ Frozen Rate",IF(OR(L50="Not able to Compare",L50="Info Not Avail",L50="NA",L50=""),"⚠ Unknown","❌ Not on Best Plan"))) -> ✅ On Best Plan | W50: =IFERROR(_xlfn.XLOOKUP(TEXT(H50,"0000000000"),'📞 Call Tracker'!A$2:A$2000,'📞 Call Tracker'!B$2:B$2000,""),"") -> Joaquin | X50: =IFERROR(_xlfn.XLOOKUP(TEXT(H50,"0000000000"),'📞 Call Tracker'!A$2:A$2000,'📞 Call Tracker'!C$2:C$2000,""),"") -> 46011 | Y50: =IFERROR(_xlfn.XLOOKUP(TEXT(H50,"0000000000"),'📞 Call Tracker'!A$2:A$2000,'📞 Call Tracker'!D$2:D$2000,""),"") -> YES | Z50: =IFERROR(_xlfn.XLOOKUP(TEXT(H50,"0000000000"),'📞 Call Tracker'!A$2:A$2000,'📞 Call Tracker'!E$2:E$2000,""),"") -> 0 | AA50: =IFERROR(_xlfn.XLOOKUP(TEXT(H50,"0000000000"),'📞 Call Tracker'!A$2:A$2000,'📞 Call Tracker'!F$2:F$2000,""),"") -> 0 | AB50: =IF(OR(H50="",X50<>""),99,IF(AND(NOT(OR(LEFT(TRIM(L50),3)="Yes",TRIM(L50)="Y",L50="Frozen Rate",L50="Frozen Plan",L50="Not able to Compare",L50="Info Not Avail",L50="NA",L50="")),AND(N50<>"No",N50<>"")),1,IF(NOT(OR(LEFT(TRIM(L50),3)="Yes",TRIM(L50)="Y",L50="Frozen Rate",L50="Frozen Plan",L50="Not able to Compare",L50="Info Not Avail",L50="NA",L50="")),2,IF(AND(N50<>"No",N50<>""),3,4)))) -> 99
A51: 45902 | B51: Poe | C51: Leighton | D51: Phoenix | E51: 85004 | F51: Form letter | G51: https://images.edocket.azcc.gov/docketpdf/E000046155.pdf | H51: 5855923100 | I51: R-BASIC | J51: No | K51: No | L51: No MEP RTOUE47($74.06) | M51: No | N51: No | O51: Yes | P51: N | Q51: 45958 | R51: 0 | S51: 0 | T51: 0 | U51: 0 | V51: =IF(OR(LEFT(TRIM(L51),3)="Yes",TRIM(L51)="Y"),"✅ On Best Plan",IF(OR(L51="Frozen Rate",L51="Frozen Plan"),"❄ Frozen Rate",IF(OR(L51="Not able to Compare",L51="Info Not Avail",L51="NA",L51=""),"⚠ Unknown","❌ Not on Best Plan"))) -> ❌ Not on Best Plan | W51: =IFERROR(_xlfn.XLOOKUP(TEXT(H51,"0000000000"),'📞 Call Tracker'!A$2:A$2000,'📞 Call Tracker'!B$2:B$2000,""),"") -> Joaquin | X51: =IFERROR(_xlfn.XLOOKUP(TEXT(H51,"0000000000"),'📞 Call Tracker'!A$2:A$2000,'📞 Call Tracker'!C$2:C$2000,""),"") -> 46011 | Y51: =IFERROR(_xlfn.XLOOKUP(TEXT(H51,"0000000000"),'📞 Call Tracker'!A$2:A$2000,'📞 Call Tracker'!D$2:D$2000,""),"") -> YES | Z51: =IFERROR(_xlfn.XLOOKUP(TEXT(H51,"0000000000"),'📞 Call Tracker'!A$2:A$2000,'📞 Call Tracker'!E$2:E$2000,""),"") -> 0 | AA51: =IFERROR(_xlfn.XLOOKUP(TEXT(H51,"0000000000"),'📞 Call Tracker'!A$2:A$2000,'📞 Call Tracker'!F$2:F$2000,""),"") -> 0 | AB51: =IF(OR(H51="",X51<>""),99,IF(AND(NOT(OR(LEFT(TRIM(L51),3)="Yes",TRIM(L51)="Y",L51="Frozen Rate",L51="Frozen Plan",L51="Not able to Compare",L51="Info Not Avail",L51="NA",L51="")),AND(N51<>"No",N51<>"")),1,IF(NOT(OR(LEFT(TRIM(L51),3)="Yes",TRIM(L51)="Y",L51="Frozen Rate",L51="Frozen Plan",L51="Not able to Compare",L51="Info Not Avail",L51="NA",L51="")),2,IF(AND(N51<>"No",N51<>""),3,4)))) -> 99
A52: 45902 | B52: Charapata | C52: Maxwell | D52: Phoenix | E52: 85027 | F52: Opposed | G52: https://images.edocket.azcc.gov/docketpdf/E000046155.pdf | H52: 2779220471 | I52: RTOUE47 | J52: No | K52: No | L52: No-MEP R3-47(23.66) | M52: No | N52: No | O52: Yes | P52: N | Q52: 45958 | R52: 0 | S52: 0 | T52: 0 | U52: 0 | V52: =IF(OR(LEFT(TRIM(L52),3)="Yes",TRIM(L52)="Y"),"✅ On Best Plan",IF(OR(L52="Frozen Rate",L52="Frozen Plan"),"❄ Frozen Rate",IF(OR(L52="Not able to Compare",L52="Info Not Avail",L52="NA",L52=""),"⚠ Unknown","❌ Not on Best Plan"))) -> ❌ Not on Best Plan | W52: =IFERROR(_xlfn.XLOOKUP(TEXT(H52,"0000000000"),'📞 Call Tracker'!A$2:A$2000,'📞 Call Tracker'!B$2:B$2000,""),"") -> Michelle | X52: =IFERROR(_xlfn.XLOOKUP(TEXT(H52,"0000000000"),'📞 Call Tracker'!A$2:A$2000,'📞 Call Tracker'!C$2:C$2000,""),"") -> 46060 | Y52: =IFERROR(_xlfn.XLOOKUP(TEXT(H52,"0000000000"),'📞 Call Tracker'!A$2:A$2000,'📞 Call Tracker'!D$2:D$2000,""),"") -> YES | Z52: =IFERROR(_xlfn.XLOOKUP(TEXT(H52,"0000000000"),'📞 Call Tracker'!A$2:A$2000,'📞 Call Tracker'!E$2:E$2000,""),"") -> 0 | AA52: =IFERROR(_xlfn.XLOOKUP(TEXT(H52,"0000000000"),'📞 Call Tracker'!A$2:A$2000,'📞 Call Tracker'!F$2:F$2000,""),"") -> SOLAR ACCT | AB52: =IF(OR(H52="",X52<>""),99,IF(AND(NOT(OR(LEFT(TRIM(L52),3)="Yes",TRIM(L52)="Y",L52="Frozen Rate",L52="Frozen Plan",L52="Not able to Compare",L52="Info Not Avail",L52="NA",L52="")),AND(N52<>"No",N52<>"")),1,IF(NOT(OR(LEFT(TRIM(L52),3)="Yes",TRIM(L52)="Y",L52="Frozen Rate",L52="Frozen Plan",L52="Not able to Compare",L52="Info Not Avail",L52="NA",L52="")),2,IF(AND(N52<>"No",N52<>""),3,4)))) -> 99
A53: 45902 | B53: Lafond | C53: Ciara | D53: Buckeye | E53: 85326 | F53: Opposed | G53: https://images.edocket.azcc.gov/docketpdf/E000046155.pdf | H53: 7245245699 | I53: RTOUE47 | J53: No | K53: No | L53: Yes | M53: No | N53: No | O53: Yes | P53: N | Q53: 45958 | R53: 0 | S53: 0 | T53: 0 | U53: 0 | V53: =IF(OR(LEFT(TRIM(L53),3)="Yes",TRIM(L53)="Y"),"✅ On Best Plan",IF(OR(L53="Frozen Rate",L53="Frozen Plan"),"❄ Frozen Rate",IF(OR(L53="Not able to Compare",L53="Info Not Avail",L53="NA",L53=""),"⚠ Unknown","❌ Not on Best Plan"))) -> ✅ On Best Plan | W53: =IFERROR(_xlfn.XLOOKUP(TEXT(H53,"0000000000"),'📞 Call Tracker'!A$2:A$2000,'📞 Call Tracker'!B$2:B$2000,""),"") -> Michelle | X53: =IFERROR(_xlfn.XLOOKUP(TEXT(H53,"0000000000"),'📞 Call Tracker'!A$2:A$2000,'📞 Call Tracker'!C$2:C$2000,""),"") -> 46067 | Y53: =IFERROR(_xlfn.XLOOKUP(TEXT(H53,"0000000000"),'📞 Call Tracker'!A$2:A$2000,'📞 Call Tracker'!D$2:D$2000,""),"") -> NO | Z53: =IFERROR(_xlfn.XLOOKUP(TEXT(H53,"0000000000"),'📞 Call Tracker'!A$2:A$2000,'📞 Call Tracker'!E$2:E$2000,""),"") -> 0 | AA53: =IFERROR(_xlfn.XLOOKUP(TEXT(H53,"0000000000"),'📞 Call Tracker'!A$2:A$2000,'📞 Call Tracker'!F$2:F$2000,""),"") -> SOLAR ACCT | AB53: =IF(OR(H53="",X53<>""),99,IF(AND(NOT(OR(LEFT(TRIM(L53),3)="Yes",TRIM(L53)="Y",L53="Frozen Rate",L53="Frozen Plan",L53="Not able to Compare",L53="Info Not Avail",L53="NA",L53="")),AND(N53<>"No",N53<>"")),1,IF(NOT(OR(LEFT(TRIM(L53),3)="Yes",TRIM(L53)="Y",L53="Frozen Rate",L53="Frozen Plan",L53="Not able to Compare",L53="Info Not Avail",L53="NA",L53="")),2,IF(AND(N53<>"No",N53<>""),3,4)))) -> 99
A54: 45902 | B54: O'Gorman | C54: Erin | D54: Prescott Valley | E54: 86314 | F54: Opposed | G54: https://images.edocket.azcc.gov/docketpdf/E000046155.pdf | H54: 0644019886 | I54: R-BASIC | J54: No | K54: No | L54: No-MEP R3-47($141.01) | M54: Yes | N54: 605.93 | O54: Yes | P54: 45932 | Q54: 0 | R54: 10/02 - LM | S54: 0 | T54: 0 | U54: 0 | V54: =IF(OR(LEFT(TRIM(L54),3)="Yes",TRIM(L54)="Y"),"✅ On Best Plan",IF(OR(L54="Frozen Rate",L54="Frozen Plan"),"❄ Frozen Rate",IF(OR(L54="Not able to Compare",L54="Info Not Avail",L54="NA",L54=""),"⚠ Unknown","❌ Not on Best Plan"))) -> ❌ Not on Best Plan | W54: =IFERROR(_xlfn.XLOOKUP(TEXT(H54,"0000000000"),'📞 Call Tracker'!A$2:A$2000,'📞 Call Tracker'!B$2:B$2000,""),"") -> Joaquin | X54: =IFERROR(_xlfn.XLOOKUP(TEXT(H54,"0000000000"),'📞 Call Tracker'!A$2:A$2000,'📞 Call Tracker'!C$2:C$2000,""),"") -> 46011 | Y54: =IFERROR(_xlfn.XLOOKUP(TEXT(H54,"0000000000"),'📞 Call Tracker'!A$2:A$2000,'📞 Call Tracker'!D$2:D$2000,""),"") -> YES | Z54: =IFERROR(_xlfn.XLOOKUP(TEXT(H54,"0000000000"),'📞 Call Tracker'!A$2:A$2000,'📞 Call Tracker'!E$2:E$2000,""),"") -> 0 | AA54: =IFERROR(_xlfn.XLOOKUP(TEXT(H54,"0000000000"),'📞 Call Tracker'!A$2:A$2000,'📞 Call Tracker'!F$2:F$2000,""),"") -> ACT 0644019886 | AB54: =IF(OR(H54="",X54<>""),99,IF(AND(NOT(OR(LEFT(TRIM(L54),3)="Yes",TRIM(L54)="Y",L54="Frozen Rate",L54="Frozen Plan",L54="Not able to Compare",L54="Info Not Avail",L54="NA",L54="")),AND(N54<>"No",N54<>"")),1,IF(NOT(OR(LEFT(TRIM(L54),3)="Yes",TRIM(L54)="Y",L54="Frozen Rate",L54="Frozen Plan",L54="Not able to Compare",L54="Info Not Avail",L54="NA",L54="")),2,IF(AND(N54<>"No",N54<>""),3,4)))) -> 99
A55: 45902 | B55: Lara | C55: Gerardo | D55: Glendale | E55: 85306 | F55: Form letter | G55: https://images.edocket.azcc.gov/docketpdf/E000046155.pdf | H55: 6799425771 | I55: R-BASICL | J55: No | K55: No | L55: No MEP R3-47(249.30) | M55: Yes | N55: 591.48 | O55: Yes | P55: 45932 | Q55: 45968 | R55: 10/02 - LM - COR initiated rate change to MEP on 10/23 | S55: 0 | T55: 0 | U55: 0 | V55: =IF(OR(LEFT(TRIM(L55),3)="Yes",TRIM(L55)="Y"),"✅ On Best Plan",IF(OR(L55="Frozen Rate",L55="Frozen Plan"),"❄ Frozen Rate",IF(OR(L55="Not able to Compare",L55="Info Not Avail",L55="NA",L55=""),"⚠ Unknown","❌ Not on Best Plan"))) -> ❌ Not on Best Plan | W55: =IFERROR(_xlfn.XLOOKUP(TEXT(H55,"0000000000"),'📞 Call Tracker'!A$2:A$2000,'📞 Call Tracker'!B$2:B$2000,""),"") -> Joaquin | X55: =IFERROR(_xlfn.XLOOKUP(TEXT(H55,"0000000000"),'📞 Call Tracker'!A$2:A$2000,'📞 Call Tracker'!C$2:C$2000,""),"") -> 46011 | Y55: =IFERROR(_xlfn.XLOOKUP(TEXT(H55,"0000000000"),'📞 Call Tracker'!A$2:A$2000,'📞 Call Tracker'!D$2:D$2000,""),"") -> NO | Z55: =IFERROR(_xlfn.XLOOKUP(TEXT(H55,"0000000000"),'📞 Call Tracker'!A$2:A$2000,'📞 Call Tracker'!E$2:E$2000,""),"") -> E3/E4 | AA55: =IFERROR(_xlfn.XLOOKUP(TEXT(H55,"0000000000"),'📞 Call Tracker'!A$2:A$2000,'📞 Call Tracker'!F$2:F$2000,""),"") -> SENT E3 | AB55: =IF(OR(H55="",X55<>""),99,IF(AND(NOT(OR(LEFT(TRIM(L55),3)="Yes",TRIM(L55)="Y",L55="Frozen Rate",L55="Frozen Plan",L55="Not able to Compare",L55="Info Not Avail",L55="NA",L55="")),AND(N55<>"No",N55<>"")),1,IF(NOT(OR(LEFT(TRIM(L55),3)="Yes",TRIM(L55)="Y",L55="Frozen Rate",L55="Frozen Plan",L55="Not able to Compare",L55="Info Not Avail",L55="NA",L55="")),2,IF(AND(N55<>"No",N55<>""),3,4)))) -> 99
A56: 45902 | B56: Howell | C56: Chris | D56: Surprise | E56: 85387 | F56: Form letter | G56: https://images.edocket.azcc.gov/docketpdf/E000046155.pdf | H56: 6635023227 | I56: RTOUE47 | J56: No | K56: No | L56: No MEP R3-47($2.91) | M56: No | N56: No | O56: Yes | P56: N | Q56: 45968 | R56: 0 | S56: 0 | T56: 0 | U56: 0 | V56: =IF(OR(LEFT(TRIM(L56),3)="Yes",TRIM(L56)="Y"),"✅ On Best Plan",IF(OR(L56="Frozen Rate",L56="Frozen Plan"),"❄ Frozen Rate",IF(OR(L56="Not able to Compare",L56="Info Not Avail",L56="NA",L56=""),"⚠ Unknown","❌ Not on Best Plan"))) -> ❌ Not on Best Plan | W56: =IFERROR(_xlfn.XLOOKUP(TEXT(H56,"0000000000"),'📞 Call Tracker'!A$2:A$2000,'📞 Call Tracker'!B$2:B$2000,""),"") -> Michelle | X56: =IFERROR(_xlfn.XLOOKUP(TEXT(H56,"0000000000"),'📞 Call Tracker'!A$2:A$2000,'📞 Call Tracker'!C$2:C$2000,""),"") -> 46032 | Y56: =IFERROR(_xlfn.XLOOKUP(TEXT(H56,"0000000000"),'📞 Call Tracker'!A$2:A$2000,'📞 Call Tracker'!D$2:D$2000,""),"") -> NO | Z56: =IFERROR(_xlfn.XLOOKUP(TEXT(H56,"0000000000"),'📞 Call Tracker'!A$2:A$2000,'📞 Call Tracker'!E$2:E$2000,""),"") -> Other (fill in) | AA56: =IFERROR(_xlfn.XLOOKUP(TEXT(H56,"0000000000"),'📞 Call Tracker'!A$2:A$2000,'📞 Call Tracker'!F$2:F$2000,""),"") -> SOLAR ACCT | AB56: =IF(OR(H56="",X56<>""),99,IF(AND(NOT(OR(LEFT(TRIM(L56),3)="Yes",TRIM(L56)="Y",L56="Frozen Rate",L56="Frozen Plan",L56="Not able to Compare",L56="Info Not Avail",L56="NA",L56="")),AND(N56<>"No",N56<>"")),1,IF(NOT(OR(LEFT(TRIM(L56),3)="Yes",TRIM(L56)="Y",L56="Frozen Rate",L56="Frozen Plan",L56="Not able to Compare",L56="Info Not Avail",L56="NA",L56="")),2,IF(AND(N56<>"No",N56<>""),3,4)))) -> 99
A57: 45902 | B57: Torres | C57: Kyle | D57: Phoenix | E57: 85020 | F57: Form letter | G57: https://images.edocket.azcc.gov/docketpdf/E000046155.pdf | H57: 9505905227 | I57: R-BASIC | J57: No | K57: No | L57: No MEP R3-47($18.99) | M57: No | N57: No | O57: Yes | P57: N | Q57: 45968 | R57: 0 | S57: 0 | T57: 0 | U57: 0 | V57: =IF(OR(LEFT(TRIM(L57),3)="Yes",TRIM(L57)="Y"),"✅ On Best Plan",IF(OR(L57="Frozen Rate",L57="Frozen Plan"),"❄ Frozen Rate",IF(OR(L57="Not able to Compare",L57="Info Not Avail",L57="NA",L57=""),"⚠ Unknown","❌ Not on Best Plan"))) -> ❌ Not on Best Plan | W57: =IFERROR(_xlfn.XLOOKUP(TEXT(H57,"0000000000"),'📞 Call Tracker'!A$2:A$2000,'📞 Call Tracker'!B$2:B$2000,""),"") -> Joaquin | X57: =IFERROR(_xlfn.XLOOKUP(TEXT(H57,"0000000000"),'📞 Call Tracker'!A$2:A$2000,'📞 Call Tracker'!C$2:C$2000,""),"") -> 46011 | Y57: =IFERROR(_xlfn.XLOOKUP(TEXT(H57,"0000000000"),'📞 Call Tracker'!A$2:A$2000,'📞 Call Tracker'!D$2:D$2000,""),"") -> YES | Z57: =IFERROR(_xlfn.XLOOKUP(TEXT(H57,"0000000000"),'📞 Call Tracker'!A$2:A$2000,'📞 Call Tracker'!E$2:E$2000,""),"") -> 0 | AA57: =IFERROR(_xlfn.XLOOKUP(TEXT(H57,"0000000000"),'📞 Call Tracker'!A$2:A$2000,'📞 Call Tracker'!F$2:F$2000,""),"") -> 0 | AB57: =IF(OR(H57="",X57<>""),99,IF(AND(NOT(OR(LEFT(TRIM(L57),3)="Yes",TRIM(L57)="Y",L57="Frozen Rate",L57="Frozen Plan",L57="Not able to Compare",L57="Info Not Avail",L57="NA",L57="")),AND(N57<>"No",N57<>"")),1,IF(NOT(OR(LEFT(TRIM(L57),3)="Yes",TRIM(L57)="Y",L57="Frozen Rate",L57="Frozen Plan",L57="Not able to Compare",L57="Info Not Avail",L57="NA",L57="")),2,IF(AND(N57<>"No",N57<>""),3,4)))) -> 99
A58: 45902 | B58: Tighe | C58: Paul | D58: Litchfield Park | E58: 85340 | F58: Opposed | G58: https://images.edocket.azcc.gov/docketpdf/E000046155.pdf | H58: 9937021000 | I58: R3-47 | J58: No | K58: No | L58: Yes | M58: No | N58: No | O58: Yes | P58: N | Q58: 45968 | R58: 0 | S58: 0 | T58: 0 | U58: 0 | V58: =IF(OR(LEFT(TRIM(L58),3)="Yes",TRIM(L58)="Y"),"✅ On Best Plan",IF(OR(L58="Frozen Rate",L58="Frozen Plan"),"❄ Frozen Rate",IF(OR(L58="Not able to Compare",L58="Info Not Avail",L58="NA",L58=""),"⚠ Unknown","❌ Not on Best Plan"))) -> ✅ On Best Plan | W58: =IFERROR(_xlfn.XLOOKUP(TEXT(H58,"0000000000"),'📞 Call Tracker'!A$2:A$2000,'📞 Call Tracker'!B$2:B$2000,""),"") -> 0 | X58: =IFERROR(_xlfn.XLOOKUP(TEXT(H58,"0000000000"),'📞 Call Tracker'!A$2:A$2000,'📞 Call Tracker'!C$2:C$2000,""),"") -> 0 | Y58: =IFERROR(_xlfn.XLOOKUP(TEXT(H58,"0000000000"),'📞 Call Tracker'!A$2:A$2000,'📞 Call Tracker'!D$2:D$2000,""),"") -> 0 | Z58: =IFERROR(_xlfn.XLOOKUP(TEXT(H58,"0000000000"),'📞 Call Tracker'!A$2:A$2000,'📞 Call Tracker'!E$2:E$2000,""),"") -> 0 | AA58: =IFERROR(_xlfn.XLOOKUP(TEXT(H58,"0000000000"),'📞 Call Tracker'!A$2:A$2000,'📞 Call Tracker'!F$2:F$2000,""),"") -> 0 | AB58: =IF(OR(H58="",X58<>""),99,IF(AND(NOT(OR(LEFT(TRIM(L58),3)="Yes",TRIM(L58)="Y",L58="Frozen Rate",L58="Frozen Plan",L58="Not able to Compare",L58="Info Not Avail",L58="NA",L58="")),AND(N58<>"No",N58<>"")),1,IF(NOT(OR(LEFT(TRIM(L58),3)="Yes",TRIM(L58)="Y",L58="Frozen Rate",L58="Frozen Plan",L58="Not able to Compare",L58="Info Not Avail",L58="NA",L58="")),2,IF(AND(N58<>"No",N58<>""),3,4)))) -> 99
A59: 45902 | B59: Ward | C59: Karen | D59: Surprise | E59: 85387 | F59: Opposed | G59: https://images.edocket.azcc.gov/docketpdf/E000046155.pdf | H59: 7949496672 | I59: R-XS | J59: Yes | K59: No | L59: Yes | M59: No | N59: No | O59: Yes | P59: N | Q59: 45968 | R59: 0 | S59: 0 | T59: 0 | U59: 0 | V59: =IF(OR(LEFT(TRIM(L59),3)="Yes",TRIM(L59)="Y"),"✅ On Best Plan",IF(OR(L59="Frozen Rate",L59="Frozen Plan"),"❄ Frozen Rate",IF(OR(L59="Not able to Compare",L59="Info Not Avail",L59="NA",L59=""),"⚠ Unknown","❌ Not on Best Plan"))) -> ✅ On Best Plan | W59: =IFERROR(_xlfn.XLOOKUP(TEXT(H59,"0000000000"),'📞 Call Tracker'!A$2:A$2000,'📞 Call Tracker'!B$2:B$2000,""),"") -> Michelle | X59: =IFERROR(_xlfn.XLOOKUP(TEXT(H59,"0000000000"),'📞 Call Tracker'!A$2:A$2000,'📞 Call Tracker'!C$2:C$2000,""),"") -> 46067 | Y59: =IFERROR(_xlfn.XLOOKUP(TEXT(H59,"0000000000"),'📞 Call Tracker'!A$2:A$2000,'📞 Call Tracker'!D$2:D$2000,""),"") -> YES | Z59: =IFERROR(_xlfn.XLOOKUP(TEXT(H59,"0000000000"),'📞 Call Tracker'!A$2:A$2000,'📞 Call Tracker'!E$2:E$2000,""),"") -> 0 | AA59: =IFERROR(_xlfn.XLOOKUP(TEXT(H59,"0000000000"),'📞 Call Tracker'!A$2:A$2000,'📞 Call Tracker'!F$2:F$2000,""),"") -> 0 | AB59: =IF(OR(H59="",X59<>""),99,IF(AND(NOT(OR(LEFT(TRIM(L59),3)="Yes",TRIM(L59)="Y",L59="Frozen Rate",L59="Frozen Plan",L59="Not able to Compare",L59="Info Not Avail",L59="NA",L59="")),AND(N59<>"No",N59<>"")),1,IF(NOT(OR(LEFT(TRIM(L59),3)="Yes",TRIM(L59)="Y",L59="Frozen Rate",L59="Frozen Plan",L59="Not able to Compare",L59="Info Not Avail",L59="NA",L59="")),2,IF(AND(N59<>"No",N59<>""),3,4)))) -> 99
A60: 45902 | B60: Nash | C60: Destiny | D60: Chandler | E60: 85225 | F60: Opposed | G60: https://images.edocket.azcc.gov/docketpdf/E000046155.pdf | H60: 8712521000 | I60: R3-47 | J60: No | K60: No | L60: Yes | M60: No | N60: No | O60: Yes | P60: N | Q60: 45968 | R60: 0 | S60: 0 | T60: 0 | U60: 0 | V60: =IF(OR(LEFT(TRIM(L60),3)="Yes",TRIM(L60)="Y"),"✅ On Best Plan",IF(OR(L60="Frozen Rate",L60="Frozen Plan"),"❄ Frozen Rate",IF(OR(L60="Not able to Compare",L60="Info Not Avail",L60="NA",L60=""),"⚠ Unknown","❌ Not on Best Plan"))) -> ✅ On Best Plan | W60: =IFERROR(_xlfn.XLOOKUP(TEXT(H60,"0000000000"),'📞 Call Tracker'!A$2:A$2000,'📞 Call Tracker'!B$2:B$2000,""),"") -> 0 | X60: =IFERROR(_xlfn.XLOOKUP(TEXT(H60,"0000000000"),'📞 Call Tracker'!A$2:A$2000,'📞 Call Tracker'!C$2:C$2000,""),"") -> 0 | Y60: =IFERROR(_xlfn.XLOOKUP(TEXT(H60,"0000000000"),'📞 Call Tracker'!A$2:A$2000,'📞 Call Tracker'!D$2:D$2000,""),"") -> 0 | Z60: =IFERROR(_xlfn.XLOOKUP(TEXT(H60,"0000000000"),'📞 Call Tracker'!A$2:A$2000,'📞 Call Tracker'!E$2:E$2000,""),"") -> 0 | AA60: =IFERROR(_xlfn.XLOOKUP(TEXT(H60,"0000000000"),'📞 Call Tracker'!A$2:A$2000,'📞 Call Tracker'!F$2:F$2000,""),"") -> 0 | AB60: =IF(OR(H60="",X60<>""),99,IF(AND(NOT(OR(LEFT(TRIM(L60),3)="Yes",TRIM(L60)="Y",L60="Frozen Rate",L60="Frozen Plan",L60="Not able to Compare",L60="Info Not Avail",L60="NA",L60="")),AND(N60<>"No",N60<>"")),1,IF(NOT(OR(LEFT(TRIM(L60),3)="Yes",TRIM(L60)="Y",L60="Frozen Rate",L60="Frozen Plan",L60="Not able to Compare",L60="Info Not Avail",L60="NA",L60="")),2,IF(AND(N60<>"No",N60<>""),3,4)))) -> 99
A61: 45902 | B61: Wilkymacky | C61: Abby | D61: Phoenix | E61: 85006 | F61: Opposed | G61: https://images.edocket.azcc.gov/docketpdf/E000046155.pdf | H61: 2584149193 | I61: RTOUE47 | J61: No | K61: No | L61: Yes | M61: No | N61: No | O61: Yes | P61: N | Q61: 45968 | R61: 0 | S61: 0 | T61: 0 | U61: 0 | V61: =IF(OR(LEFT(TRIM(L61),3)="Yes",TRIM(L61)="Y"),"✅ On Best Plan",IF(OR(L61="Frozen Rate",L61="Frozen Plan"),"❄ Frozen Rate",IF(OR(L61="Not able to Compare",L61="Info Not Avail",L61="NA",L61=""),"⚠ Unknown","❌ Not on Best Plan"))) -> ✅ On Best Plan | W61: =IFERROR(_xlfn.XLOOKUP(TEXT(H61,"0000000000"),'📞 Call Tracker'!A$2:A$2000,'📞 Call Tracker'!B$2:B$2000,""),"") -> Michelle | X61: =IFERROR(_xlfn.XLOOKUP(TEXT(H61,"0000000000"),'📞 Call Tracker'!A$2:A$2000,'📞 Call Tracker'!C$2:C$2000,""),"") -> 46067 | Y61: =IFERROR(_xlfn.XLOOKUP(TEXT(H61,"0000000000"),'📞 Call Tracker'!A$2:A$2000,'📞 Call Tracker'!D$2:D$2000,""),"") -> YES | Z61: =IFERROR(_xlfn.XLOOKUP(TEXT(H61,"0000000000"),'📞 Call Tracker'!A$2:A$2000,'📞 Call Tracker'!E$2:E$2000,""),"") -> 0 | AA61: =IFERROR(_xlfn.XLOOKUP(TEXT(H61,"0000000000"),'📞 Call Tracker'!A$2:A$2000,'📞 Call Tracker'!F$2:F$2000,""),"") -> 0 | AB61: =IF(OR(H61="",X61<>""),99,IF(AND(NOT(OR(LEFT(TRIM(L61),3)="Yes",TRIM(L61)="Y",L61="Frozen Rate",L61="Frozen Plan",L61="Not able to Compare",L61="Info Not Avail",L61="NA",L61="")),AND(N61<>"No",N61<>"")),1,IF(NOT(OR(LEFT(TRIM(L61),3)="Yes",TRIM(L61)="Y",L61="Frozen Rate",L61="Frozen Plan",L61="Not able to Compare",L61="Info Not Avail",L61="NA",L61="")),2,IF(AND(N61<>"No",N61<>""),3,4)))) -> 99
A62: 45902 | B62: Melendez | C62: Jose | D62: Surprise | E62: 85388 | F62: Opposed | G62: https://images.edocket.azcc.gov/docketpdf/E000046155.pdf | H62: 3811821000 | I62: RTOUE47 | J62: No | K62: No | L62: No MEP R3-47 ($128.91) | M62: No | N62: No | O62: Yes | P62: 45932 | Q62: 45968 | R62: 10/02 - LM | S62: 0 | T62: 0 | U62: 0 | V62: =IF(OR(LEFT(TRIM(L62),3)="Yes",TRIM(L62)="Y"),"✅ On Best Plan",IF(OR(L62="Frozen Rate",L62="Frozen Plan"),"❄ Frozen Rate",IF(OR(L62="Not able to Compare",L62="Info Not Avail",L62="NA",L62=""),"⚠ Unknown","❌ Not on Best Plan"))) -> ❌ Not on Best Plan | W62: =IFERROR(_xlfn.XLOOKUP(TEXT(H62,"0000000000"),'📞 Call Tracker'!A$2:A$2000,'📞 Call Tracker'!B$2:B$2000,""),"") -> Joaquin | X62: =IFERROR(_xlfn.XLOOKUP(TEXT(H62,"0000000000"),'📞 Call Tracker'!A$2:A$2000,'📞 Call Tracker'!C$2:C$2000,""),"") -> 46011 | Y62: =IFERROR(_xlfn.XLOOKUP(TEXT(H62,"0000000000"),'📞 Call Tracker'!A$2:A$2000,'📞 Call Tracker'!D$2:D$2000,""),"") -> YES | Z62: =IFERROR(_xlfn.XLOOKUP(TEXT(H62,"0000000000"),'📞 Call Tracker'!A$2:A$2000,'📞 Call Tracker'!E$2:E$2000,""),"") -> 0 | AA62: =IFERROR(_xlfn.XLOOKUP(TEXT(H62,"0000000000"),'📞 Call Tracker'!A$2:A$2000,'📞 Call Tracker'!F$2:F$2000,""),"") -> VOICE MESSAGE | AB62: =IF(OR(H62="",X62<>""),99,IF(AND(NOT(OR(LEFT(TRIM(L62),3)="Yes",TRIM(L62)="Y",L62="Frozen Rate",L62="Frozen Plan",L62="Not able to Compare",L62="Info Not Avail",L62="NA",L62="")),AND(N62<>"No",N62<>"")),1,IF(NOT(OR(LEFT(TRIM(L62),3)="Yes",TRIM(L62)="Y",L62="Frozen Rate",L62="Frozen Plan",L62="Not able to Compare",L62="Info Not Avail",L62="NA",L62="")),2,IF(AND(N62<>"No",N62<>""),3,4)))) -> 99
A63: 45902 | B63: Crosbie | C63: David | D63: Goodyear | E63: 85338 | F63: Opposed | G63: https://images.edocket.azcc.gov/docketpdf/E000046155.pdf | H63: 0814350000 | I63: RTOUE47 | J63: No | K63: No | L63: Yes | M63: No | N63: No | O63: Yes | P63: N | Q63: 45968 | R63: 0 | S63: 0 | T63: 0 | U63: 0 | V63: =IF(OR(LEFT(TRIM(L63),3)="Yes",TRIM(L63)="Y"),"✅ On Best Plan",IF(OR(L63="Frozen Rate",L63="Frozen Plan"),"❄ Frozen Rate",IF(OR(L63="Not able to Compare",L63="Info Not Avail",L63="NA",L63=""),"⚠ Unknown","❌ Not on Best Plan"))) -> ✅ On Best Plan | W63: =IFERROR(_xlfn.XLOOKUP(TEXT(H63,"0000000000"),'📞 Call Tracker'!A$2:A$2000,'📞 Call Tracker'!B$2:B$2000,""),"") -> Michelle | X63: =IFERROR(_xlfn.XLOOKUP(TEXT(H63,"0000000000"),'📞 Call Tracker'!A$2:A$2000,'📞 Call Tracker'!C$2:C$2000,""),"") -> 46067 | Y63: =IFERROR(_xlfn.XLOOKUP(TEXT(H63,"0000000000"),'📞 Call Tracker'!A$2:A$2000,'📞 Call Tracker'!D$2:D$2000,""),"") -> YES | Z63: =IFERROR(_xlfn.XLOOKUP(TEXT(H63,"0000000000"),'📞 Call Tracker'!A$2:A$2000,'📞 Call Tracker'!E$2:E$2000,""),"") -> 0 | AA63: =IFERROR(_xlfn.XLOOKUP(TEXT(H63,"0000000000"),'📞 Call Tracker'!A$2:A$2000,'📞 Call Tracker'!F$2:F$2000,""),"") -> SOLAR ACCT | AB63: =IF(OR(H63="",X63<>""),99,IF(AND(NOT(OR(LEFT(TRIM(L63),3)="Yes",TRIM(L63)="Y",L63="Frozen Rate",L63="Frozen Plan",L63="Not able to Compare",L63="Info Not Avail",L63="NA",L63="")),AND(N63<>"No",N63<>"")),1,IF(NOT(OR(LEFT(TRIM(L63),3)="Yes",TRIM(L63)="Y",L63="Frozen Rate",L63="Frozen Plan",L63="Not able to Compare",L63="Info Not Avail",L63="NA",L63="")),2,IF(AND(N63<>"No",N63<>""),3,4)))) -> 99
A64: 45902 | B64: Tolinos | C64: Jacinta | D64: Phoenix | E64: 85023 | F64: Opposed | G64: https://images.edocket.azcc.gov/docketpdf/E000046155.pdf | H64: 0050340630 | I64: R-BASIC | J64: No | K64: No | L64: Yes | M64: No | N64: No | O64: Yes | P64: N | Q64: 45968 | R64: 0 | S64: 0 | T64: 0 | U64: 0 | V64: =IF(OR(LEFT(TRIM(L64),3)="Yes",TRIM(L64)="Y"),"✅ On Best Plan",IF(OR(L64="Frozen Rate",L64="Frozen Plan"),"❄ Frozen Rate",IF(OR(L64="Not able to Compare",L64="Info Not Avail",L64="NA",L64=""),"⚠ Unknown","❌ Not on Best Plan"))) -> ✅ On Best Plan | W64: =IFERROR(_xlfn.XLOOKUP(TEXT(H64,"0000000000"),'📞 Call Tracker'!A$2:A$2000,'📞 Call Tracker'!B$2:B$2000,""),"") -> Michelle | X64: =IFERROR(_xlfn.XLOOKUP(TEXT(H64,"0000000000"),'📞 Call Tracker'!A$2:A$2000,'📞 Call Tracker'!C$2:C$2000,""),"") -> 45997 | Y64: =IFERROR(_xlfn.XLOOKUP(TEXT(H64,"0000000000"),'📞 Call Tracker'!A$2:A$2000,'📞 Call Tracker'!D$2:D$2000,""),"") -> YES | Z64: =IFERROR(_xlfn.XLOOKUP(TEXT(H64,"0000000000"),'📞 Call Tracker'!A$2:A$2000,'📞 Call Tracker'!E$2:E$2000,""),"") -> 0 | AA64: =IFERROR(_xlfn.XLOOKUP(TEXT(H64,"0000000000"),'📞 Call Tracker'!A$2:A$2000,'📞 Call Tracker'!F$2:F$2000,""),"") -> 0 | AB64: =IF(OR(H64="",X64<>""),99,IF(AND(NOT(OR(LEFT(TRIM(L64),3)="Yes",TRIM(L64)="Y",L64="Frozen Rate",L64="Frozen Plan",L64="Not able to Compare",L64="Info Not Avail",L64="NA",L64="")),AND(N64<>"No",N64<>"")),1,IF(NOT(OR(LEFT(TRIM(L64),3)="Yes",TRIM(L64)="Y",L64="Frozen Rate",L64="Frozen Plan",L64="Not able to Compare",L64="Info Not Avail",L64="NA",L64="")),2,IF(AND(N64<>"No",N64<>""),3,4)))) -> 99
A65: 45902 | B65: Findley | C65: Moses | D65: Goodyear | E65: 85338 | F65: Opposed | G65: https://images.edocket.azcc.gov/docketpdf/E000046155.pdf | H65: 7949331000 | I65: EPR-6w/E-12 | J65: Yes | K65: No | L65: Frozen Rate | M65: Yes | N65: 326.87 | O65: Yes | P65: N | Q65: 45968 | R65: COR has spoken to CX several times in the last few weeks and been advised of assitance options and extended PA | S65: 0 | T65: 0 | U65: 0 | V65: =IF(OR(LEFT(TRIM(L65),3)="Yes",TRIM(L65)="Y"),"✅ On Best Plan",IF(OR(L65="Frozen Rate",L65="Frozen Plan"),"❄ Frozen Rate",IF(OR(L65="Not able to Compare",L65="Info Not Avail",L65="NA",L65=""),"⚠ Unknown","❌ Not on Best Plan"))) -> ❄ Frozen Rate | W65: =IFERROR(_xlfn.XLOOKUP(TEXT(H65,"0000000000"),'📞 Call Tracker'!A$2:A$2000,'📞 Call Tracker'!B$2:B$2000,""),"") -> Michelle | X65: =IFERROR(_xlfn.XLOOKUP(TEXT(H65,"0000000000"),'📞 Call Tracker'!A$2:A$2000,'📞 Call Tracker'!C$2:C$2000,""),"") -> 46032 | Y65: =IFERROR(_xlfn.XLOOKUP(TEXT(H65,"0000000000"),'📞 Call Tracker'!A$2:A$2000,'📞 Call Tracker'!D$2:D$2000,""),"") -> YES | Z65: =IFERROR(_xlfn.XLOOKUP(TEXT(H65,"0000000000"),'📞 Call Tracker'!A$2:A$2000,'📞 Call Tracker'!E$2:E$2000,""),"") -> 0 | AA65: =IFERROR(_xlfn.XLOOKUP(TEXT(H65,"0000000000"),'📞 Call Tracker'!A$2:A$2000,'📞 Call Tracker'!F$2:F$2000,""),"") -> SOLAR ACCT | AB65: =IF(OR(H65="",X65<>""),99,IF(AND(NOT(OR(LEFT(TRIM(L65),3)="Yes",TRIM(L65)="Y",L65="Frozen Rate",L65="Frozen Plan",L65="Not able to Compare",L65="Info Not Avail",L65="NA",L65="")),AND(N65<>"No",N65<>"")),1,IF(NOT(OR(LEFT(TRIM(L65),3)="Yes",TRIM(L65)="Y",L65="Frozen Rate",L65="Frozen Plan",L65="Not able to Compare",L65="Info Not Avail",L65="NA",L65="")),2,IF(AND(N65<>"No",N65<>""),3,4)))) -> 99
A66: 45902 | B66: Schmidt | C66: Bryan | D66: Goodyear | E66: 85338 | F66: Opposed | G66: https://images.edocket.azcc.gov/docketpdf/E000046155.pdf | H66: 4676231000 | I66: R3-47 | J66: No | K66: No | L66: Yes | M66: No | N66: No | O66: Yes | P66: N | Q66: 45968 | R66: 0 | S66: 0 | T66: 0 | U66: 0 | V66: =IF(OR(LEFT(TRIM(L66),3)="Yes",TRIM(L66)="Y"),"✅ On Best Plan",IF(OR(L66="Frozen Rate",L66="Frozen Plan"),"❄ Frozen Rate",IF(OR(L66="Not able to Compare",L66="Info Not Avail",L66="NA",L66=""),"⚠ Unknown","❌ Not on Best Plan"))) -> ✅ On Best Plan | W66: =IFERROR(_xlfn.XLOOKUP(TEXT(H66,"0000000000"),'📞 Call Tracker'!A$2:A$2000,'📞 Call Tracker'!B$2:B$2000,""),"") -> 0 | X66: =IFERROR(_xlfn.XLOOKUP(TEXT(H66,"0000000000"),'📞 Call Tracker'!A$2:A$2000,'📞 Call Tracker'!C$2:C$2000,""),"") -> 0 | Y66: =IFERROR(_xlfn.XLOOKUP(TEXT(H66,"0000000000"),'📞 Call Tracker'!A$2:A$2000,'📞 Call Tracker'!D$2:D$2000,""),"") -> 0 | Z66: =IFERROR(_xlfn.XLOOKUP(TEXT(H66,"0000000000"),'📞 Call Tracker'!A$2:A$2000,'📞 Call Tracker'!E$2:E$2000,""),"") -> 0 | AA66: =IFERROR(_xlfn.XLOOKUP(TEXT(H66,"0000000000"),'📞 Call Tracker'!A$2:A$2000,'📞 Call Tracker'!F$2:F$2000,""),"") -> 0 | AB66: =IF(OR(H66="",X66<>""),99,IF(AND(NOT(OR(LEFT(TRIM(L66),3)="Yes",TRIM(L66)="Y",L66="Frozen Rate",L66="Frozen Plan",L66="Not able to Compare",L66="Info Not Avail",L66="NA",L66="")),AND(N66<>"No",N66<>"")),1,IF(NOT(OR(LEFT(TRIM(L66),3)="Yes",TRIM(L66)="Y",L66="Frozen Rate",L66="Frozen Plan",L66="Not able to Compare",L66="Info Not Avail",L66="NA",L66="")),2,IF(AND(N66<>"No",N66<>""),3,4)))) -> 99
